Workbook

Sheet RECAP
P1: ALT COINS | AU1: PRIX | AV1: lien | AW1: Crypto Prices
B2: PAIR | C2: $BTC* | D2: $ETH | E2: $TON | F2: $SOL* | G2: $TAO* | H2: ALT | I2: USDC | P2: $RON | Q2: $LINK | R2: $DOGE | S2: $SHIB | T2: $CAKE | U2: $JUP | V2: $AAVE | W2: $CKB | X2: $PENDLE | Y2: $BOME | Z2: $PEPE | AA2: $WIF | AB2: $RAY | AT2: $BTC | AU2: 67500 | AV2: https://cryptoprices.cc/BTC/ | AW2: =IFERROR(__xludf.DUMMYFUNCTION("IMPORTDATA(AV2)"),67315.0) -> 67315
A3: PF at | B3: 46071 | C3: =C4*C6 -> 24971.317 | D3: =D4*D6 -> 3517.6425 | E3: =E4*E6 -> 0.0020019876 | F3: =F4*F6 -> 0 | G3: =G4*G6 -> 0 | H3: =SUM(P3:AA3) -> -0.0024058335 | I3: =I4*I6 -> 10332.394 | P3: =P4*P6 -> 0 | Q3: =Q4*Q6 -> 0 | R3: =R4*R6 -> -0.0041718684 | S3: =S4*S6 -> -1.2644183e-07 | T3: =T4*T6 -> 0 | U3: =U4*U6 -> 0 | V3: =V4*V6 -> 0 | W3: =W4*W6 -> 0 | ... AB3: =AB4*AB6 -> 0 | AT3: $ETH | AU3: 1950 | AV3: https://cryptoprices.cc/ETH/ | AW3: =IFERROR(__xludf.DUMMYFUNCTION("IMPORTDATA(AV3)"),"1972.35") -> 1972.35
A4: QTY at | B4: =ARBITRAGES!E268 -> 46066 | C4: =VLOOKUP($B$4,'QUANTITE DETENUES'!1:999,2,FALSE) -> 0.36994544 | D4: =VLOOKUP($B$4,'QUANTITE DETENUES'!1:999,3,FALSE) -> 1.8039192 | E4: =VLOOKUP($B$4,'QUANTITE DETENUES'!1:999,4,FALSE) -> 0.0013902692 | F4: =VLOOKUP($B$4,'QUANTITE DETENUES'!1:999,5,FALSE) -> 0 | G4: =VLOOKUP($B$4,'QUANTITE DETENUES'!1:999,6,FALSE) -> 0 | H4: - | I4: =VLOOKUP(B4,PRIX!1:998,20) -> 10332.394 | P4: =VLOOKUP($B$4,'QUANTITE DETENUES'!1:999,7,FALSE) -> 0 | Q4: =VLOOKUP($B$4,'QUANTITE DETENUES'!1:999,8,FALSE) -> 0 | R4: =VLOOKUP($B$4,'QUANTITE DETENUES'!1:999,9,FALSE) -> -0.041760444 | S4: =VLOOKUP($B$4,'QUANTITE DETENUES'!1:999,10,FALSE) -> -0.01945259 | T4: =VLOOKUP($B$4,'QUANTITE DETENUES'!1:999,11,FALSE) -> 0 | U4: =VLOOKUP($B$4,'QUANTITE DETENUES'!1:999,12,FALSE) -> 0 | V4: =VLOOKUP($B$4,'QUANTITE DETENUES'!1:999,13,FALSE) -> 0 | W4: =VLOOKUP($B$4,'QUANTITE DETENUES'!1:999,14,FALSE) -> 0 | X4: =VLOOKUP($B$4,'QUANTITE DETENUES'!1:999,15,FALSE) -> 0.0014612915 | Y4: =VLOOKUP($B$4,'QUANTITE DETENUES'!1:999,16,FALSE) -> 0.028919892 | Z4: =VLOOKUP($B$4,'QUANTITE DETENUES'!1:999,17,FALSE) -> 0.039999998 | AA4: =VLOOKUP($B$4,'QUANTITE DETENUES'!1:999,18,FALSE) -> 0 | AB4: =VLOOKUP($B$4,'QUANTITE DETENUES'!1:999,19,FALSE) -> 0 | AT4: $TON | AU4: 1.44 | AV4: https://cryptoprices.cc/TON/ | AW4: =IFERROR(__xludf.DUMMYFUNCTION("IMPORTDATA(AV4)"),"1.44") -> 1.44
B5: Pondération (%) | C5: =C3/$K$11 -> 0.64323665 | D5: =D3/$K$11 -> 0.090611023 | E5: =E3/$K$11 -> 5.1569239e-08 | F5: =F3/$K$11 -> 0 | G5: =G3/$K$11 -> 0 | H5: =H3/$K$11 -> -6.1971914e-08 | I5: =I3/$K$11 -> 0.26615234 | P5: =P3/$K$11 -> 0 | Q5: =Q3/$K$11 -> 0 | R5: =R3/$K$11 -> -1.0746324e-07 | S5: =S3/$K$11 -> 0 | T5: =T3/$K$11 -> 0 | U5: =U3/$K$11 -> 0 | V5: =V3/$K$11 -> 0 | W5: =W3/$K$11 -> 0 | ... AB5: =AB3/$K$11 -> 0 | AT5: $SOL | AU5: 83 | AV5: https://cryptoprices.cc/SOL/ | AW5: =IFERROR(__xludf.DUMMYFUNCTION("IMPORTDATA(AV5)"),"82.69") -> 82.69
B6: PRIX ACTUELS | C6: =AU2 -> 67500 | D6: =AU3 -> 1950 | E6: =AU4 -> 1.44 | F6: =AU5 -> 83 | G6: =AU6 -> 190 | H6: - | I6: 1 | P6: =AU7 -> 0.096 | Q6: =AU8 -> 8.7 | R6: =AU9 -> 0.0999 | S6: =AU10 -> 6.5e-06 | T6: =AU11 -> 1.3 | U6: =AU12 -> 0.157 | V6: =AU13 -> 125 | W6: =AU14 -> 0.00165 | X6: =AU15 -> 1.2 | Y6: =AU16 -> 0.00043 | Z6: =AU17 -> 4.4e-06 | AA6: =AU18 -> 0.23 | AB6: =AU19 -> 0.6 | AT6: $TAO | AU6: 190 | AV6: https://cryptoprices.cc/TAO/ | AW6: =IFERROR(__xludf.DUMMYFUNCTION("IMPORTDATA(AV6)"),"189.87") -> 189.87
B7: Prix d'entrée | C7: 59283 | D7: 2405 | E7: 6.28 | F7: 141 | G7: 317 | H7: - | I7: - | P7: 1.61 | Q7: 10.95 | R7: 0.10172 | S7: 1.4e-05 | T7: 1.6 | U7: 0.9355 | V7: 172.58 | W7: 0.0111 | X7: 4.29 | Y7: 0.009774 | Z7: 1.78e-05 | AA7: 3.35 | AB7: 6.35 | AT7: $RON | AU7: 0.096 | AV7: https://cryptoprices.cc/RON | AW7: =IFERROR(__xludf.DUMMYFUNCTION("IMPORTDATA(AV7)"),"0.098075") -> 0.098075
B8: PERF (par rapport au PMA) | C8: =(C6-C7)/C7 -> 0.13860635 | D8: =(D6-D7)/D7 -> -0.18918919 | E8: =(E6-E7)/E7 -> -0.77070064 | F8: =(F6-F7)/F7 -> -0.41134752 | G8: =(G6-G7)/G7 -> -0.40063091 | H8: =(P8*P5+Q8*Q5+R8*R5+S8*S5+T8*T5+U8*U5+V8*V5+W5*W8+X5*X8+Y5*Y8+Z5*Z8+AA5*AA8+AB5*AB8)/H5 -> 0.49893536 | P8: =(P6-P7)/P7 -> -0.94037267 | Q8: =(Q6-Q7)/Q7 -> -0.20547945 | R8: =(R6-R7)/R7 -> -0.017892253 | S8: =(S6-S7)/S7 -> -0.53571429 | T8: =(T6-T7)/T7 -> -0.1875 | U8: =(U6-U7)/U7 -> -0.83217531 | V8: =(V6-V7)/V7 -> -0.27569823 | W8: =(W6-W7)/W7 -> -0.85135135 | ... AB8: =(AB6-AB7)/AB7 -> -0.90551181 | AT8: $LINK | AU8: 8.7 | AV8: https://cryptoprices.cc/LINK/ | AW8: =IFERROR(__xludf.DUMMYFUNCTION("IMPORTDATA(AV8)"),"8.71") -> 8.71
I9: AUJOURD'HUI | AT9: $DOGE | AU9: 0.0999 | AV9: https://cryptoprices.cc/DOGE/ | AW9: =IFERROR(__xludf.DUMMYFUNCTION("IMPORTDATA(AV9)"),"0.099931") -> 0.099931
I10: TOTAL INVESTI | K10: PORTFOLLIO | M10: ROI % | N10: ROI $ | AT10: $SHIB | AU10: 6.5e-06 | AV10: https://cryptoprices.cc/SHIB/ | AW10: =IFERROR(__xludf.DUMMYFUNCTION("IMPORTDATA(AV10)"),"6.42e-06") -> 6.42e-06
I11: =VLOOKUP($B$4,BILAN!1:1000,14) -> 37467.522 | K11: =SUM(C3:I3) -> 38821.353 | M11: =(K11-I11)/I11 -> 0.036133457 | N11: =K11-I11 -> 1353.8311 | AT11: $CAKE | AU11: 1.3 | AV11: https://cryptoprices.cc/CAKE/ | AW11: =IFERROR(__xludf.DUMMYFUNCTION("IMPORTDATA(AV11)"),"1.29") -> 1.29
AT12: $JUP | AU12: 0.157 | AV12: https://cryptoprices.cc/JUP/ | AW12: =IFERROR(__xludf.DUMMYFUNCTION("IMPORTDATA(AV12)"),"0.160764") -> 0.160764
AT13: $AAVE | AU13: 125 | AV13: https://cryptoprices.cc/AAVE/ | AW13: =IFERROR(__xludf.DUMMYFUNCTION("IMPORTDATA(AV13)"),"125.79") -> 125.79
AT14: $CKB | AU14: 0.00165 | AV14: https://cryptoprices.cc/CKB/ | AW14: =IFERROR(__xludf.DUMMYFUNCTION("IMPORTDATA(AV14)"),"0.00164314") -> 0.00164314
AT15: $PENDLE | AU15: 1.2 | AV15: https://cryptoprices.cc/PENDLE/ | AW15: =IFERROR(__xludf.DUMMYFUNCTION("IMPORTDATA(AV15)"),"1.22") -> 1.22
AT16: $BOME | AU16: 0.00043 | AV16: https://cryptoprices.cc/BOME/ | AW16: =IFERROR(__xludf.DUMMYFUNCTION("IMPORTDATA(AV16)"),"0.00042636") -> 0.00042636
AT17: $PEPE | AU17: 4.4e-06 | AV17: https://cryptoprices.cc/PEPE/ | AW17: =IFERROR(__xludf.DUMMYFUNCTION("IMPORTDATA(AV17)"),"4.32e-06") -> 4.32e-06
AT18: $WIF | AU18: 0.23 | AV18: https://cryptoprices.cc/WIF/ | AW18: =IFERROR(__xludf.DUMMYFUNCTION("IMPORTDATA(AV18)"),"0.227432") -> 0.227432
J19: Global perf from 11/08 | N19: =IF(M19="","", IF(J19="Invest",#REF!-K19,#REF!+K19)) | AT19: $RAY | AU19: 0.6 | AV19: https://cryptoprices.cc/RAY/ | AW19: =IFERROR(__xludf.DUMMYFUNCTION("IMPORTDATA(AV19)"),"0.661748") -> 0.661748
J20: $BTC | K20: 63000 | L20: =C6 -> 67500 | M20: =(L20-K20)/K20 -> 0.071428571
J21: $ETH | K21: 2650 | L21: =D6 -> 1950 | M21: =(L21-K21)/K21 -> -0.26415094
J22: $TON | K22: 6.666 | L22: =E6 -> 1.44 | M22: =(L22-K22)/K22 -> -0.7839784
J23: $SOL | K23: 155 | L23: =F6 -> 83 | M23: =(L23-K23)/K23 -> -0.46451613
J24: $TAO | K24: 295 | L24: =G6 -> 190 | M24: =(L24-K24)/K24 -> -0.3559322
J25: $RON | K25: 1.55 | L25: =P6 -> 0.096 | M25: =(L25-K25)/K25 -> -0.93806452
J26: $LINK | K26: 10.2 | L26: =Q6 -> 8.7 | M26: =(L26-K26)/K26 -> -0.14705882
J27: $DOGE | K27: 0.1025 | L27: =R6 -> 0.0999 | M27: =(L27-K27)/K27 -> -0.025365854
J28: Sp500 | K28: 5350 | L28: 7000 | M28: =(L28-K28)/K28 -> 0.30841122
J29: Nasdaq 100 | K29: 19000 | L29: 25200 | M29: =(L29-K29)/K29 -> 0.32631579
J30: $$$ | K30: 45515 | L30: Aujourd'hui | M30: Perf
A107: PAIR | B107: $BTC | C107: $ETH | D107: $TON | E107: $SOL | F107: $TAO | G107: $RON | H107: $LINK | I107: $DOGE | J107: $SHIB | K107: $CAKE | L107: $JUP | M107: $AAVE | N107: $CKB | O107: $PENDLE | P107: USDC
A108: =B3 -> 46071 | B108: =C3 -> 24971.317 | C108: =D3 -> 3517.6425 | D108: =E3 -> 0.0020019876 | E108: =F3 -> 0 | F108: =G3 -> 0 | G108: =P3 -> 0 | H108: =Q3 -> 0 | I108: =R3 -> -0.0041718684 | J108: =S3 -> -1.2644183e-07 | K108: =T3 -> 0 | L108: =U3 -> 0 | M108: =V3 -> 0 | N108: =W3 -> 0 | O108: =X3 -> 0.0017535498 | P108: =I3 -> 10332.394

Sheet ARBITRAGES
A1: ARBITRAGES | P1: .
E2: DATE | F2: +/- | G2: $ INJECTED | H2: ACTIF | I2: PRIX ($) | J2: MONTANT ($) | K2: QUANTITE | L2: Frais | M2: Liquidités | N2: Surperf/Sousperf
E3: 45515 | F3: Invest | G3: $21 550,45 | H3: USDC | I3: $ 1,00 | J3: $21 550,44 | K3: 21550 | L3: $1,00 | M3: 21550 | N3: 1
E4: 45515 | F4: Invest | G4: 0 | H4: BTC | I4: $ 58 000,00 | J4: 7500 | K4: 0.12931 | L4: 0 | M4: =IF(E4="","",IF(G4=0,IF(F4="Invest",M3-J4-L4,M3+J4),M3)) -> 14050 | N4: 1
E5: 45516 | F5: Invest | G5: 0 | H5: ETH | I5: $ 2 600,00 | J5: 3000 | K5: 1.1538 | L5: 0 | M5: =IF(E5="","",IF(G5=0,IF(F5="Invest",M4-J5-L5,M4+J5),M4)) -> 11050 | N5: 1
E6: 45517 | F6: Invest | G6: 0 | H6: SOL | I6: $ 145,00 | J6: 1150 | K6: 7.931 | L6: 0 | M6: =IF(E6="","",IF(G6=0,IF(F6="Invest",M5-J6-L6,M5+J6),M5)) -> 9900 | N6: 1
E7: 45518 | F7: Invest | G7: 0 | H7: TAO | I7: 279.2 | J7: 840 | K7: 3 | L7: 0 | M7: =IF(E7="","",IF(G7=0,IF(F7="Invest",M6-J7-L7,M6+J7),M6)) -> 9060 | N7: 1
E8: 45518 | F8: Invest | G8: 0 | H8: RON | I8: 1.54 | J8: 310 | K8: 200 | L8: 0 | M8: =IF(E8="","",IF(G8=0,IF(F8="Invest",M7-J8-L8,M7+J8),M7)) -> 8750 | N8: 1
E9: 45519 | F9: Invest | G9: 0 | H9: TON | I9: 6.48 | J9: 2750 | K9: =IF(J9=0,"",IF(H9="USDC",J9,(J9/I9))) -> 424.38272 | L9: 0 | M9: =IF(E9="","",IF(G9=0,IF(F9="Invest",M8-J9-L9,M8+J9),M8)) -> 6000 | N9: 1
E10: 45522 | F10: Invest | G10: 0 | H10: BTC | I10: 57500 | J10: 1500 | K10: =IF(J10=0,"",IF(H10="USDC",J10,(J10/I10))) -> 0.026086957 | L10: 0 | M10: =IF(E10="","",IF(G10=0,IF(F10="Invest",M9-J10-L10,M9+J10),M9)) -> 4500 | N10: 1
E11: 45527 | F11: Retrait | G11: 0 | H11: TAO | I11: 345 | J11: 345 | K11: =IF(J11=0,"",IF(H11="USDC",J11,(J11/I11))) -> 1 | L11: 0 | M11: =IF(E11="","",IF(G11=0,IF(F11="Invest",M10-J11-L11,M10+J11),M10)) -> 4845 | N11: 1
E12: 45527 | F12: Retrait | G12: 0 | H12: SOL | I12: 155 | J12: 1500 | K12: =IF(J12=0,"",IF(H12="USDC",J12,(J12/I12))) -> 9.6774194 | L12: 0 | M12: =IF(E12="","",IF(G12=0,IF(F12="Invest",M11-J12-L12,M11+J12),M11)) -> 6345 | N12: 1
E13: 45528 | F13: Retrait | G13: 0 | H13: SOL | I13: 157.5 | J13: 1833 | K13: =IF(J13=0,"",IF(H13="USDC",J13,(J13/I13))) -> 11.638095 | L13: 0 | M13: =IF(E13="","",IF(G13=0,IF(F13="Invest",M12-J13-L13,M12+J13),M12)) -> 8178 | N13: 1
E14: 45529 | F14: Invest | G14: 0 | H14: TON | I14: 6 | J14: 500 | K14: =IF(J14=0,"",IF(H14="USDC",J14,(J14/I14))) -> 83.333333 | L14: 0 | M14: =IF(E14="","",IF(G14=0,IF(F14="Invest",M13-J14-L14,M13+J14),M13)) -> 7678 | N14: 0
E15: 45530 | F15: Invest | G15: 0 | H15: BTC | I15: 62100 | J15: 2200 | K15: =IF(J15=0,"",IF(H15="USDC",J15,(J15/I15))) -> 0.035426731 | L15: 0 | M15: =IF(E15="","",IF(G15=0,IF(F15="Invest",M14-J15-L15,M14+J15),M14)) -> 5478 | N15: 1
E16: 45531 | F16: Invest | G16: 0 | H16: RON | I16: 1.65 | J16: 825 | K16: =IF(J16=0,"",IF(H16="USDC",J16,(J16/I16))) -> 500 | L16: 0 | M16: =IF(E16="","",IF(G16=0,IF(F16="Invest",M15-J16-L16,M15+J16),M15)) -> 4653 | N16: 1
E17: 45531 | F17: Invest | G17: 0 | H17: TAO | I17: 330 | J17: 1155 | K17: =IF(J17=0,"",IF(H17="USDC",J17,(J17/I17))) -> 3.5 | L17: 0 | M17: =IF(E17="","",IF(G17=0,IF(F17="Invest",M16-J17-L17,M16+J17),M16)) -> 3498 | N17: 1
E18: 45531 | F18: Invest | G18: 0 | H18: DOGE | I18: 0.102 | J18: 280.5 | K18: =IF(J18=0,"",IF(H18="USDC",J18,(J18/I18))) -> 2750 | L18: 0 | M18: =IF(E18="","",IF(G18=0,IF(F18="Invest",M17-J18-L18,M17+J18),M17)) -> 3217.5 | N18: 1
E19: 45531 | F19: Invest | G19: 0 | H19: LINK | I19: 11 | J19: 1100 | K19: =IF(J19=0,"",IF(H19="USDC",J19,(J19/I19))) -> 100 | L19: 0 | M19: =IF(E19="","",IF(G19=0,IF(F19="Invest",M18-J19-L19,M18+J19),M18)) -> 2117.5 | N19: 1
E20: 45532 | F20: Invest | G20: 0 | H20: BTC | I20: 58800 | J20: 1300 | K20: =IF(J20=0,"",IF(H20="USDC",J20,(J20/I20))) -> 0.022108844 | L20: 0 | M20: =IF(E20="","",IF(G20=0,IF(F20="Invest",M19-J20-L20,M19+J20),M19)) -> 817.5 | N20: 1
... E40: 45609 | F40: Invest | G40: 0 | H40: JUP | I40: 1.1 | J40: 500.5 | K40: =IF(J40=0,"",IF(H40="USDC",J40,(J40/I40))) -> 455 | L40: 0 | M40: =IF(E40="","",IF(G40=0,IF(F40="Invest",M39-J40-L40,M39+J40),M39)) -> 2895.4656 | N40: 0
E41: 45610 | F41: Invest | G41: 0 | H41: BTC | I41: 88000 | J41: 1320 | K41: =IF(J41=0,"",IF(H41="USDC",J41,(J41/I41))) -> 0.015 | L41: 0 | M41: =IF(E41="","",IF(G41=0,IF(F41="Invest",M40-J41-L41+10,M40+J41),M40)) -> 1585.4656 | N41: 1
E42: 45615 | F42: Retrait | G42: 0 | H42: SHIB | I42: 2.6e-05 | J42: 377 | K42: =IF(J42=0,"",IF(H42="USDC",J42,(J42/I42))) -> 14500000 | L42: 0 | M42: =IF(E42="","",IF(G42=0,IF(F42="Invest",M41-J42-L42,M41+J42),M41)) -> 1962.4656 | N42: 0
E43: 45618 | F43: Invest | G43: 0 | H43: PENDLE | I43: 4.8885 | J43: 440 | K43: =IF(J43=0,"",IF(H43="USDC",J43,(J43/I43))) -> 90.00716 | L43: 0 | M43: =IF(E43="","",IF(G43=0,IF(F43="Invest",M42-J43-L43,M42+J43),M42)) -> 1522.4656 | N43: 0
E44: 45619 | F44: Invest | G44: 0 | H44: BOME | I44: 0.009774 | J44: 175.932 | K44: =IF(J44=0,"",IF(H44="USDC",J44,(J44/I44))) -> 18000 | L44: 0 | M44: =IF(E44="","",IF(G44=0,IF(F44="Invest",M43-J44-L44,M43+J44),M43)) -> 1346.5336 | N44: 0
E45: 45622 | F45: Invest | G45: 0 | H45: WIF | I45: 3.35 | J45: 197.65 | K45: =IF(J45=0,"",IF(H45="USDC",J45,(J45/I45))) -> 59 | L45: 0 | M45: =IF(E45="","",IF(G45=0,IF(F45="Invest",M44-J45-L45,M44+J45),M44)) -> 1148.8836 | N45: 0
E46: 45630 | F46: Retrait | G46: 0 | H46: CAKE | I46: 4.33 | J46: 108.31 | K46: =IF(J46=0,"",IF(H46="USDC",J46,(J46/I46))) -> 25.013857 | L46: 0.08 | M46: =IF(E46="","",IF(G46=0,IF(F46="Invest",M45-J46-L46,M45+J46),M45)) -> 1257.1936 | N46: 1
E47: 45636 | F47: Invest | G47: 0 | H47: SOL | I47: 210 | J47: 420 | K47: =IF(J47=0,"",IF(H47="USDC",J47,(J47/I47))) -> 2 | L47: 0 | M47: =IF(E47="","",IF(G47=0,IF(F47="Invest",M46-J47-L47,M46+J47),M46)) -> 837.19364 | N47: 1
E48: 45644 | F48: Invest | G48: 0 | H48: PEPE | I48: 2e-05 | J48: 279 | K48: =IF(J48=0,"",IF(H48="USDC",J48,(J48/I48))) -> 13950000 | L48: 0 | M48: =IF(E48="","",IF(G48=0,IF(F48="Invest",M47-J48-L48,M47+J48),M47)) -> 558.19364 | N48: 1
E49: 45646 | F49: Invest | G49: 0 | H49: PEPE | I49: 1.5e-05 | J49: 150 | K49: =IF(J49=0,"",IF(H49="USDC",J49,(J49/I49))) -> 10000000 | L49: 0 | M49: =IF(E49="","",IF(G49=0,IF(F49="Invest",M48-J49-L49,M48+J49),M48)) -> 408.19364 | N49: 1
E50: 45658 | F50: Invest | G50: 0 | H50: PENDLE | I50: 4.85 | J50: 201.275 | K50: =IF(J50=0,"",IF(H50="USDC",J50,(J50/I50))) -> 41.5 | L50: 0 | M50: =IF(E50="","",IF(G50=0,IF(F50="Invest",M49-J50-L50,M49+J50),M49)) -> 206.91864 | N50: 0
E51: 45666 | F51: Invest | G51: 0 | H51: TAO | I51: 430 | J51: 193.5 | K51: =IF(J51=0,"",IF(H51="USDC",J51,(J51/I51))) -> 0.45 | L51: 0 | M51: =IF(E51="","",IF(G51=0,IF(F51="Invest",M50-J51-L51,M50+J51),M50)) -> 13.418639 | N51: 1
E52: 45676 | F52: Retrait | G52: 0 | H52: SOL | I52: 280 | J52: 280 | K52: =IF(J52=0,"",IF(H52="USDC",J52,(J52/I52))) -> 1 | L52: 0 | M52: =IF(E52="","",IF(G52=0,IF(F52="Invest",M51-J52-L52,M51+J52),M51)) -> 293.41864 | N52: 1
E53: 45677 | F53: Invest | G53: 0 | H53: RAY | I53: 6.35 | J53: 279.4 | K53: =IF(J53=0,"",IF(H53="USDC",J53,(J53/I53))) -> 44 | L53: 0 | M53: =IF(E53="","",IF(G53=0,IF(F53="Invest",M52-J53-L53,M52+J53),M52)) -> 14.018639 | N53: 1
... E72: 45779 | F72: Retrait | G72: 0 | H72: BTC | I72: 97000 | J72: 970 | K72: =IF(J72=0,"",IF(H72="USDC",J72,(J72/I72))) -> 0.01 | L72: 0 | M72: =IF(E72="","",IF(G72=0,IF(F72="Invest",M71-J72-L72,M71+J72),M71)) -> 1571.1596 | N72: 1
E73: 45779 | F73: Retrait | G73: 0 | H73: BTC | I73: 98000 | J73: 980 | K73: 0.01 | L73: 0 | M73: =IF(E73="","",IF(G73=0,IF(F73="Invest",M72-J73-L73,M72+J73),M72)) -> 2551.1596 | N73: 1
E74: 45785 | F74: Retrait | G74: 0 | H74: BTC | I74: 102000 | J74: 1020 | K74: =IF(J74=0,"",IF(H74="USDC",J74,(J74/I74))) -> 0.01 | L74: 0 | M74: =IF(E74="","",IF(G74=0,IF(F74="Invest",M73-J74-L74,M73+J74),M73)) -> 3571.1596 | N74: 1
E75: 45785 | F75: Retrait | G75: 0 | H75: BTC | I75: 102500 | J75: 1266.1487 | K75: =IF(J75=0,"",IF(H75="USDC",J75,(J75/I75))) -> 0.01235267 | L75: 0 | M75: =IF(E75="","",IF(G75=0,IF(F75="Invest",M74-J75-L75,M74+J75),M74)) -> 4837.3083 | N75: 0
E76: 45054 | F76: Retrait | G76: 0 | H76: RON | I76: 0.59 | J76: 222.55174 | K76: =IF(J76=0,"",IF(H76="USDC",J76,(J76/I76))) -> 377.20633 | L76: 0 | M76: =IF(E76="","",IF(G76=0,IF(F76="Invest",M75-J76-L76,M75+J76),M75)) -> 5059.86 | N76: 0
E77: 45786 | F77: Retrait | G77: 0 | H77: TAO | I77: 425 | J77: 425 | K77: =IF(J77=0,"",IF(H77="USDC",J77,(J77/I77))) -> 1 | L77: 0 | M77: =IF(E77="","",IF(G77=0,IF(F77="Invest",M76-J77-L77,M76+J77),M76)) -> 5484.86 | N77: 1
E78: 45789 | F78: Retrait | G78: 0 | H78: TON | I78: 3.25 | J78: 246.75 | K78: =IF(J78=0,"",IF(H78="USDC",J78,(J78/I78))) -> 75.923077 | L78: 0 | M78: =IF(E78="","",IF(G78=0,IF(F78="Invest",M77-J78-L78,M77+J78),M77)) -> 5731.61 | N78: 0
E79: 45790 | F79: Invest | G79: 0 | H79: BTC | I79: 101000 | J79: 1500 | K79: =IF(J79=0,"",IF(H79="USDC",J79,(J79/I79))) -> 0.014851485 | L79: 0 | M79: =IF(E79="","",IF(G79=0,IF(F79="Invest",M78-J79-L79,M78+J79),M78)) -> 4231.61 | N79: 1
E80: 45808 | F80: Invest | G80: 0 | H80: TAO | I80: 380 | J80: 456 | K80: =IF(J80=0,"",IF(H80="USDC",J80,(J80/I80))) -> 1.2 | L80: 0 | M80: =IF(E80="","",IF(G80=0,IF(F80="Invest",M79-J80-L80,M79+J80),M79)) -> 3775.61 | N80: 1
E81: 45817 | F81: Retrait | G81: 0 | H81: BTC | I81: 108500 | J81: 2154.6331 | K81: =IF(J81=0,"",IF(H81="USDC",J81,(J81/I81))) -> 0.01985837 | L81: 0 | M81: =IF(E81="","",IF(G81=0,IF(F81="Invest",M80-J81-L81,M80+J81),M80)) -> 5930.2432 | N81: 1
E82: 45817 | F82: Retrait | G82: 0 | H82: BTC | I82: 110000 | J82: 2750 | K82: =IF(J82=0,"",IF(H82="USDC",J82,(J82/I82))) -> 0.025 | L82: 0 | M82: =IF(E82="","",IF(G82=0,IF(F82="Invest",M81-J82-L82,M81+J82+10),M81)) -> 8690.2432 | N82: 1
E83: 45818 | F83: Invest | G83: 0 | H83: BTC | I83: 109000 | J83: 1300 | K83: =IF(J83=0,"",IF(H83="USDC",J83,(J83/I83))) -> 0.011926605 | L83: 0 | M83: =IF(E83="","",IF(G83=0,IF(F83="Invest",M82-J83-L83,M82+J83),M82)) -> 7390.2432 | N83: 1
E84: 45831 | F84: Invest | G84: 0 | H84: AAVE | I84: 225 | J84: 300 | K84: =IF(J84=0,"",IF(H84="USDC",J84,(J84/I84))) -> 1.3333333 | L84: 0 | M84: =IF(E84="","",IF(G84=0,IF(F84="Invest",M83-J84-L84-99,M83+J84),M83)) -> 6991.2432 | N84: 1
E85: 45831 | F85: Retrait | G85: 0 | H85: JUP | I85: 0.35 | J85: 140 | K85: =IF(J85=0,"",IF(H85="USDC",J85,(J85/I85))) -> 400 | L85: 0 | M85: =IF(E85="","",IF(G85=0,IF(F85="Invest",M84-J85-L85,M84+J85),M84)) -> 7131.2432 | N85: 0
E86: 45831 | F86: Retrait | G86: 0 | H86: CKB | I86: 0.0032 | J86: 128 | K86: =IF(J86=0,"",IF(H86="USDC",J86,(J86/I86))) -> 40000 | L86: 0 | M86: =IF(E86="","",IF(G86=0,IF(F86="Invest",M85-J86-L86,M85+J86),M85)) -> 7259.2432 | N86: 0
E87: 45831 | F87: Retrait | G87: 0 | H87: RAY | I87: 1.9 | J87: 83.55 | K87: =IF(J87=0,"",IF(H87="USDC",J87,(J87/I87))) -> 43.973684 | L87: 0 | M87: =IF(E87="","",IF(G87=0,IF(F87="Invest",M86-J87-L87,M86+J87),M86)) -> 7342.7932 | N87: 0
E88: 45831 | F88: Retrait | G88: 0 | H88: CKB | I88: 0.0033 | J88: 111.49304 | K88: =IF(J88=0,"",IF(H88="USDC",J88,(J88/I88))) -> 33785.77 | L88: 0 | M88: =IF(E88="","",IF(G88=0,IF(F88="Invest",M87-J88-L88,M87+J88),M87)) -> 7454.2862 | N88: 0
E89: 45832 | F89: Retrait | G89: 0 | H89: JUP | I89: 0.375 | J89: 159.37524 | K89: =IF(J89=0,"",IF(H89="USDC",J89,(J89/I89))) -> 425.00064 | L89: 0 | M89: =IF(E89="","",IF(G89=0,IF(F89="Invest",M88-J89-L89,M88+J89),M88)) -> 7613.6615 | N89: 0
E90: 45847 | F90: Invest | G90: 0 | H90: SOL | I90: 149 | J90: 298 | K90: =IF(J90=0,"",IF(H90="USDC",J90,(J90/I90))) -> 2 | L90: 0 | M90: =IF(E90="","",IF(G90=0,IF(F90="Invest",M89-J90-L90,M89+J90),M89)) -> 7315.6615 | N90: 1
E91: 45848 | F91: Retrait | G91: 0 | H91: TON | I91: 2.85 | J91: 370 | K91: =IF(J91=0,"",IF(H91="USDC",J91,(J91/I91))) -> 129.82456 | L91: 0 | M91: =IF(E91="","",IF(G91=0,IF(F91="Invest",M90-J91-L91,M90+J91),M90)) -> 7685.6615 | N91: 0
E92: 45849 | F92: Retrait | G92: 0 | H92: BTC | I92: 118170 | J92: 473.9999 | K92: =IF(J92=0,"",IF(H92="USDC",J92,(J92/I92))) -> 0.0040111695 | L92: 0 | M92: =IF(E92="","",IF(G92=0,IF(F92="Invest",M91-J92-L92,M91+J92),M91)) -> 8159.6614 | N92: 1
E93: 45849 | F93: Retrait | G93: 0 | H93: BTC | I93: 118500 | J93: 500.00009 | K93: =IF(J93=0,"",IF(H93="USDC",J93,(J93/I93))) -> 0.00421941 | L93: 0 | M93: =IF(E93="","",IF(G93=0,IF(F93="Invest",M92-J93-L93,M92+J93),M92)) -> 8659.6615 | N93: 1
E94: 45850 | F94: Retrait | G94: 0 | H94: BTC | I94: 118850 | J94: 329.14557 | K94: =IF(J94=0,"",IF(H94="USDC",J94,(J94/I94))) -> 0.00276942 | L94: 0 | M94: =IF(E94="","",IF(G94=0,IF(F94="Invest",M93-J94-L94,M93+J94),M93)) -> 8988.807 | N94: 1
E95: 45852 | F95: Invest | G95: 0 | H95: BTC | I95: 121000 | J95: 1000 | K95: =IF(J95=0,"",IF(H95="USDC",J95,(J95/I95))) -> 0.0082644628 | L95: 0 | M95: =IF(E95="","",IF(G95=0,IF(F95="Invest",M94-J95-L95,M94+J95),M94)) -> 7988.807 | N95: 0
E96: 45852 | F96: Invest | G96: 0 | H96: DOGE | I96: 0.195 | J96: 199.875 | K96: =IF(J96=0,"",IF(H96="USDC",J96,(J96/I96))) -> 1025 | L96: 0 | M96: =IF(E96="","",IF(G96=0,IF(F96="Invest",M95-J96-L96,M95+J96),M95)) -> 7788.932 | N96: 1
... E142: 45891 | F142: Retrait | G142: 0 | H142: PENDLE | I142: 6 | J142: 60 | K142: =IF(J142=0,"",IF(H142="USDC",J142,(J142/I142))) -> 10 | L142: 0 | M142: =IF(E142="","",IF(G142=0,IF(F142="Invest",M141-J142-L142,M141+J142),M141)) -> 14753.869 | N142: 1
E143: 45892 | F143: Retrait | G143: 0 | H143: PENDLE | I143: 6.2 | J143: 93 | K143: =IF(J143=0,"",IF(H143="USDC",J143,(J143/I143))) -> 15 | L143: 0 | M143: =IF(E143="","",IF(G143=0,IF(F143="Invest",M142-J143-L143,M142+J143+42),M142)) -> 14888.869 | N143: 1
E144: 45894 | F144: Invest | G144: 0 | H144: DOGE | I144: 0.222 | J144: 222 | K144: =IF(J144=0,"",IF(H144="USDC",J144,(J144/I144))) -> 1000 | L144: 0 | M144: =IF(E144="","",IF(G144=0,IF(F144="Invest",M143-J144-L144,M143+J144),M143)) -> 14666.869 | N144: 0
E145: 45894 | F145: Invest | G145: 0 | H145: ETH | I145: 4444 | J145: 311.08 | K145: =IF(J145=0,"",IF(H145="USDC",J145,(J145/I145))) -> 0.07 | L145: 0 | M145: =IF(E145="","",IF(G145=0,IF(F145="Invest",M144-J145-L145,M144+J145),M144)) -> 14355.789 | N145: 1
E146: 45894 | F146: Invest | G146: 0 | H146: BTC | I146: 110400 | J146: 297.50453 | K146: =IF(J146=0,"",IF(H146="USDC",J146,(J146/I146))) -> 0.0026947874 | L146: 0 | M146: =IF(E146="","",IF(G146=0,IF(F146="Invest",M145-J146-L146,M145+J146),M145)) -> 14058.284 | N146: 1
E147: 45894 | F147: Invest | G147: 0 | H147: TAO | I147: 333 | J147: 499.5 | K147: =IF(J147=0,"",IF(H147="USDC",J147,(J147/I147))) -> 1.5 | L147: 0 | M147: =IF(E147="","",IF(G147=0,IF(F147="Invest",M146-J147-L147,M146+J147),M146)) -> 13558.784 | N147: 1
E148: 45895 | F148: Invest | G148: 0 | H148: BTC | I148: 110000 | J148: 495 | K148: =IF(J148=0,"",IF(H148="USDC",J148,(J148/I148))) -> 0.0045 | L148: 0 | M148: =IF(E148="","",IF(G148=0,IF(F148="Invest",M147-J148-L148,M147+J148),M147)) -> 13063.784 | N148: 1
E149: 45908 | F149: Invest | G149: 0 | H149: ETH | I149: 4350 | J149: 200 | K149: =IF(J149=0,"",IF(H149="USDC",J149,(J149/I149))) -> 0.045977011 | L149: 0 | M149: =IF(E149="","",IF(G149=0,IF(F149="Invest",M148-J149-L149,M148+J149),M148)) -> 12863.784 | N149: 1
E150: 45908 | F150: Invest | G150: 0 | H150: ETH | I150: 4325 | J150: 300 | K150: =IF(J150=0,"",IF(H150="USDC",J150,(J150/I150))) -> 0.069364162 | L150: 0 | M150: =IF(E150="","",IF(G150=0,IF(F150="Invest",M149-J150-L150,M149+J150),M149)) -> 12563.784 | N150: 1
E151: 45909 | F151: Retrait | G151: 0 | H151: SOL | I151: 217 | J151: 235.61497 | K151: =IF(J151=0,"",IF(H151="USDC",J151,(J151/I151))) -> 1.0857833 | L151: 0 | M151: =IF(E151="","",IF(G151=0,IF(F151="Invest",M150-J151-L151,M150+J151),M150)) -> 12799.399 | N151: 1
E152: 45911 | F152: Retrait | G152: 0 | H152: DOGE | I152: 0.25 | J152: 125 | K152: =IF(J152=0,"",IF(H152="USDC",J152,(J152/I152))) -> 500 | L152: 0 | M152: =IF(E152="","",IF(G152=0,IF(F152="Invest",M151-J152-L152,M151+J152),M151)) -> 12924.399 | N152: 1
E153: 45911 | F153: Retrait | G153: 0 | H153: PENDLE | I153: 5.2 | J153: 104 | K153: =IF(J153=0,"",IF(H153="USDC",J153,(J153/I153))) -> 20 | L153: 0 | M153: =IF(E153="","",IF(G153=0,IF(F153="Invest",M152-J153-L153,M152+J153),M152)) -> 13028.399 | N153: 1
E154: 45911 | F154: Retrait | G154: 0 | H154: SOL | I154: 235 | J154: 235 | K154: =IF(J154=0,"",IF(H154="USDC",J154,(J154/I154))) -> 1 | L154: 0 | M154: =IF(E154="","",IF(G154=0,IF(F154="Invest",M153-J154-L154,M153+J154),M153)) -> 13263.399 | N154: 1
E155: 45912 | F155: Retrait | G155: 0 | H155: SOL | I155: 240 | J155: 240 | K155: =IF(J155=0,"",IF(H155="USDC",J155,(J155/I155))) -> 1 | L155: 0 | M155: =IF(E155="","",IF(G155=0,IF(F155="Invest",M154-J155-L155,M154+J155-50),M154)) -> 13453.399 | N155: 1
E156: 45914 | F156: Retrait | G156: 0 | H156: SOL | I156: 245 | J156: 245 | K156: =IF(J156=0,"",IF(H156="USDC",J156,(J156/I156))) -> 1 | L156: 0 | M156: =IF(E156="","",IF(G156=0,IF(F156="Invest",M155-J156-L156,M155+J156),M155)) -> 13698.399 | N156: 1
E157: 45918 | F157: Retrait | G157: 0 | H157: TAO | I157: 370 | J157: 222 | K157: =IF(J157=0,"",IF(H157="USDC",J157,(J157/I157))) -> 0.6 | L157: 0 | M157: =IF(E157="","",IF(G157=0,IF(F157="Invest",M156-J157-L157,M156+J157),M156)) -> 13920.399 | N157: 1
E158: 45918 | F158: Retrait | G158: 0 | H158: SOL | I158: 250 | J158: 250 | K158: =IF(J158=0,"",IF(H158="USDC",J158,(J158/I158))) -> 1 | L158: 0 | M158: =IF(E158="","",IF(G158=0,IF(F158="Invest",M157-J158-L158,M157+J158),M157)) -> 14170.399 | N158: 1
E159: 45919 | F159: Retrait | G159: 0 | H159: TAO | I159: 357 | J159: 249.9 | K159: =IF(J159=0,"",IF(H159="USDC",J159,(J159/I159))) -> 0.7 | L159: 0 | M159: =IF(E159="","",IF(G159=0,IF(F159="Invest",M158-J159-L159,M158+J159),M158)) -> 14420.299 | N159: 1
E160: 45922 | F160: Invest | G160: 0 | H160: ETH | I160: 4150 | J160: 290.5 | K160: =IF(J160=0,"",IF(H160="USDC",J160,(J160/I160))) -> 0.07 | L160: 0 | M160: =IF(E160="","",IF(G160=0,IF(F160="Invest",M159-J160-L160,M159+J160),M159)) -> 14129.799 | N160: 1
E161: 45923 | F161: Invest | G161: 0 | H161: SOL | I161: 218 | J161: 109 | K161: =IF(J161=0,"",IF(H161="USDC",J161,(J161/I161))) -> 0.5 | L161: 0 | M161: =IF(E161="","",IF(G161=0,IF(F161="Invest",M160-J161-L161,M160+J161),M160)) -> 14020.799 | N161: 1
E162: 45924 | F162: Invest | G162: 0 | H162: TAO | I162: 305 | J162: 152.5 | K162: =IF(J162=0,"",IF(H162="USDC",J162,(J162/I162))) -> 0.5 | L162: 0 | M162: =IF(E162="","",IF(G162=0,IF(F162="Invest",M161-J162-L162,M161+J162),M161)) -> 13868.299 | N162: 1
E163: 45925 | F163: Invest | G163: 0 | H163: DOGE | I163: 0.23 | J163: 57.5 | K163: =IF(J163=0,"",IF(H163="USDC",J163,(J163/I163))) -> 250 | L163: 0 | M163: =IF(E163="","",IF(G163=0,IF(F163="Invest",M162-J163-L163,M162+J163),M162)) -> 13810.799 | N163: 1
E164: 45928 | F164: Invest | G164: 0 | H164: TAO | I164: 295 | J164: 295 | K164: =IF(J164=0,"",IF(H164="USDC",J164,(J164/I164))) -> 1 | L164: 0 | M164: =IF(E164="","",IF(G164=0,IF(F164="Invest",M163-J164-L164,M163+J164),M163)) -> 13515.799 | N164: 1
E165: 45905 | F165: Retrait | G165: 0 | H165: ETH | I165: 4550 | J165: 227.5 | K165: =IF(J165=0,"",IF(H165="USDC",J165,(J165/I165))) -> 0.05 | L165: 0 | M165: =IF(E165="","",IF(G165=0,IF(F165="Invest",M164-J165-L165,M164+J165),M164)) -> 13743.299 | N165: 1
E166: 45939 | F166: Retrait | G166: 0 | H166: TAO | I166: 388.389 | J166: 194.19441 | K166: =IF(J166=0,"",IF(H166="USDC",J166,(J166/I166))) -> 0.49999978 | L166: 0 | M166: =IF(E166="","",IF(G166=0,IF(F166="Invest",M165-J166-L166,M165+J166),M165)) -> 13937.494 | N166: 1
E167: 45939 | F167: Retrait | G167: 0 | H167: TAO | I167: 395 | J167: 197.5 | K167: =IF(J167=0,"",IF(H167="USDC",J167,(J167/I167))) -> 0.5 | L167: 0 | M167: =IF(E167="","",IF(G167=0,IF(F167="Invest",M166-J167-L167,M166+J167),M166)) -> 14134.994 | N167: 1
E168: 45940 | F168: Retrait | G168: 0 | H168: ETH | I168: 4600 | J168: 230 | K168: =IF(J168=0,"",IF(H168="USDC",J168,(J168/I168))) -> 0.05 | L168: 0 | M168: =IF(E168="","",IF(G168=0,13591.898,M167)) -> 13591.898 | N168: 1
E169: 45941 | F169: Invest | G169: 0 | H169: ETH | I169: 3805 | J169: 76.1 | K169: =IF(J169=0,"",IF(H169="USDC",J169,(J169/I169))) -> 0.02 | L169: 0 | M169: =IF(E169="","",IF(G169=0,IF(F169="Invest",M168-J169-L169,M168+J169),M168)) -> 13515.798 | N169: 1
E170: 45941 | F170: Invest | G170: 0 | H170: ETH | I170: 3760 | J170: 94 | K170: =IF(J170=0,"",IF(H170="USDC",J170,(J170/I170))) -> 0.025 | L170: 0 | M170: =IF(E170="","",IF(G170=0,IF(F170="Invest",M169-J170-L170,M169+J170),M169)) -> 13421.798 | N170: 1
E171: 45942 | F171: Invest | G171: 0 | H171: ETH | I171: 3720 | J171: 100.44 | K171: =IF(J171=0,"",IF(H171="USDC",J171,(J171/I171))) -> 0.027 | L171: 0 | M171: =IF(E171="","",IF(G171=0,IF(F171="Invest",M170-J171-L171,M170+J171),M170)) -> 13321.358 | N171: 1
E172: 45945 | F172: Retrait | G172: 0 | H172: TAO | I172: 445 | J172: 222.5 | K172: =IF(J172=0,"",IF(H172="USDC",J172,(J172/I172))) -> 0.5 | L172: 0 | M172: =IF(E172="","",IF(G172=0,IF(F172="Invest",M171-J172-L172,M171+J172),M171)) -> 13543.858 | N172: 1
E173: 45949 | F173: Retrait | G173: 0 | H173: TAO | I173: 450 | J173: 225 | K173: =IF(J173=0,"",IF(H173="USDC",J173,(J173/I173))) -> 0.5 | L173: 0 | M173: =IF(E173="","",IF(G173=0,IF(F173="Invest",M172-J173-L173,M172+J173),M172)) -> 13768.858 | N173: 1
E174: 45950 | F174: Retrait | G174: 0 | H174: TAO | I174: 457 | J174: 228.5 | K174: =IF(J174=0,"",IF(H174="USDC",J174,(J174/I174))) -> 0.5 | L174: 0 | M174: =IF(E174="","",IF(G174=0,IF(F174="Invest",M173-J174-L174,M173+J174),M173)) -> 13997.358 | N174: 1
E175: 45952 | F175: Retrait | G175: 0 | H175: TON | I175: 2.3 | J175: 567.2479 | K175: =IF(J175=0,"",IF(H175="USDC",J175,(J175/I175))) -> 246.62952 | L175: 0 | M175: =IF(E175="","",IF(G175=0,IF(F175="Invest",M174-J175-L175,M174+J175),M174)) -> 14564.606 | N175: 0
E176: 45953 | F176: Retrait | G176: 0 | H176: PEPE | I176: 7e-06 | J176: 169.00687 | K176: =IF(J176=0,"",IF(H176="USDC",J176,(J176/I176))) -> 24143839 | L176: 0 | M176: =IF(E176="","",IF(G176=0,IF(F176="Invest",M175-J176-L176,M175+J176),M175)) -> 14733.613 | N176: 0
E177: 45957 | F177: Retrait | G177: 0 | H177: BTC | I177: 114500 | J177: 1145 | K177: =IF(J177=0,"",IF(H177="USDC",J177,(J177/I177))) -> 0.01 | L177: 0 | M177: =IF(E177="","",IF(G177=0,IF(F177="Invest",M176-J177-L177,M176+J177),M176)) -> 15878.613 | N177: 1
E178: 45957 | F178: Retrait | G178: 0 | H178: ETH | I178: 4125 | J178: 825 | K178: =IF(J178=0,"",IF(H178="USDC",J178,(J178/I178))) -> 0.2 | L178: 0 | M178: =IF(E178="","",IF(G178=0,IF(F178="Invest",M177-J178-L178,M177+J178),M177)) -> 16703.613 | N178: 1
E179: 45958 | F179: Retrait | G179: 0 | H179: TAO | I179: 450 | J179: 450 | K179: =IF(J179=0,"",IF(H179="USDC",J179,(J179/I179))) -> 1 | L179: 0 | M179: =IF(E179="","",IF(G179=0,IF(F179="Invest",M178-J179-L179,M178+J179+30),M178)) -> 17183.613 | N179: 1
E180: 45960 | F180: Retrait | G180: 0 | H180: TAO | I180: 465 | J180: 465 | K180: =IF(J180=0,"",IF(H180="USDC",J180,(J180/I180))) -> 1 | L180: 0 | M180: =IF(E180="","",IF(G180=0,IF(F180="Invest",M179-J180-L180,M179+J180),M179)) -> 17648.613 | N180: 1
E181: 45961 | F181: Retrait | G181: 0 | H181: TAO | I181: 470 | J181: 705 | K181: =IF(J181=0,"",IF(H181="USDC",J181,(J181/I181))) -> 1.5 | L181: 0 | M181: =IF(E181="","",IF(G181=0,IF(F181="Invest",M180-J181-L181,M180+J181),M180)) -> 18353.613 | N181: 1
E182: 45961 | F182: Retrait | G182: 0 | H182: TAO | I182: 500 | J182: 400 | K182: =IF(J182=0,"",IF(H182="USDC",J182,(J182/I182))) -> 0.8 | L182: 0 | M182: =IF(E182="","",IF(G182=0,IF(F182="Invest",M181-J182-L182,M181+J182),M181)) -> 18753.613 | N182: 1
...

Sheet HISTORIQUE RAPIDE
A2: DATE | B2: INITIAL ENTRY | C2: ACTUAL PORTFOLLIO | D2: ROI % | E2: PV
A3: =ARBITRAGES!E3 -> 45515 | B3: =BILAN!N3 -> 37467.522 | C3: =BILAN!O3 -> 37684.606 | D3: =(C3-B3)/B3 -> 0.0057939408 | E3: =C3-B3 -> 217.0846
A4: =IF(ARBITRAGES!E4="","",ARBITRAGES!E4) -> 45515 | B4: =BILAN!N4 -> 37467.522 | C4: =BILAN!O4 -> 39187.939 | D4: =(C4-B4)/B4 -> 0.04591757 | E4: =C4-B4 -> 1720.4176
A5: =IF(ARBITRAGES!E5="","",ARBITRAGES!E5) -> 45516 | B5: =BILAN!N5 -> 37467.522 | C5: =BILAN!O5 -> 38425.058 | D5: =(C5-B5)/B5 -> 0.025556434 | E5: =C5-B5 -> 957.53625
A6: =IF(ARBITRAGES!E6="","",ARBITRAGES!E6) -> 45517 | B6: =BILAN!N6 -> 37467.522 | C6: =BILAN!O6 -> 38797.452 | D6: =(C6-B6)/B6 -> 0.035495565 | E6: =C6-B6 -> 1329.9308
A7: =IF(ARBITRAGES!E7="","",ARBITRAGES!E7) -> 45518 | B7: =BILAN!N7 -> 37467.522 | C7: =BILAN!O7 -> 38816.265 | D7: =(C7-B7)/B7 -> 0.035997663 | E7: =C7-B7 -> 1348.7432
A8: =IF(ARBITRAGES!E8="","",ARBITRAGES!E8) -> 45518 | B8: =BILAN!N8 -> 37467.522 | C8: =BILAN!O8 -> 38836.265 | D8: =(C8-B8)/B8 -> 0.036531459 | E8: =C8-B8 -> 1368.7432
A9: =IF(ARBITRAGES!E9="","",ARBITRAGES!E9) -> 45519 | B9: =BILAN!N9 -> 37467.522 | C9: =BILAN!O9 -> 37999.572 | D9: =(C9-B9)/B9 -> 0.014200307 | E9: =C9-B9 -> 532.05032
A10: =IF(ARBITRAGES!E10="","",ARBITRAGES!E10) -> 45522 | B10: =BILAN!N10 -> 37467.522 | C10: =BILAN!O10 -> 38621.63 | D10: =(C10-B10)/B10 -> 0.030802901 | E10: =C10-B10 -> 1154.1083
A11: =IF(ARBITRAGES!E11="","",ARBITRAGES!E11) -> 45527 | B11: =BILAN!N11 -> 37467.522 | C11: =BILAN!O11 -> 40071.087 | D11: =(C11-B11)/B11 -> 0.069488585 | E11: =C11-B11 -> 2603.5651
A12: =IF(ARBITRAGES!E12="","",ARBITRAGES!E12) -> 45527 | B12: =BILAN!N12 -> 37467.522 | C12: =BILAN!O12 -> 40130.796 | D12: =(C12-B12)/B12 -> 0.071082223 | E12: =C12-B12 -> 2663.2747
A13: =IF(ARBITRAGES!E13="","",ARBITRAGES!E13) -> 45528 | B13: =BILAN!N13 -> 37467.522 | C13: =BILAN!O13 -> 40893.775 | D13: =(C13-B13)/B13 -> 0.091445958 | E13: =C13-B13 -> 3426.2534
A14: =IF(ARBITRAGES!E14="","",ARBITRAGES!E14) -> 45529 | B14: =BILAN!N14 -> 37467.522 | C14: =BILAN!O14 -> 40117.46 | D14: =(C14-B14)/B14 -> 0.070726265 | E14: =C14-B14 -> 2649.9379
A15: =IF(ARBITRAGES!E15="","",ARBITRAGES!E15) -> 45530 | B15: =BILAN!N15 -> 37467.522 | C15: =BILAN!O15 -> 38900.624 | D15: =(C15-B15)/B15 -> 0.038249185 | E15: =C15-B15 -> 1433.1022
... A34: =IF(ARBITRAGES!E34="","",ARBITRAGES!E34) -> 45602 | B34: =BILAN!N34 -> 37467.522 | C34: =BILAN!O34 -> 45167.981 | D34: =(C34-B34)/B34 -> 0.20552359 | E34: =C34-B34 -> 7700.4597
A35: 45603 | B35: =IF(A35="","",B34) -> 37467.522 | C35: 46153.166 | D35: =(C35-B35)/B35 -> 0.23181797 | E35: =C35-B35 -> 8685.6447
A36: 45605 | B36: =IF(A36="","",B35) -> 37467.522 | C36: 49222.315 | D36: =IF(C36="","",(C36-B36)/B36) -> 0.31373287 | E36: =IF(C36="","",C36-B36) -> 11754.793
A37: 45607 | B37: =IF(A37="","",B36) -> 37467.522 | C37: 51641.25 | D37: =IF(C37="","",(C37-B37)/B37) -> 0.37829373 | E37: =IF(C37="","",C37-B37) -> 14173.728
A38: 45608 | B38: =IF(C38="","",B37) -> 37467.522 | C38: 54284.52 | D38: =IF(C38="","",(C38-B38)/B38) -> 0.44884203 | E38: =IF(C38="","",C38-B38) -> 16816.998
A39: 45609 | B39: =IF(C39="","",B38) -> 37467.522 | C39: 51403.192 | D39: =IF(C39="","",(C39-B39)/B39) -> 0.37194002 | E39: =IF(C39="","",C39-B39) -> 13935.671
A40: 45610 | B40: =IF(C40="","",B39) -> 37467.522 | C40: 51527.826 | D40: =IF(C40="","",(C40-B40)/B40) -> 0.37526647 | E40: =IF(C40="","",C40-B40) -> 14060.304
A41: 45613 | B41: =IF(C41="","",B40) -> 37467.522 | C41: 53158.117 | D41: =IF(C41="","",(C41-B41)/B41) -> 0.41877856 | E41: =IF(C41="","",C41-B41) -> 15690.595
A42: 45615 | B42: =IF(C42="","",B41) -> 37467.522 | C42: 53867.707 | D42: =IF(C42="","",(C42-B42)/B42) -> 0.43771737 | E42: =IF(C42="","",C42-B42) -> 16400.185
A43: 45617 | B43: =IF(C43="","",B42) -> 37467.522 | C43: 56248.56 | D43: =IF(C43="","",(C43-B43)/B43) -> 0.50126183 | E43: =IF(C43="","",C43-B43) -> 18781.038
A44: 45619 | B44: =IF(C44="","",B43) -> 37467.522 | C44: 58682.42 | D44: =IF(C44="","",(C44-B44)/B44) -> 0.56622102 | E44: =IF(C44="","",C44-B44) -> 21214.898
A45: 45621 | B45: =IF(C45="","",B44) -> 37467.522 | C45: 58525.26 | D45: =IF(C45="","",(C45-B45)/B45) -> 0.56202645 | E45: =IF(C45="","",C45-B45) -> 21057.738
A46: 45622 | B46: =IF(C46="","",B45) -> 37467.522 | C46: 54937.25 | D46: =IF(C46="","",(C46-B46)/B46) -> 0.46626325 | E46: =IF(C46="","",C46-B46) -> 17469.728
A47: 45624 | B47: =IF(C47="","",B46) -> 37467.522 | C47: 58243.56 | D47: =IF(C47="","",(C47-B47)/B47) -> 0.55450794 | E47: =IF(C47="","",C47-B47) -> 20776.038
A48: 45625 | B48: =IF(C48="","",B47) -> 37467.522 | C48: 60084.09 | D48: =IF(C48="","",(C48-B48)/B48) -> 0.60363129 | E48: =IF(C48="","",C48-B48) -> 22616.568
A49: 45628 | B49: =IF(C49="","",B48) -> 37467.522 | C49: 58531.42 | D49: =IF(C49="","",(C49-B49)/B49) -> 0.56219086 | E49: =IF(C49="","",C49-B49) -> 21063.898
... A69: 45680 | B69: =IF(C69="","",B68) -> 37467.522 | C69: 57532.15 | D69: =IF(C69="","",(C69-B69)/B69) -> 0.53552056 | E69: =IF(C69="","",C69-B69) -> 20064.628
A70: 45687 | B70: =IF(C70="","",B68) -> 37467.522 | C70: 56523.14 | D70: =IF(C70="","",(C70-B70)/B70) -> 0.50859031 | E70: =IF(C70="","",C70-B70) -> 19055.618
A71: 45692 | B71: =IF(C71="","",B69) -> 37467.522 | C71: 51213.21 | D71: =IF(C71="","",(C71-B71)/B71) -> 0.36686943 | E71: =IF(C71="","",C71-B71) -> 13745.688
A72: 45695 | B72: =IF(C72="","",B71) -> 37467.522 | C72: 49452.15 | D72: =IF(C72="","",(C72-B72)/B72) -> 0.31986712 | E72: =IF(C72="","",C72-B72) -> 11984.628
A73: 45698 | B73: =IF(C73="","",B72) -> 37467.522 | C73: 52341.87 | D73: =IF(C73="","",(C73-B73)/B73) -> 0.39699312 | E73: =IF(C73="","",C73-B73) -> 14874.348
A74: 45700 | B74: =IF(C74="","",B73) -> 37467.522 | C74: 50632.64 | D74: =IF(C74="","",(C74-B74)/B74) -> 0.35137414 | E74: =IF(C74="","",C74-B74) -> 13165.118
A75: 45702 | B75: =IF(C75="","",B74) -> 37467.522 | C75: 49241.18 | D75: =IF(C75="","",(C75-B75)/B75) -> 0.31423638 | E75: =IF(C75="","",C75-B75) -> 11773.658
A76: 45705 | B76: =IF(C76="","",B75) -> 37467.522 | C76: 51986.2 | D76: =IF(C76="","",(C76-B76)/B76) -> 0.38750037 | E76: =IF(C76="","",C76-B76) -> 14518.678
A77: 45707 | B77: =IF(C77="","",B76) -> 37467.522 | C77: 48862.47 | D77: =IF(C77="","",(C77-B77)/B77) -> 0.30412869 | E77: =IF(C77="","",C77-B77) -> 11394.948
A78: 45711 | B78: =IF(C78="","",B77) -> 37467.522 | C78: 50136.4 | D78: =IF(C78="","",(C78-B78)/B78) -> 0.33812961 | E78: =IF(C78="","",C78-B78) -> 12668.878
A79: 45712 | B79: =IF(C79="","",B78) -> 37467.522 | C79: 48315.29 | D79: =IF(C79="","",(C79-B79)/B79) -> 0.28952458 | E79: =IF(C79="","",C79-B79) -> 10847.768
A80: 45714 | B80: =IF(C80="","",B79) -> 37467.522 | C80: 45633.1 | D80: =IF(C80="","",(C80-B80)/B80) -> 0.21793751 | E80: =IF(C80="","",C80-B80) -> 8165.5783
A81: 45715 | B81: =IF(C81="","",B80) -> 37467.522 | C81: 42186.48 | D81: =IF(C81="","",(C81-B81)/B81) -> 0.12594797 | E81: =IF(C81="","",C81-B81) -> 4718.9583
A82: 45716 | B82: =IF(C82="","",B81) -> 37467.522 | C82: 41583.4 | D82: =IF(C82="","",(C82-B82)/B82) -> 0.1098519 | E82: =IF(C82="","",C82-B82) -> 4115.8783
A83: 45718 | B83: =IF(C83="","",B82) -> 37467.522 | C83: 47321.84 | D83: =IF(C83="","",(C83-B83)/B83) -> 0.26300961 | E83: =IF(C83="","",C83-B83) -> 9854.3183
... A182: 46046 | B182: =IF(C182="","",B181) -> 37467.522 | C182: 49007.23 | D182: =IF(C182="","",(C182-B182)/B182) -> 0.3079923 | E182: =IF(C182="","",C182-B182) -> 11539.708
B183: =IF(C183="","",B182) | D183: =IF(C183="","",(C183-B183)/B183) | E183: =IF(C183="","",C183-B183)
B184: =IF(C184="","",B183) | D184: =IF(C184="","",(C184-B184)/B184) | E184: =IF(C184="","",C184-B184)
B185: =IF(C185="","",B184) | D185: =IF(C185="","",(C185-B185)/B185) | E185: =IF(C185="","",C185-B185)
B186: =IF(C186="","",B185) | D186: =IF(C186="","",(C186-B186)/B186) | E186: =IF(C186="","",C186-B186)
B187: =IF(C187="","",B186) | D187: =IF(C187="","",(C187-B187)/B187) | E187: =IF(C187="","",C187-B187)
B188: =IF(C188="","",B187) | D188: =IF(C188="","",(C188-B188)/B188) | E188: =IF(C188="","",C188-B188)
B189: =IF(C189="","",B188) | D189: =IF(C189="","",(C189-B189)/B189) | E189: =IF(C189="","",C189-B189)
B190: =IF(C190="","",B189) | D190: =IF(C190="","",(C190-B190)/B190) | E190: =IF(C190="","",C190-B190)
B191: =IF(C191="","",B190) | D191: =IF(C191="","",(C191-B191)/B191) | E191: =IF(C191="","",C191-B191)
B192: =IF(C192="","",B191) | D192: =IF(C192="","",(C192-B192)/B192) | E192: =IF(C192="","",C192-B192)
B193: =IF(C193="","",B192) | D193: =IF(C193="","",(C193-B193)/B193) | E193: =IF(C193="","",C193-B193)
B194: =IF(C194="","",B193) | D194: =IF(C194="","",(C194-B194)/B194) | E194: =IF(C194="","",C194-B194)
... B401: =IF(C401="","",B400) | D401: =IF(C401="","",(C401-B401)/B401) | E401: =IF(C401="","",C401-B401)

Sheet PV (%)
Q2: $BTC | R2: $ETH | S2: $TON | T2: $SOL | U2: $TAO | V2: $RON | W2: $LINK | X2: $DOGE | Y2: total
B3: Date | C3: Investissement | D3: $BTC | E3: Portefeuille full BTC | F3: Portefeuille sans arbitrage | G3: Portefeuille avec arbitrage | H3: Plus value | I3: ROI GLOBAL | Q3: =Q4*$Y$3 -> 16860.385 | R3: =R4*$Y$3 -> 7493.5043 | S3: =S4*$Y$3 -> 3746.7522 | T3: =T4*$Y$3 -> 3746.7522 | U3: =U4*$Y$3 -> 1873.3761 | V3: =V4*$Y$3 -> 1873.3761 | W3: =W4*$Y$3 -> 1498.7009 | X3: =X4*$Y$3 -> 374.67522 | Y3: =C4 -> 37467.522
B4: =IF(ARBITRAGES!E4=0,"",ARBITRAGES!E4) -> 45515 | C4: =BILAN!N4 -> 37467.522 | D4: =IF(F4="","",PRIX!B3) -> 63000 | E4: =IF(F4="","",($G$4/$D$4)*D4) -> 37467.522 | F4: =IF(B4="","",G4) -> 37467.522 | G4: =IF(B4="","",C4) -> 37467.522 | H4: =IF(B4="","",(G4-F4)/F4) -> 0 | I4: =IF(H4="","",(G4-C4)/C4) -> 0 | P4: Quantité prévue (%) | Q4: 0.45 | R4: 0.2 | S4: 0.1 | T4: 0.1 | U4: 0.05 | V4: 0.05 | W4: 0.04 | X4: 0.01 | Y4: =SUM(Q4:X4) -> 1
B5: =IF(ARBITRAGES!E5=0,"",ARBITRAGES!E5) -> 45516 | C5: =IF(F5="","",C4) -> 37467.522 | D5: =IF(F5="","",PRIX!B4) -> 63000 | E5: =IF(F5="","",($G$4/$D$4)*D5) -> 37467.522 | F5: =IF(B5="","",PRIX!B5*$Q$6+$R$6*PRIX!C5+PRIX!D5*$S$6+$T$6*PRIX!E5+PRIX!F5*$U$6+PRIX!G5*$V$6+$W$6*PRIX!H5+PRIX!I5*$X$6) -> 36849.451 | G5: =IF(B5="","",'Historique détail'!U4) -> 39187.939 | H5: =IF(B5="","",(G5-F5)/F5) -> 0.063460607 | I5: =IF(H5="","",(G5-C5)/C5) -> 0.04591757 | P5: PMA | Q5: 60800 | R5: 2650 | S5: 7.61 | T5: 155 | U5: 300 | V5: 1.6 | W5: 11.5 | X5: 0.105 | Y5: -
B6: =IF(ARBITRAGES!E6=0,"",ARBITRAGES!E6) -> 45517 | C6: =IF(F6="","",C5) -> 37467.522 | D6: =IF(F6="","",PRIX!B5) -> 59800 | E6: =IF(F6="","",($G$4/$D$4)*D6) -> 35564.409 | F6: =IF(B6="","",PRIX!B6*$Q$6+$R$6*PRIX!C6+PRIX!D6*$S$6+$T$6*PRIX!E6+PRIX!F6*$U$6+PRIX!G6*$V$6+$W$6*PRIX!H6+PRIX!I6*$X$6) -> 37173.715 | G6: =IF(B6="","",'Historique détail'!U5) -> 38425.058 | H6: =IF(B6="","",(G6-F6)/F6) -> 0.03366203 | I6: =IF(H6="","",(G6-C6)/C6) -> 0.025556434 | P6: Quantité prévue | Q6: =Q3/Q5 -> 0.27730896 | R6: =R3/R5 -> 2.8277375 | S6: =S3/S5 -> 492.34588 | T6: =T3/T5 -> 24.172595 | U6: =U3/U5 -> 6.2445869 | V6: =V3/V5 -> 1170.8601 | W6: =W3/W5 -> 130.32181 | X6: =X3/X5 -> 3568.3354 | Y6: -
B7: =IF(ARBITRAGES!E7=0,"",ARBITRAGES!E7) -> 45518 | C7: =IF(F7="","",C6) -> 37467.522 | D7: =IF(F7="","",PRIX!B6) -> 61000 | E7: =IF(F7="","",($G$4/$D$4)*D7) -> 36278.077 | F7: =IF(B7="","",PRIX!B7*$Q$6+$R$6*PRIX!C7+PRIX!D7*$S$6+$T$6*PRIX!E7+PRIX!F7*$U$6+PRIX!G7*$V$6+$W$6*PRIX!H7+PRIX!I7*$X$6) -> 37126.881 | G7: =IF(B7="","",'Historique détail'!U6) -> 38797.452 | H7: =IF(B7="","",(G7-F7)/F7) -> 0.044996286 | I7: =IF(H7="","",(G7-C7)/C7) -> 0.035495565 | P7: Prix actuel | Q7: =RECAP!AU2 -> 67500 | R7: =RECAP!AU3 -> 1950 | S7: =RECAP!AU4 -> 1.44 | T7: =RECAP!AU5 -> 83 | U7: =RECAP!AU6 -> 190 | V7: =RECAP!AU7 -> 0.096 | W7: =RECAP!AU8 -> 8.7 | X7: =RECAP!AU9 -> 0.0999 | Y7: =Q6*Q7+R6*R7+S6*S7+T6*T7+U6*U7+V6*V7+W6*W7+X6*X7 -> 29736.897
B8: =IF(ARBITRAGES!E9=0,"",ARBITRAGES!E9) -> 45519 | C8: =IF(F8="","",C7) -> 37467.522 | D8: =IF(F8="","",PRIX!B7) -> 61000 | E8: =IF(F8="","",($G$4/$D$4)*D8) -> 36278.077 | F8: =IF(B8="","",PRIX!B9*$Q$6+$R$6*PRIX!C9+PRIX!D9*$S$6+$T$6*PRIX!E9+PRIX!F9*$U$6+PRIX!G9*$V$6+$W$6*PRIX!H9+PRIX!I9*$X$6) -> 35694.108 | G8: =IF(B8="","",'Historique détail'!U8) -> 38836.265 | H8: =IF(B8="","",(G8-F8)/F8) -> 0.088030118 | I8: =IF(H8="","",(G8-C8)/C8) -> 0.036531459 | K8: Moyenne de performance
B9: =IF(ARBITRAGES!E10=0,"",ARBITRAGES!E10) -> 45522 | C9: =IF(F9="","",C8) -> 37467.522 | D9: =IF(F9="","",PRIX!B8) -> 61000 | E9: =IF(F9="","",($G$4/$D$4)*D9) -> 36278.077 | F9: =IF(B9="","",PRIX!B10*$Q$6+$R$6*PRIX!C10+PRIX!D10*$S$6+$T$6*PRIX!E10+PRIX!F10*$U$6+PRIX!G10*$V$6+$W$6*PRIX!H10+PRIX!I10*$X$6) -> 36536.792 | G9: =IF(B9="","",'Historique détail'!U9) -> 37999.572 | H9: =IF(B9="","",(G9-F9)/F9) -> 0.04003582 | I9: =IF(H9="","",(G9-C9)/C9) -> 0.014200307 | K9: 10 dernier jours | L9: =AVERAGE(H195:H205) -> 0.19011918
B10: =IF(ARBITRAGES!E11=0,"",ARBITRAGES!E11) -> 45527 | C10: =IF(F10="","",C9) -> 37467.522 | D10: =IF(F10="","",PRIX!B9) -> 58000 | E10: =IF(F10="","",($G$4/$D$4)*D10) -> 34493.909 | F10: =IF(B10="","",PRIX!B11*$Q$6+$R$6*PRIX!C11+PRIX!D11*$S$6+$T$6*PRIX!E11+PRIX!F11*$U$6+PRIX!G11*$V$6+$W$6*PRIX!H11+PRIX!I11*$X$6) -> 38338.251 | G10: =IF(B10="","",'Historique détail'!U10) -> 38621.63 | H10: =IF(B10="","",(G10-F10)/F10) -> 0.0073915584 | I10: =IF(H10="","",(G10-C10)/C10) -> 0.030802901 | K10: le mois en cours | L10: =AVERAGE(H163:H205) -> 0.17038752
B11: =IF(ARBITRAGES!E12=0,"",ARBITRAGES!E12) -> 45527 | C11: =IF(F11="","",C10) -> 37467.522 | D11: =IF(F11="","",PRIX!B10) -> 60100 | E11: =IF(F11="","",($G$4/$D$4)*D11) -> 35742.826 | F11: =IF(B11="","",PRIX!B12*$Q$6+$R$6*PRIX!C12+PRIX!D12*$S$6+$T$6*PRIX!E12+PRIX!F12*$U$6+PRIX!G12*$V$6+$W$6*PRIX!H12+PRIX!I12*$X$6) -> 38338.251 | G11: =IF(B11="","",'Historique détail'!U11) -> 40071.087 | H11: =IF(B11="","",(G11-F11)/F11) -> 0.045198623 | I11: =IF(H11="","",(G11-C11)/C11) -> 0.069488585 | K11: 6 dernier mois | L11: =AVERAGE(H59:H205) -> 0.097221009
B12: =IF(ARBITRAGES!E13=0,"",ARBITRAGES!E13) -> 45528 | C12: =IF(F12="","",C11) -> 37467.522 | D12: =IF(F12="","",PRIX!B11) -> 63400 | E12: =IF(F12="","",($F$4/$D$4)*D12) -> 37705.411 | F12: =IF(B12="","",PRIX!B13*$Q$6+$R$6*PRIX!C13+PRIX!D13*$S$6+$T$6*PRIX!E13+PRIX!F13*$U$6+PRIX!G13*$V$6+$W$6*PRIX!H13+PRIX!I13*$X$6) -> 39159.97 | G12: =IF(B12="","",'Historique détail'!U12) -> 40130.796 | H12: =IF(B12="","",(G12-F12)/F12) -> 0.024791302 | I12: =IF(H12="","",(G12-C12)/C12) -> 0.071082223 | K12: l'année en cours | L12: =AVERAGE(H:H) -> 0.11438787
B13: =IF(ARBITRAGES!E14=0,"",ARBITRAGES!E14) -> 45529 | C13: =IF(F13="","",C12) -> 37467.522 | D13: =IF(F13="","",PRIX!B12) -> 63400 | E13: =IF(F13="","",($F$4/$D$4)*D13) -> 37705.411 | F13: =IF(B13="","",PRIX!B14*$Q$6+$R$6*PRIX!C14+PRIX!D14*$S$6+$T$6*PRIX!E14+PRIX!F14*$U$6+PRIX!G14*$V$6+$W$6*PRIX!H14+PRIX!I14*$X$6) -> 38233.711 | G13: =IF(B13="","",'Historique détail'!U13) -> 40893.775 | H13: =IF(B13="","",(G13-F13)/F13) -> 0.069573791 | I13: =IF(H13="","",(G13-C13)/C13) -> 0.091445958
B14: =IF(ARBITRAGES!E15=0,"",ARBITRAGES!E15) -> 45530 | C14: =IF(F14="","",C13) -> 37467.522 | D14: =IF(F14="","",PRIX!B13) -> 64400 | E14: =IF(F14="","",($G$4/$D$4)*D14) -> 38300.133 | F14: =IF(B14="","",PRIX!B15*$Q$6+$R$6*PRIX!C15+PRIX!D15*$S$6+$T$6*PRIX!E15+PRIX!F15*$U$6+PRIX!G15*$V$6+$W$6*PRIX!H15+PRIX!I15*$X$6) -> 36872.135 | G14: =IF(B14="","",'Historique détail'!U14) -> 40117.46 | H14: =IF(B14="","",(G14-F14)/F14) -> 0.088015649 | I14: =IF(H14="","",(G14-C14)/C14) -> 0.070726265
B15: =IF(ARBITRAGES!E16=0,"",ARBITRAGES!E16) -> 45531 | C15: =IF(F15="","",C14) -> 37467.522 | D15: =IF(F15="","",PRIX!B14) -> 64000 | E15: =IF(F15="","",($G$4/$D$4)*D15) -> 38062.244 | F15: =IF(B15="","",PRIX!B16*$Q$6+$R$6*PRIX!C16+PRIX!D16*$S$6+$T$6*PRIX!E16+PRIX!F16*$U$6+PRIX!G16*$V$6+$W$6*PRIX!H16+PRIX!I16*$X$6) -> 36872.135 | G15: =IF(B15="","",'Historique détail'!U15) -> 38900.624 | H15: =IF(B15="","",(G15-F15)/F15) -> 0.055014149 | I15: =IF(H15="","",(G15-C15)/C15) -> 0.038249185
B16: =IF(ARBITRAGES!E20=0,"",ARBITRAGES!E20) -> 45532 | C16: =IF(F16="","",C15) -> 37467.522 | D16: =IF(F16="","",PRIX!B15) -> 62000 | E16: =IF(F16="","",($G$4/$D$4)*D16) -> 36872.799 | F16: =IF(B16="","",PRIX!B20*$Q$6+$R$6*PRIX!C20+PRIX!D20*$S$6+$T$6*PRIX!E20+PRIX!F20*$U$6+PRIX!G20*$V$6+$W$6*PRIX!H20+PRIX!I20*$X$6) -> 35451.629 | G16: =IF(B16="","",'Historique détail'!U19) -> 38937.508 | H16: =IF(B16="","",(G16-F16)/F16) -> 0.098327755 | I16: =IF(H16="","",(G16-C16)/C16) -> 0.039233626
B17: =IF(ARBITRAGES!E21=0,"",ARBITRAGES!E21) -> 45545 | C17: =IF(F17="","",C16) -> 37467.522 | D17: =IF(F17="","",PRIX!B16) -> 62000 | E17: =IF(F17="","",($F$4/$D$4)*D17) -> 36872.799 | F17: =IF(B17="","",PRIX!B21*$Q$6+$R$6*PRIX!C21+PRIX!D21*$S$6+$T$6*PRIX!E21+PRIX!F21*$U$6+PRIX!G21*$V$6+$W$6*PRIX!H21+PRIX!I21*$X$6) -> 33732.789 | G17: =IF(B17="","",'Historique détail'!U20) -> 37571.824 | H17: =IF(B17="","",(G17-F17)/F17) -> 0.1138072 | I17: =IF(H17="","",(G17-C17)/C17) -> 0.0027838007
B18: =IF(ARBITRAGES!E22=0,"",ARBITRAGES!E22) -> 45551 | C18: =IF(F18="","",C17) -> 37467.522 | D18: =IF(F18="","",PRIX!B17) -> 62000 | E18: =IF(F18="","",($F$4/$D$4)*D18) -> 36872.799 | F18: =IF(B18="","",PRIX!B22*$Q$6+$R$6*PRIX!C22+PRIX!D22*$S$6+$T$6*PRIX!E22+PRIX!F22*$U$6+PRIX!G22*$V$6+$W$6*PRIX!H22+PRIX!I22*$X$6) -> 34523.808 | G18: =IF(B18="","",'Historique détail'!U21) -> 35856.037 | H18: =IF(B18="","",(G18-F18)/F18) -> 0.038588717 | I18: =IF(H18="","",(G18-C18)/C18) -> -0.043010175
B19: =IF(ARBITRAGES!E23=0,"",ARBITRAGES!E23) -> 45552 | C19: =IF(F19="","",C18) -> 37467.522 | D19: =IF(F19="","",PRIX!B18) -> 62000 | E19: =IF(F19="","",($F$4/$D$4)*D19) -> 36872.799 | F19: =IF(B19="","",PRIX!B23*$Q$6+$R$6*PRIX!C23+PRIX!D23*$S$6+$T$6*PRIX!E23+PRIX!F23*$U$6+PRIX!G23*$V$6+$W$6*PRIX!H23+PRIX!I23*$X$6) -> 35693.794 | G19: =IF(B19="","",'Historique détail'!U22) -> 36696.807 | H19: =IF(B19="","",(G19-F19)/F19) -> 0.028100479 | I19: =IF(H19="","",(G19-C19)/C19) -> -0.020570216
B20: =IF(ARBITRAGES!E24=0,"",ARBITRAGES!E24) -> 45555 | C20: =IF(F20="","",C19) -> 37467.522 | D20: =IF(F20="","",PRIX!B19) -> 62000 | E20: =IF(F20="","",($F$4/$D$4)*D20) -> 36872.799 | F20: =IF(B20="","",PRIX!B24*$Q$6+$R$6*PRIX!C24+PRIX!D24*$S$6+$T$6*PRIX!E24+PRIX!F24*$U$6+PRIX!G24*$V$6+$W$6*PRIX!H24+PRIX!I24*$X$6) -> 38152.442 | G20: =IF(B20="","",'Historique détail'!U23) -> 37935.52 | H20: =IF(B20="","",(G20-F20)/F20) -> -0.005685668 | I20: =IF(H20="","",(G20-C20)/C20) -> 0.012490773
B21: =IF(ARBITRAGES!E25=0,"",ARBITRAGES!E25) -> 45557 | C21: =IF(F21="","",C20) -> 37467.522 | D21: =IF(F21="","",PRIX!B20) -> 59500 | E21: =IF(F21="","",($F$4/$D$4)*D21) -> 35385.993 | F21: =IF(B21="","",PRIX!B25*$Q$6+$R$6*PRIX!C25+PRIX!D25*$S$6+$T$6*PRIX!E25+PRIX!F25*$U$6+PRIX!G25*$V$6+$W$6*PRIX!H25+PRIX!I25*$X$6) -> 39351.681 | G21: =IF(B21="","",'Historique détail'!U24) -> 40252.678 | H21: =IF(B21="","",(G21-F21)/F21) -> 0.022896017 | I21: =IF(H21="","",(G21-C21)/C21) -> 0.074335216
B22: =IF(ARBITRAGES!E26=0,"",ARBITRAGES!E26) -> 45558 | C22: =IF(F22="","",C21) -> 37467.522 | D22: =IF(F22="","",PRIX!B21) -> 57300 | E22: =IF(F22="","",($F$4/$D$4)*D22) -> 34077.603 | F22: =IF(B22="","",PRIX!B26*$Q$6+$R$6*PRIX!C26+PRIX!D26*$S$6+$T$6*PRIX!E26+PRIX!F26*$U$6+PRIX!G26*$V$6+$W$6*PRIX!H26+PRIX!I26*$X$6) -> 38728.401 | G22: =IF(B22="","",'Historique détail'!U25) -> 41372.68 | H22: =IF(B22="","",(G22-F22)/F22) -> 0.068277526 | I22: =IF(H22="","",(G22-C22)/C22) -> 0.10422783
B23: =IF(ARBITRAGES!E27=0,"",ARBITRAGES!E27) -> 45568 | C23: =IF(F23="","",C22) -> 37467.522 | D23: =IF(F23="","",PRIX!B22) -> 59000 | E23: =IF(F23="","",($F$4/$D$4)*D23) -> 35088.631 | F23: =IF(B23="","",PRIX!B27*$Q$6+$R$6*PRIX!C27+PRIX!D27*$S$6+$T$6*PRIX!E27+PRIX!F27*$U$6+PRIX!G27*$V$6+$W$6*PRIX!H27+PRIX!I27*$X$6) -> 36720.633 | G23: =IF(B23="","",'Historique détail'!U26) -> 40838.915 | H23: =IF(B23="","",(G23-F23)/F23) -> 0.11215171 | I23: =IF(H23="","",(G23-C23)/C23) -> 0.089981761
B24: =IF(ARBITRAGES!E28=0,"",ARBITRAGES!E28) -> 45586 | C24: =IF(F24="","",C23) -> 37467.522 | D24: =IF(F24="","",PRIX!B23) -> 61200 | E24: =IF(F24="","",($F$4/$D$4)*D24) -> 36397.021 | F24: =IF(B24="","",PRIX!B28*$Q$6+$R$6*PRIX!C28+PRIX!D28*$S$6+$T$6*PRIX!E28+PRIX!F28*$U$6+PRIX!G28*$V$6+$W$6*PRIX!H28+PRIX!I28*$X$6) -> 41504.004 | G24: =IF(B24="","",'Historique détail'!U27) -> 38996.089 | H24: =IF(B24="","",(G24-F24)/F24) -> -0.060425844 | I24: =IF(H24="","",(G24-C24)/C24) -> 0.040797133
B25: =IF(ARBITRAGES!E29=0,"",ARBITRAGES!E29) -> 45591 | C25: =IF(F25="","",C24) -> 37467.522 | D25: =IF(F25="","",PRIX!B24) -> 64050 | E25: =IF(F25="","",($F$4/$D$4)*D25) -> 38091.98 | F25: =IF(B25="","",PRIX!B29*$Q$6+$R$6*PRIX!C29+PRIX!D29*$S$6+$T$6*PRIX!E29+PRIX!F29*$U$6+PRIX!G29*$V$6+$W$6*PRIX!H29+PRIX!I29*$X$6) -> 42085.772 | G25: =IF(B25="","",'Historique détail'!U28) -> 43650.544 | H25: =IF(B25="","",(G25-F25)/F25) -> 0.037180538 | I25: =IF(H25="","",(G25-C25)/C25) -> 0.16502352
B26: =IF(ARBITRAGES!E30=0,"",ARBITRAGES!E30) -> 45594 | C26: =IF(F26="","",C25) -> 37467.522 | D26: =IF(F26="","",PRIX!B25) -> 64000 | E26: =IF(F26="","",($F$4/$D$4)*D26) -> 38062.244 | F26: =IF(B26="","",PRIX!B30*$Q$6+$R$6*PRIX!C30+PRIX!D30*$S$6+$T$6*PRIX!E30+PRIX!F30*$U$6+PRIX!G30*$V$6+$W$6*PRIX!H30+PRIX!I30*$X$6) -> 41940.318 | G26: =IF(B26="","",'Historique détail'!U29) -> 44302.285 | H26: =IF(B26="","",(G26-F26)/F26) -> 0.056317336 | I26: =IF(H26="","",(G26-C26)/C26) -> 0.18241833
B27: =IF(ARBITRAGES!E31=0,"",ARBITRAGES!E31) -> 45595 | C27: =IF(F27="","",C26) -> 37467.522 | D27: =IF(F27="","",PRIX!B26) -> 63600 | E27: =IF(F27="","",($F$4/$D$4)*D27) -> 37824.355 | F27: =IF(B27="","",PRIX!B31*$Q$6+$R$6*PRIX!C31+PRIX!D31*$S$6+$T$6*PRIX!E31+PRIX!F31*$U$6+PRIX!G31*$V$6+$W$6*PRIX!H31+PRIX!I31*$X$6) -> 39504.875 | G27: =IF(B27="","",'Historique détail'!U30) -> 44166.08 | H27: =IF(B27="","",(G27-F27)/F27) -> 0.11799065 | I27: =IF(H27="","",(G27-C27)/C27) -> 0.17878307
B28: =IF(ARBITRAGES!E32=0,"",ARBITRAGES!E32) -> 45598 | C28: =IF(F28="","",C27) -> 37467.522 | D28: =IF(F28="","",PRIX!B27) -> 61100 | E28: =IF(F28="","",($F$4/$D$4)*D28) -> 36337.549 | F28: =IF(B28="","",PRIX!B32*$Q$6+$R$6*PRIX!C32+PRIX!D32*$S$6+$T$6*PRIX!E32+PRIX!F32*$U$6+PRIX!G32*$V$6+$W$6*PRIX!H32+PRIX!I32*$X$6) -> 38160.91 | G28: =IF(B28="","",'Historique détail'!U31) -> 41963.675 | H28: =IF(B28="","",(G28-F28)/F28) -> 0.09965079 | I28: =IF(H28="","",(G28-C28)/C28) -> 0.12000136
... B30: =IF(ARBITRAGES!E34=0,"",ARBITRAGES!E34) -> 45602 | C30: =IF(F30="","",C29) -> 37467.522 | D30: =IF(F30="","",PRIX!B29) -> 67000 | E30: =IF(F30="","",($F$4/$D$4)*D30) -> 39846.412 | F30: =IF(B30="","",PRIX!B34*$Q$6+$R$6*PRIX!C34+PRIX!D34*$S$6+$T$6*PRIX!E34+PRIX!F34*$U$6+PRIX!G34*$V$6+$W$6*PRIX!H34+PRIX!I34*$X$6) -> 42788.243 | G30: =IF(B30="","",'Historique détail'!U33) -> 40932.405 | H30: =IF(B30="","",(G30-F30)/F30) -> -0.043372606 | I30: =IF(H30="","",(G30-C30)/C30) -> 0.092476982
B31: =IF(ARBITRAGES!E36=0,"",ARBITRAGES!E36) -> 45576 | C31: =IF(F31="","",C30) -> 37467.522 | D31: =IF(F31="","",PRIX!B30) -> 72500 | E31: =IF(F31="","",($F$4/$D$4)*D31) -> 43117.386 | F31: =IF(B31="","",PRIX!B36*$Q$6+$R$6*PRIX!C36+PRIX!D36*$S$6+$T$6*PRIX!E36+PRIX!F36*$U$6+PRIX!G36*$V$6+$W$6*PRIX!H36+PRIX!I36*$X$6) -> 50465.379 | G31: =IF(B31="","",'Historique détail'!U35) -> 50381.221 | H31: =IF(B31="","",(G31-F31)/F31) -> -0.0016676361 | I31: =IF(H31="","",(G31-C31)/C31) -> 0.34466384
B32: =IF(ARBITRAGES!E37=0,"",ARBITRAGES!E37) -> 45608 | C32: =IF(F32="","",C31) -> 37467.522 | D32: =IF(F32="","",PRIX!B53) -> 92000 | E32: =IF(F32="","",($F$4/$D$4)*D32) -> 54714.476 | F32: =IF(B32="","",PRIX!B37*$Q$6+$R$6*PRIX!C37+PRIX!D37*$S$6+$T$6*PRIX!E37+PRIX!F37*$U$6+PRIX!G37*$V$6+$W$6*PRIX!H37+PRIX!I37*$X$6) -> 51901.244 | G32: =IF(B32="","",'Historique détail'!U36) -> 52869.461 | H32: =IF(B32="","",(G32-F32)/F32) -> 0.018654986 | I32: =IF(H32="","",(G32-C32)/C32) -> 0.4110744
B33: =IF(ARBITRAGES!E38=0,"",ARBITRAGES!E38) -> 45609 | C33: =IF(F33="","",C32) -> 37467.522 | D33: =IF(F33="","",PRIX!B54) -> 94000 | E33: =IF(F33="","",($F$4/$D$4)*D33) -> 55903.921 | F33: =IF(B33="","",PRIX!B38*$Q$6+$R$6*PRIX!C38+PRIX!D38*$S$6+$T$6*PRIX!E38+PRIX!F38*$U$6+PRIX!G38*$V$6+$W$6*PRIX!H38+PRIX!I38*$X$6) -> 48980.286 | G33: =IF(B33="","",'Historique détail'!U37) -> 54208.656 | H33: =IF(B33="","",(G33-F33)/F33) -> 0.10674437 | I33: =IF(H33="","",(G33-C33)/C33) -> 0.44681723
B34: =IF(ARBITRAGES!E41=0,"",ARBITRAGES!E41) -> 45610 | C34: =IF(F34="","",C33) -> 37467.522 | D34: =IF(F34="","",PRIX!B55) -> 88000 | E34: =IF(F34="","",($F$4/$D$4)*D34) -> 52335.586 | F34: =IF(B34="","",PRIX!B41*$Q$6+$R$6*PRIX!C41+PRIX!D41*$S$6+$T$6*PRIX!E41+PRIX!F41*$U$6+PRIX!G41*$V$6+$W$6*PRIX!H41+PRIX!I41*$X$6) -> 51650.258 | G34: =IF(B34="","",'Historique détail'!U40) -> 51415.192 | H34: =IF(B34="","",(G34-F34)/F34) -> -0.0045511073 | I34: =IF(H34="","",(G34-C34)/C34) -> 0.3722603
B35: =IF(ARBITRAGES!E42=0,"",ARBITRAGES!E42) -> 45615 | C35: =IF(F35="","",C34) -> 37467.522 | D35: =IF(F35="","",PRIX!B48) -> 96000 | E35: =IF(F35="","",($F$4/$D$4)*D35) -> 57093.366 | F35: =IF(B35="","",PRIX!B42*$Q$6+$R$6*PRIX!C42+PRIX!D42*$S$6+$T$6*PRIX!E42+PRIX!F42*$U$6+PRIX!G42*$V$6+$W$6*PRIX!H42+PRIX!I42*$X$6) -> 51650.258 | G35: =IF(B35="","",'Historique détail'!U41) -> 53867.707 | H35: =IF(B35="","",(G35-F35)/F35) -> 0.04293199 | I35: =IF(H35="","",(G35-C35)/C35) -> 0.43771737
B36: =IF(ARBITRAGES!E44=0,"",ARBITRAGES!E44) -> 45619 | C36: =IF(F36="","",C35) -> 37467.522 | D36: =IF(F36="","",PRIX!B49) -> 93000 | E36: =IF(F36="","",($F$4/$D$4)*D36) -> 55309.199 | F36: =IF(B36="","",PRIX!B44*$Q$6+$R$6*PRIX!C44+PRIX!D44*$S$6+$T$6*PRIX!E44+PRIX!F44*$U$6+PRIX!G44*$V$6+$W$6*PRIX!H44+PRIX!I44*$X$6) -> 56216.258 | G36: =IF(B36="","",'Historique détail'!U43) -> 58333.004 | H36: =IF(B36="","",(G36-F36)/F36) -> 0.037653627 | I36: =IF(H36="","",(G36-C36)/C36) -> 0.55689519
B37: =IF(ARBITRAGES!E45=0,"",ARBITRAGES!E45) -> 45622 | C37: =IF(F37="","",C36) -> 37467.522 | D37: =IF(F37="","",PRIX!B50) -> 89000 | E37: =IF(F37="","",($F$4/$D$4)*D37) -> 52930.308 | F37: =IF(B37="","",PRIX!B45*$Q$6+$R$6*PRIX!C45+PRIX!D45*$S$6+$T$6*PRIX!E45+PRIX!F45*$U$6+PRIX!G45*$V$6+$W$6*PRIX!H45+PRIX!I45*$X$6) -> 52780.589 | G37: =IF(B37="","",'Historique détail'!U44) -> 58333.004 | H37: =IF(B37="","",(G37-F37)/F37) -> 0.10519805 | I37: =IF(H37="","",(G37-C37)/C37) -> 0.55689519
B38: =IF(ARBITRAGES!E46=0,"",ARBITRAGES!E46) -> 45630 | C38: =IF(F38="","",C37) -> 37467.522 | D38: =IF(F38="","",PRIX!B51) -> 92000 | E38: =IF(F38="","",($F$4/$D$4)*D38) -> 54714.476 | F38: =IF(B38="","",PRIX!B46*$Q$6+$R$6*PRIX!C46+PRIX!D46*$S$6+$T$6*PRIX!E46+PRIX!F46*$U$6+PRIX!G46*$V$6+$W$6*PRIX!H46+PRIX!I46*$X$6) -> 58525.642 | G38: =IF(B38="","",'Historique détail'!U45) -> 55137.786 | H38: =IF(B38="","",(G38-F38)/F38) -> -0.057886684 | I38: =IF(H38="","",(G38-C38)/C38) -> 0.47161552
B39: =IF(ARBITRAGES!E47=0,"",ARBITRAGES!E47) -> 45636 | C39: =IF(F39="","",C38) -> 37467.522 | D39: =IF(F39="","",PRIX!B52) -> 90000 | E39: =IF(F39="","",($F$4/$D$4)*D39) -> 53525.031 | F39: =IF(B39="","",PRIX!B47*$Q$6+$R$6*PRIX!C47+PRIX!D47*$S$6+$T$6*PRIX!E47+PRIX!F47*$U$6+PRIX!G47*$V$6+$W$6*PRIX!H47+PRIX!I47*$X$6) -> 57307.054 | G39: =IF(B39="","",'Historique détail'!U46) -> 61473.762 | H39: =IF(B39="","",(G39-F39)/F39) -> 0.072708467 | I39: =IF(H39="","",(G39-C39)/C39) -> 0.64072134
B40: =IF(ARBITRAGES!E48=0,"",ARBITRAGES!E48) -> 45644 | C40: =IF(F40="","",C39) -> 37467.522 | D40: =IF(F40="","",PRIX!B53) -> 92000 | E40: =IF(F40="","",($F$4/$D$4)*D40) -> 54714.476 | F40: =IF(B40="","",PRIX!B48*$Q$6+$R$6*PRIX!C48+PRIX!D48*$S$6+$T$6*PRIX!E48+PRIX!F48*$U$6+PRIX!G48*$V$6+$W$6*PRIX!H48+PRIX!I48*$X$6) -> 54045.762 | G40: =IF(B40="","",'Historique détail'!U47) -> 60076.062 | H40: =IF(B40="","",(G40-F40)/F40) -> 0.11157768 | I40: =IF(H40="","",(G40-C40)/C40) -> 0.60341703
B41: =IF(ARBITRAGES!E49=0,"",ARBITRAGES!E49) -> 45646 | C41: =IF(F41="","",C40) -> 37467.522 | D41: =IF(F41="","",PRIX!B54) -> 94000 | E41: =IF(F41="","",($F$4/$D$4)*D41) -> 55903.921 | F41: =IF(B41="","",PRIX!B49*$Q$6+$R$6*PRIX!C49+PRIX!D49*$S$6+$T$6*PRIX!E49+PRIX!F49*$U$6+PRIX!G49*$V$6+$W$6*PRIX!H49+PRIX!I49*$X$6) -> 51484.633 | G41: =IF(B41="","",'Historique détail'!U48) -> 56800.476 | H41: =IF(B41="","",(G41-F41)/F41) -> 0.10325108 | I41: =IF(H41="","",(G41-C41)/C41) -> 0.51599236
B42: =IF(ARBITRAGES!E50=0,"",ARBITRAGES!E50) -> 45658 | C42: =IF(F42="","",C41) -> 37467.522 | D42: =IF(F42="","",PRIX!B50) -> 89000 | E42: =IF(F42="","",($F$4/$D$4)*D42) -> 52930.308 | F42: =IF(B42="","",PRIX!B50*$Q$6+$R$6*PRIX!C50+PRIX!D50*$S$6+$T$6*PRIX!E50+PRIX!F50*$U$6+PRIX!G50*$V$6+$W$6*PRIX!H50+PRIX!I50*$X$6) -> 50770.602 | G42: =IF(B42="","",'Historique détail'!U49) -> 54086.409 | H42: =IF(B42="","",(G42-F42)/F42) -> 0.065309584 | I42: =IF(H42="","",(G42-C42)/C42) -> 0.44355449
B43: =IF(ARBITRAGES!E51=0,"",ARBITRAGES!E51) -> 45666 | C43: =IF(F43="","",C42) -> 37467.522 | D43: =IF(F43="","",PRIX!B51) -> 92000 | E43: =IF(F43="","",($F$4/$D$4)*D43) -> 54714.476 | F43: =IF(B43="","",PRIX!B51*$Q$6+$R$6*PRIX!C51+PRIX!D51*$S$6+$T$6*PRIX!E51+PRIX!F51*$U$6+PRIX!G51*$V$6+$W$6*PRIX!H51+PRIX!I51*$X$6) -> 53187.099 | G43: =IF(B43="","",'Historique détail'!U50) -> 52919.583 | H43: =IF(B43="","",(G43-F43)/F43) -> -0.0050297173 | I43: =IF(H43="","",(G43-C43)/C43) -> 0.41241215
B44: =IF(ARBITRAGES!E52=0,"",ARBITRAGES!E52) -> 45676 | C44: =IF(F44="","",C43) -> 37467.522 | D44: =IF(F44="","",PRIX!B52) -> 90000 | E44: =IF(F44="","",($F$4/$D$4)*D44) -> 53525.031 | F44: =IF(B44="","",PRIX!B52*$Q$6+$R$6*PRIX!C52+PRIX!D52*$S$6+$T$6*PRIX!E52+PRIX!F52*$U$6+PRIX!G52*$V$6+$W$6*PRIX!H52+PRIX!I52*$X$6) -> 52373.094 | G44: =IF(B44="","",'Historique détail'!U51) -> 55303.265 | H44: =IF(B44="","",(G44-F44)/F44) -> 0.055948024 | I44: =IF(H44="","",(G44-C44)/C44) -> 0.47603212
B45: =IF(ARBITRAGES!E53=0,"",ARBITRAGES!E53) -> 45677 | C45: =IF(F45="","",C44) -> 37467.522 | D45: =IF(F45="","",PRIX!B53) -> 92000 | E45: =IF(F45="","",($F$4/$D$4)*D45) -> 54714.476 | F45: =IF(B45="","",PRIX!B53*$Q$6+$R$6*PRIX!C53+PRIX!D53*$S$6+$T$6*PRIX!E53+PRIX!F53*$U$6+PRIX!G53*$V$6+$W$6*PRIX!H53+PRIX!I53*$X$6) -> 52375.969 | G45: =IF(B45="","",'Historique détail'!U52) -> 54210.272 | H45: =IF(B45="","",(G45-F45)/F45) -> 0.035021856 | I45: =IF(H45="","",(G45-C45)/C45) -> 0.44686038
B46: =IF(ARBITRAGES!E54=0,"",ARBITRAGES!E54) -> 45718 | C46: =IF(F46="","",C45) -> 37467.522 | D46: =IF(F46="","",PRIX!B54) -> 94000 | E46: =IF(F46="","",($F$4/$D$4)*D46) -> 55903.921 | F46: =IF(B46="","",PRIX!B54*$Q$6+$R$6*PRIX!C54+PRIX!D54*$S$6+$T$6*PRIX!E54+PRIX!F54*$U$6+PRIX!G54*$V$6+$W$6*PRIX!H54+PRIX!I54*$X$6) -> 48697.254 | G46: =IF(B46="","",'Historique détail'!U53) -> 53954.968 | H46: =IF(B46="","",(G46-F46)/F46) -> 0.10796736 | I46: =IF(H46="","",(G46-C46)/C46) -> 0.44004636
B47: =IF(ARBITRAGES!E55=0,"",ARBITRAGES!E55) -> 45719 | C47: =IF(F47="","",C46) -> 37467.522 | D47: =IF(F47="","",PRIX!B55) -> 88000 | E47: =IF(F47="","",($F$4/$D$4)*D47) -> 52335.586 | F47: =IF(B47="","",PRIX!B55*$Q$6+$R$6*PRIX!C55+PRIX!D55*$S$6+$T$6*PRIX!E55+PRIX!F55*$U$6+PRIX!G55*$V$6+$W$6*PRIX!H55+PRIX!I55*$X$6) -> 44402.18 | G47: =IF(B47="","",'Historique détail'!U54) -> 50501.989 | H47: =IF(B47="","",(G47-F47)/F47) -> 0.13737633 | I47: =IF(H47="","",(G47-C47)/C47) -> 0.34788709
B48: =IF(ARBITRAGES!E59=0,"",ARBITRAGES!E59) -> 45720 | C48: =IF(F48="","",C47) -> 37467.522 | D48: =IF(F48="","",PRIX!B59) -> 86000 | E48: =IF(F48="","",($F$4/$D$4)*D48) -> 51146.141 | F48: =IF(B48="","",PRIX!B59*$Q$6+$R$6*PRIX!C59+PRIX!D59*$S$6+$T$6*PRIX!E59+PRIX!F59*$U$6+PRIX!G59*$V$6+$W$6*PRIX!H59+PRIX!I59*$X$6) -> 42086.609 | G48: =IF(B48="","",'Historique détail'!U58) -> 46028.676 | H48: =IF(B48="","",(G48-F48)/F48) -> 0.093665588 | I48: =IF(H48="","",(G48-C48)/C48) -> 0.22849535
B49: =IF(ARBITRAGES!E60=0,"",ARBITRAGES!E60) -> 45725 | C49: =IF(F49="","",C48) -> 37467.522 | D49: =IF(F49="","",PRIX!B60) -> 85000 | E49: =IF(F49="","",($F$4/$D$4)*D49) -> 50551.418 | F49: =IF(B49="","",PRIX!B60*$Q$6+$R$6*PRIX!C60+PRIX!D60*$S$6+$T$6*PRIX!E60+PRIX!F60*$U$6+PRIX!G60*$V$6+$W$6*PRIX!H60+PRIX!I60*$X$6) -> 40153.06 | G49: =IF(B49="","",'Historique détail'!U59) -> 44004.982 | H49: =IF(B49="","",(G49-F49)/F49) -> 0.095930969 | I49: =IF(H49="","",(G49-C49)/C49) -> 0.1744834
B50: =IF(ARBITRAGES!E61=0,"",ARBITRAGES!E61) -> 45734 | C50: =IF(F50="","",C49) -> 37467.522 | D50: =IF(F50="","",PRIX!B61) -> 93000 | E50: =IF(F50="","",($F$4/$D$4)*D50) -> 55309.199 | F50: =IF(B50="","",PRIX!B61*$Q$6+$R$6*PRIX!C61+PRIX!D61*$S$6+$T$6*PRIX!E61+PRIX!F61*$U$6+PRIX!G61*$V$6+$W$6*PRIX!H61+PRIX!I61*$X$6) -> 41409.604 | G50: =IF(B50="","",'Historique détail'!U60) -> 42004.476 | H50: =IF(B50="","",(G50-F50)/F50) -> 0.014365554 | I50: =IF(H50="","",(G50-C50)/C50) -> 0.12109033
B51: =IF(ARBITRAGES!E62=0,"",ARBITRAGES!E62) -> 45749 | C51: =IF(F51="","",C50) -> 37467.522 | D51: =IF(F51="","",PRIX!B62) -> 87000 | E51: =IF(F51="","",($F$4/$D$4)*D51) -> 51740.863 | F51: =IF(B51="","",PRIX!B62*$Q$6+$R$6*PRIX!C62+PRIX!D62*$S$6+$T$6*PRIX!E62+PRIX!F62*$U$6+PRIX!G62*$V$6+$W$6*PRIX!H62+PRIX!I62*$X$6) -> 38153.482 | G51: =IF(B51="","",'Historique détail'!U61) -> 43548.663 | H51: =IF(B51="","",(G51-F51)/F51) -> 0.14140731 | I51: =IF(H51="","",(G51-C51)/C51) -> 0.16230435
B52: =IF(ARBITRAGES!E63=0,"",ARBITRAGES!E63) -> 45751 | C52: =IF(F52="","",C51) -> 37467.522 | D52: =IF(F52="","",PRIX!B63) -> 83000 | E52: =IF(F52="","",($F$4/$D$4)*D52) -> 49361.973 | F52: =IF(B52="","",PRIX!B63*$Q$6+$R$6*PRIX!C63+PRIX!D63*$S$6+$T$6*PRIX!E63+PRIX!F63*$U$6+PRIX!G63*$V$6+$W$6*PRIX!H63+PRIX!I63*$X$6) -> 37044.246 | G52: =IF(B52="","",'Historique détail'!U62) -> 40154.824 | H52: =IF(B52="","",(G52-F52)/F52) -> 0.083969245 | I52: =IF(H52="","",(G52-C52)/C52) -> 0.071723505
B53: =IF(ARBITRAGES!E65=0,"",ARBITRAGES!E65) -> 45753 | C53: =IF(F53="","",C52) -> 37467.522 | D53: =IF(F53="","",PRIX!B66) -> 79000 | E53: =IF(F53="","",($F$4/$D$4)*D53) -> 46983.083 | F53: =IF(B53="","",PRIX!B65*$Q$6+$R$6*PRIX!C65+PRIX!D65*$S$6+$T$6*PRIX!E65+PRIX!F65*$U$6+PRIX!G65*$V$6+$W$6*PRIX!H65+PRIX!I65*$X$6) -> 34862.203 | G53: =IF(B53="","",'Historique détail'!U64) -> 36867.236 | H53: =IF(B53="","",(G53-F53)/F53) -> 0.05751307 | I53: =IF(H53="","",(G53-C53)/C53) -> -0.016021506
B54: =IF(ARBITRAGES!E66=0,"",ARBITRAGES!E66) -> 45754 | C54: =IF(F54="","",C53) -> 37467.522 | D54: =IF(F54="","",PRIX!B65) -> 80000 | E54: =IF(F54="","",($F$4/$D$4)*D54) -> 47577.805 | F54: =IF(B54="","",PRIX!B66*$Q$6+$R$6*PRIX!C66+PRIX!D66*$S$6+$T$6*PRIX!E66+PRIX!F66*$U$6+PRIX!G66*$V$6+$W$6*PRIX!H66+PRIX!I66*$X$6) -> 34584.894 | G54: =IF(B54="","",'Historique détail'!U65) -> 36887.236 | H54: =IF(B54="","",(G54-F54)/F54) -> 0.066570719 | I54: =IF(H54="","",(G54-C54)/C54) -> -0.015487711
B55: =IF(ARBITRAGES!E67=0,"",ARBITRAGES!E67) -> 45756 | C55: =IF(F55="","",C54) -> 37467.522 | D55: =IF(F55="","",PRIX!B66) -> 79000 | E55: =IF(F55="","",($F$4/$D$4)*D55) -> 46983.083 | F55: =IF(B55="","",PRIX!B67*$Q$6+$R$6*PRIX!C67+PRIX!D67*$S$6+$T$6*PRIX!E67+PRIX!F67*$U$6+PRIX!G67*$V$6+$W$6*PRIX!H67+PRIX!I67*$X$6) -> 34307.585 | G55: =IF(B55="","",'Historique détail'!U66) -> 36631.223 | H55: =IF(B55="","",(G55-F55)/F55) -> 0.067729562 | I55: =IF(H55="","",(G55-C55)/C55) -> -0.022320629
B56: =IF(ARBITRAGES!E69=0,"",ARBITRAGES!E69) -> 45757 | C56: =IF(F56="","",C55) -> 37467.522 | D56: =IF(F56="","",PRIX!B69) -> 80000 | E56: =IF(F56="","",($F$4/$D$4)*D56) -> 47577.805 | F56: =IF(B56="","",PRIX!B69*$Q$6+$R$6*PRIX!C69+PRIX!D69*$S$6+$T$6*PRIX!E69+PRIX!F69*$U$6+PRIX!G69*$V$6+$W$6*PRIX!H69+PRIX!I69*$X$6) -> 36121.832 | G56: =IF(B56="","",'Historique détail'!U68) -> 38502.144 | H56: =IF(B56="","",(G56-F56)/F56) -> 0.065896765 | I56: =IF(H56="","",(G56-C56)/C56) -> 0.027613835
B57: =IF(ARBITRAGES!E70=0,"",ARBITRAGES!E70) -> 45758 | C57: =IF(F57="","",C56) -> 37467.522 | D57: =IF(F57="","",PRIX!B70) -> 86000 | E57: =IF(F57="","",($F$4/$D$4)*D57) -> 51146.141 | F57: =IF(B57="","",PRIX!B70*$Q$6+$R$6*PRIX!C70+PRIX!D70*$S$6+$T$6*PRIX!E70+PRIX!F70*$U$6+PRIX!G70*$V$6+$W$6*PRIX!H70+PRIX!I70*$X$6) -> 37785.686 | G57: =IF(B57="","",'Historique détail'!U69) -> 38493.939 | H57: =IF(B57="","",(G57-F57)/F57) -> 0.018743957 | I57: =IF(H57="","",(G57-C57)/C57) -> 0.02739485
B58: =IF(ARBITRAGES!E71=0,"",ARBITRAGES!E71) -> 45760 | C58: =IF(F58="","",C57) -> 37467.522 | D58: =IF(F58="","",PRIX!B71) -> 86000 | E58: =IF(F58="","",($F$4/$D$4)*D58) -> 51146.141 | F58: =IF(B58="","",PRIX!B71*$Q$6+$R$6*PRIX!C71+PRIX!D71*$S$6+$T$6*PRIX!E71+PRIX!F71*$U$6+PRIX!G71*$V$6+$W$6*PRIX!H71+PRIX!I71*$X$6) -> 37785.686 | G58: =IF(B58="","",'Historique détail'!U70) -> 40128.976 | H58: =IF(B58="","",(G58-F58)/F58) -> 0.062015286 | I58: =IF(H58="","",(G58-C58)/C58) -> 0.071033627
B59: =IF(ARBITRAGES!E73=0,"",ARBITRAGES!E73) -> 45779 | C59: =IF(F59="","",C58) -> 37467.522 | D59: =IF(F59="","",PRIX!B72) -> 93000 | E59: =IF(F59="","",($F$4/$D$4)*D59) -> 55309.199 | F59: =IF(B59="","",PRIX!B73*$Q$6+$R$6*PRIX!C73+PRIX!D73*$S$6+$T$6*PRIX!E73+PRIX!F73*$U$6+PRIX!G73*$V$6+$W$6*PRIX!H73+PRIX!I73*$X$6) -> 41135.875 | G59: =IF(B59="","",'Historique détail'!U72) -> 44107.819 | H59: =IF(B59="","",(G59-F59)/F59) -> 0.072247006 | I59: =IF(H59="","",(G59-C59)/C59) -> 0.1772281
B60: =IF(ARBITRAGES!E76=0,"",ARBITRAGES!E76) -> 45054 | C60: =IF(F60="","",C59) -> 37467.522 | D60: =IF(F60="","",PRIX!B73) -> 93000 | E60: =IF(F60="","",($F$4/$D$4)*D60) -> 55309.199 | F60: =IF(B60="","",PRIX!B76*$Q$6+$R$6*PRIX!C76+PRIX!D76*$S$6+$T$6*PRIX!E76+PRIX!F76*$U$6+PRIX!G76*$V$6+$W$6*PRIX!H76+PRIX!I76*$X$6) -> 47384.538 | G60: =IF(B60="","",'Historique détail'!U75) -> 51104.187 | H60: =IF(B60="","",(G60-F60)/F60) -> 0.078499217 | I60: =IF(H60="","",(G60-C60)/C60) -> 0.36395963
B61: =IF(ARBITRAGES!E77=0,"",ARBITRAGES!E77) -> 45786 | C61: =IF(F61="","",C60) -> 37467.522 | D61: =IF(F61="","",PRIX!B74) -> 104000 | E61: =IF(F61="","",($F$4/$D$4)*D61) -> 61851.147 | F61: =IF(B61="","",PRIX!B77*$Q$6+$R$6*PRIX!C77+PRIX!D77*$S$6+$T$6*PRIX!E77+PRIX!F77*$U$6+PRIX!G77*$V$6+$W$6*PRIX!H77+PRIX!I77*$X$6) -> 47384.538 | G61: =IF(B61="","",'Historique détail'!U76) -> 51062.167 | H61: =IF(B61="","",(G61-F61)/F61) -> 0.07761243 | I61: =IF(H61="","",(G61-C61)/C61) -> 0.36283813
B62: =IF(ARBITRAGES!E78=0,"",ARBITRAGES!E78) -> 45789 | C62: =IF(F62="","",C61) -> 37467.522 | D62: =IF(F62="","",PRIX!B75) -> 104000 | E62: =IF(F62="","",($F$4/$D$4)*D62) -> 61851.147 | F62: =IF(B62="","",PRIX!B78*$Q$6+$R$6*PRIX!C78+PRIX!D78*$S$6+$T$6*PRIX!E78+PRIX!F78*$U$6+PRIX!G78*$V$6+$W$6*PRIX!H78+PRIX!I78*$X$6) -> 49045.584 | G62: =IF(B62="","",'Historique détail'!U77) -> 52809.097 | H62: =IF(B62="","",(G62-F62)/F62) -> 0.076735006 | I62: =IF(H62="","",(G62-C62)/C62) -> 0.4094633
B63: =IF(ARBITRAGES!E79=0,"",ARBITRAGES!E79) -> 45790 | C63: =IF(F63="","",C62) -> 37467.522 | D63: =IF(F63="","",PRIX!B76) -> 104000 | E63: =IF(F63="","",($F$4/$D$4)*D63) -> 61851.147 | F63: =IF(B63="","",PRIX!B79*$Q$6+$R$6*PRIX!C79+PRIX!D79*$S$6+$T$6*PRIX!E79+PRIX!F79*$U$6+PRIX!G79*$V$6+$W$6*PRIX!H79+PRIX!I79*$X$6) -> 48130.625 | G63: =IF(B63="","",'Historique détail'!U78) -> 51891.139 | H63: =IF(B63="","",(G63-F63)/F63) -> 0.078131416 | I63: =IF(H63="","",(G63-C63)/C63) -> 0.38496321
B64: =IF(ARBITRAGES!E80=0,"",ARBITRAGES!E80) -> 45808 | C64: =IF(F64="","",C63) -> 37467.522 | D64: =IF(F64="","",PRIX!B77) -> 104000 | E64: =IF(F64="","",($F$4/$D$4)*D64) -> 61851.147 | F64: =IF(B64="","",PRIX!B80*$Q$6+$R$6*PRIX!C80+PRIX!D80*$S$6+$T$6*PRIX!E80+PRIX!F80*$U$6+PRIX!G80*$V$6+$W$6*PRIX!H80+PRIX!I80*$X$6) -> 46805.913 | G64: =IF(B64="","",'Historique détail'!U79) -> 50774.018 | H64: =IF(B64="","",(G64-F64)/F64) -> 0.084777857 | I64: =IF(H64="","",(G64-C64)/C64) -> 0.35514749
B65: =IF(ARBITRAGES!E82=0,"",ARBITRAGES!E82) -> 45817 | C65: =IF(F65="","",C64) -> 37467.522 | D65: =IF(F65="","",PRIX!B78) -> 104500 | E65: =IF(F65="","",($F$4/$D$4)*D65) -> 62148.508 | F65: =IF(B65="","",PRIX!B82*$Q$6+$R$6*PRIX!C82+PRIX!D82*$S$6+$T$6*PRIX!E82+PRIX!F82*$U$6+PRIX!G82*$V$6+$W$6*PRIX!H82+PRIX!I82*$X$6) -> 49729.506 | G65: =IF(B65="","",'Historique détail'!U81) -> 53721.829 | H65: =IF(B65="","",(G65-F65)/F65) -> 0.080280749 | I65: =IF(H65="","",(G65-C65)/C65) -> 0.43382391
B66: =IF(ARBITRAGES!E83=0,"",ARBITRAGES!E83) -> 45818 | C66: =IF(F66="","",C65) -> 37467.522 | D66: =IF(F66="","",PRIX!B79) -> 103000 | E66: =IF(F66="","",($F$4/$D$4)*D66) -> 61256.424 | F66: =IF(B66="","",PRIX!B83*$Q$6+$R$6*PRIX!C83+PRIX!D83*$S$6+$T$6*PRIX!E83+PRIX!F83*$U$6+PRIX!G83*$V$6+$W$6*PRIX!H83+PRIX!I83*$X$6) -> 49870.893 | G66: =IF(B66="","",'Historique détail'!U82) -> 53968.134 | H66: =IF(B66="","",(G66-F66)/F66) -> 0.082156958 | I66: =IF(H66="","",(G66-C66)/C66) -> 0.44039776
B67: =IF(ARBITRAGES!E87=0,"",ARBITRAGES!E87) -> 45831 | C67: =IF(F67="","",C66) -> 37467.522 | D67: =IF(F67="","",PRIX!B80) -> 103000 | E67: =IF(F67="","",($F$4/$D$4)*D67) -> 61256.424 | F67: =IF(B67="","",PRIX!B87*$Q$6+$R$6*PRIX!C87+PRIX!D87*$S$6+$T$6*PRIX!E87+PRIX!F87*$U$6+PRIX!G87*$V$6+$W$6*PRIX!H87+PRIX!I87*$X$6) -> 47115.973 | G67: =IF(B67="","",'Historique détail'!U86) -> 50252.423 | H67: =IF(B67="","",(G67-F67)/F67) -> 0.066568707 | I67: =IF(H67="","",(G67-C67)/C67) -> 0.34122623
B68: =IF(ARBITRAGES!E89=0,"",ARBITRAGES!E89) -> 45832 | C68: =IF(F68="","",C67) -> 37467.522 | D68: =IF(F68="","",PRIX!B81) -> 110000 | E68: =IF(F68="","",($F$4/$D$4)*D68) -> 65419.482 | F68: =IF(B68="","",PRIX!B89*$Q$6+$R$6*PRIX!C89+PRIX!D89*$S$6+$T$6*PRIX!E89+PRIX!F89*$U$6+PRIX!G89*$V$6+$W$6*PRIX!H89+PRIX!I89*$X$6) -> 46194.058 | G68: =IF(B68="","",'Historique détail'!U88) -> 49783.285 | H68: =IF(B68="","",(G68-F68)/F68) -> 0.077698893 | I68: =IF(H68="","",(G68-C68)/C68) -> 0.32870504
B69: =IF(ARBITRAGES!E90=0,"",ARBITRAGES!E90) -> 45847 | C69: =IF(F69="","",C68) -> 37467.522 | D69: =IF(F69="","",PRIX!B82) -> 110000 | E69: =IF(F69="","",($F$4/$D$4)*D69) -> 65419.482 | F69: =IF(B69="","",PRIX!B90*$Q$6+$R$6*PRIX!C90+PRIX!D90*$S$6+$T$6*PRIX!E90+PRIX!F90*$U$6+PRIX!G90*$V$6+$W$6*PRIX!H90+PRIX!I90*$X$6) -> 49211.164 | G69: =IF(B69="","",'Historique détail'!U89) -> 52535.112 | H69: =IF(B69="","",(G69-F69)/F69) -> 0.067544608 | I69: =IF(H69="","",(G69-C69)/C69) -> 0.40215071
B70: =IF(ARBITRAGES!E91=0,"",ARBITRAGES!E91) -> 45848 | C70: =IF(F70="","",C69) -> 37467.522 | D70: =IF(F70="","",PRIX!B91) -> 118000 | E70: =IF(F70="","",($F$4/$D$4)*D70) -> 70177.263 | F70: =IF(B70="","",PRIX!B91*$Q$6+$R$6*PRIX!C91+PRIX!D91*$S$6+$T$6*PRIX!E91+PRIX!F91*$U$6+PRIX!G91*$V$6+$W$6*PRIX!H91+PRIX!I91*$X$6) -> 52347.664 | G70: =IF(B70="","",'Historique détail'!U90) -> 55609.702 | H70: =IF(B70="","",(G70-F70)/F70) -> 0.062314877 | I70: =IF(H70="","",(G70-C70)/C70) -> 0.48421086
B71: =IF(ARBITRAGES!E92=0,"",ARBITRAGES!E92) -> 45849 | C71: =IF(F71="","",C69) -> 37467.522 | D71: =IF(F71="","",PRIX!B92) -> 118000 | E71: =IF(F71="","",($F$4/$D$4)*D71) -> 70177.263 | F71: =IF(B71="","",PRIX!B92*$Q$6+$R$6*PRIX!C92+PRIX!D92*$S$6+$T$6*PRIX!E92+PRIX!F92*$U$6+PRIX!G92*$V$6+$W$6*PRIX!H92+PRIX!I92*$X$6) -> 52347.664 | G71: =IF(B71="","",'Historique détail'!U91) -> 55610.384 | H71: =IF(B71="","",(G71-F71)/F71) -> 0.062327903 | I71: =IF(H71="","",(G71-C71)/C71) -> 0.48422906
B72: =IF(ARBITRAGES!E93=0,"",ARBITRAGES!E93) -> 45849 | C72: =IF(F72="","",C70) -> 37467.522 | D72: =IF(F72="","",PRIX!B93) -> 118000 | E72: =IF(F72="","",($F$4/$D$4)*D72) -> 70177.263 | F72: =IF(B72="","",PRIX!B93*$Q$6+$R$6*PRIX!C93+PRIX!D93*$S$6+$T$6*PRIX!E93+PRIX!F93*$U$6+PRIX!G93*$V$6+$W$6*PRIX!H93+PRIX!I93*$X$6) -> 52347.664 | G72: =IF(B72="","",'Historique détail'!U92) -> 55612.494 | H72: =IF(B72="","",(G72-F72)/F72) -> 0.062368205 | I72: =IF(H72="","",(G72-C72)/C72) -> 0.48428536
B73: =IF(ARBITRAGES!E94=0,"",ARBITRAGES!E94) -> 45850 | C73: =IF(F73="","",C72) -> 37467.522 | D73: =IF(F73="","",PRIX!B94) -> 118000 | E73: =IF(F73="","",($F$4/$D$4)*D73) -> 70177.263 | F73: =IF(B73="","",PRIX!B94*$Q$6+$R$6*PRIX!C94+PRIX!D94*$S$6+$T$6*PRIX!E94+PRIX!F94*$U$6+PRIX!G94*$V$6+$W$6*PRIX!H94+PRIX!I94*$X$6) -> 52347.664 | G73: =IF(B73="","",'Historique détail'!U93) -> 55614.848 | H73: =IF(B73="","",(G73-F73)/F73) -> 0.062413174 | I73: =IF(H73="","",(G73-C73)/C73) -> 0.48434819
B74: =IF(ARBITRAGES!E95=0,"",ARBITRAGES!E95) -> 45852 | C74: =IF(F74="","",C73) -> 37467.522 | D74: =IF(F74="","",PRIX!B95) -> 119500 | E74: =IF(F74="","",($F$4/$D$4)*D74) -> 71069.347 | F74: =IF(B74="","",PRIX!B95*$Q$6+$R$6*PRIX!C95+PRIX!D95*$S$6+$T$6*PRIX!E95+PRIX!F95*$U$6+PRIX!G95*$V$6+$W$6*PRIX!H95+PRIX!I95*$X$6) -> 54815.628 | G74: =IF(B74="","",'Historique détail'!U94) -> 58302.686 | H74: =IF(B74="","",(G74-F74)/F74) -> 0.063614316 | I74: =IF(H74="","",(G74-C74)/C74) -> 0.55608601
B75: =IF(ARBITRAGES!E96=0,"",ARBITRAGES!E96) -> 45852 | C75: =IF(F75="","",C74) -> 37467.522 | D75: =IF(F75="","",PRIX!B96) -> 119500 | E75: =IF(F75="","",($F$4/$D$4)*D75) -> 71069.347 | F75: =IF(B75="","",PRIX!B96*$Q$6+$R$6*PRIX!C96+PRIX!D96*$S$6+$T$6*PRIX!E96+PRIX!F96*$U$6+PRIX!G96*$V$6+$W$6*PRIX!H96+PRIX!I96*$X$6) -> 54815.628 | G75: =IF(B75="","",'Historique détail'!U95) -> 58315.193 | H75: =IF(B75="","",(G75-F75)/F75) -> 0.063842481 | I75: =IF(H75="","",(G75-C75)/C75) -> 0.55641982
B76: =IF(ARBITRAGES!E97=0,"",ARBITRAGES!E97) -> 45852 | C76: =IF(F76="","",C75) -> 37467.522 | D76: =IF(F76="","",PRIX!B97) -> 119500 | E76: =IF(F76="","",($F$4/$D$4)*D76) -> 71069.347 | F76: =IF(B76="","",PRIX!B97*$Q$6+$R$6*PRIX!C97+PRIX!D97*$S$6+$T$6*PRIX!E97+PRIX!F97*$U$6+PRIX!G97*$V$6+$W$6*PRIX!H97+PRIX!I97*$X$6) -> 54815.628 | G76: =IF(B76="","",'Historique détail'!U96) -> 58340.063 | H76: =IF(B76="","",(G76-F76)/F76) -> 0.064296176 | I76: =IF(H76="","",(G76-C76)/C76) -> 0.55708358
B77: =IF(ARBITRAGES!E98=0,"",ARBITRAGES!E98) -> 45852 | C77: =IF(F77="","",C76) -> 37467.522 | D77: =IF(F77="","",PRIX!B98) -> 119500 | E77: =IF(F77="","",($F$4/$D$4)*D77) -> 71069.347 | F77: =IF(B77="","",PRIX!B98*$Q$6+$R$6*PRIX!C98+PRIX!D98*$S$6+$T$6*PRIX!E98+PRIX!F98*$U$6+PRIX!G98*$V$6+$W$6*PRIX!H98+PRIX!I98*$X$6) -> 54815.628 | G77: =IF(B77="","",'Historique détail'!U97) -> 58344.862 | H77: =IF(B77="","",(G77-F77)/F77) -> 0.064383717 | I77: =IF(H77="","",(G77-C77)/C77) -> 0.55721166
B78: =IF(ARBITRAGES!E99=0,"",ARBITRAGES!E99) -> 45853 | C78: =IF(F78="","",C77) -> 37467.522 | D78: =IF(F78="","",PRIX!B99) -> 118000 | E78: =IF(F78="","",($F$4/$D$4)*D78) -> 70177.263 | F78: =IF(B78="","",PRIX!B99*$Q$6+$R$6*PRIX!C99+PRIX!D99*$S$6+$T$6*PRIX!E99+PRIX!F99*$U$6+PRIX!G99*$V$6+$W$6*PRIX!H99+PRIX!I99*$X$6) -> 53732.028 | G78: =IF(B78="","",'Historique détail'!U98) -> 57309.237 | H78: =IF(B78="","",(G78-F78)/F78) -> 0.066574993 | I78: =IF(H78="","",(G78-C78)/C78) -> 0.52957107
B79: =IF(ARBITRAGES!E100=0,"",ARBITRAGES!E100) -> 45854 | C79: =IF(F79="","",C78) -> 37467.522 | D79: =IF(F79="","",PRIX!B100) -> 119500 | E79: =IF(F79="","",($F$4/$D$4)*D79) -> 71069.347 | F79: =IF(B79="","",PRIX!B100*$Q$6+$R$6*PRIX!C100+PRIX!D100*$S$6+$T$6*PRIX!E100+PRIX!F100*$U$6+PRIX!G100*$V$6+$W$6*PRIX!H100+PRIX!I100*$X$6) -> 54815.628 | G79: =IF(B79="","",'Historique détail'!U99) -> 58367.673 | H79: =IF(B79="","",(G79-F79)/F79) -> 0.064799867 | I79: =IF(H79="","",(G79-C79)/C79) -> 0.55782049
B80: =IF(ARBITRAGES!E101=0,"",ARBITRAGES!E101) -> 45856 | C80: =IF(F80="","",C79) -> 37467.522 | D80: =IF(F80="","",PRIX!B101) -> 122000 | E80: =IF(F80="","",($F$4/$D$4)*D80) -> 72556.153 | F80: =IF(B80="","",PRIX!B101*$Q$6+$R$6*PRIX!C101+PRIX!D101*$S$6+$T$6*PRIX!E101+PRIX!F101*$U$6+PRIX!G101*$V$6+$W$6*PRIX!H101+PRIX!I101*$X$6) -> 56229.508 | G80: =IF(B80="","",'Historique détail'!U100) -> 59627.836 | H80: =IF(B80="","",(G80-F80)/F80) -> 0.060436733 | I80: =IF(H80="","",(G80-C80)/C80) -> 0.59145397
B81: =IF(ARBITRAGES!E102=0,"",ARBITRAGES!E102) -> 45856 | C81: =IF(F81="","",C80) -> 37467.522 | D81: =IF(F81="","",PRIX!B102) -> 122000 | E81: =IF(F81="","",($F$4/$D$4)*D81) -> 72556.153 | F81: =IF(B81="","",PRIX!B102*$Q$6+$R$6*PRIX!C102+PRIX!D102*$S$6+$T$6*PRIX!E102+PRIX!F102*$U$6+PRIX!G102*$V$6+$W$6*PRIX!H102+PRIX!I102*$X$6) -> 56385.034 | G81: =IF(B81="","",'Historique détail'!U101) -> 59793.417 | H81: =IF(B81="","",(G81-F81)/F81) -> 0.060448373 | I81: =IF(H81="","",(G81-C81)/C81) -> 0.5958733
B82: =IF(ARBITRAGES!E103=0,"",ARBITRAGES!E103) -> 45857 | C82: =IF(F82="","",C81) -> 37467.522 | D82: =IF(F82="","",PRIX!B103) -> 120000 | E82: =IF(F82="","",($F$4/$D$4)*D82) -> 71366.708 | F82: =IF(B82="","",PRIX!B103*$Q$6+$R$6*PRIX!C103+PRIX!D103*$S$6+$T$6*PRIX!E103+PRIX!F103*$U$6+PRIX!G103*$V$6+$W$6*PRIX!H103+PRIX!I103*$X$6) -> 56311.872 | G82: =IF(B82="","",'Historique détail'!U102) -> 59959.084 | H82: =IF(B82="","",(G82-F82)/F82) -> 0.064768066 | I82: =IF(H82="","",(G82-C82)/C82) -> 0.60029489
B83: =IF(ARBITRAGES!E104=0,"",ARBITRAGES!E104) -> 45858 | C83: =IF(F83="","",C82) -> 37467.522 | D83: =IF(F83="","",PRIX!B104) -> 120000 | E83: =IF(F83="","",($F$4/$D$4)*D83) -> 71366.708 | F83: =IF(B83="","",PRIX!B104*$Q$6+$R$6*PRIX!C104+PRIX!D104*$S$6+$T$6*PRIX!E104+PRIX!F104*$U$6+PRIX!G104*$V$6+$W$6*PRIX!H104+PRIX!I104*$X$6) -> 56354.288 | G83: =IF(B83="","",'Historique détail'!U103) -> 60002.077 | H83: =IF(B83="","",(G83-F83)/F83) -> 0.064729569 | I83: =IF(H83="","",(G83-C83)/C83) -> 0.60144239
B84: =IF(ARBITRAGES!E105=0,"",ARBITRAGES!E105) -> 45858 | C84: =IF(F84="","",C83) -> 37467.522 | D84: =IF(F84="","",PRIX!B105) -> 120000 | E84: =IF(F84="","",($F$4/$D$4)*D84) -> 71366.708 | F84: =IF(B84="","",PRIX!B105*$Q$6+$R$6*PRIX!C105+PRIX!D105*$S$6+$T$6*PRIX!E105+PRIX!F105*$U$6+PRIX!G105*$V$6+$W$6*PRIX!H105+PRIX!I105*$X$6) -> 56354.288 | G84: =IF(B84="","",'Historique détail'!U104) -> 60004.087 | H84: =IF(B84="","",(G84-F84)/F84) -> 0.064765237 | I84: =IF(H84="","",(G84-C84)/C84) -> 0.60149603
... B237: =IF(ARBITRAGES!E258=0,"",ARBITRAGES!E258) -> 46058 | C237: =IF(F237="","",C236) -> 37467.522 | D237: =IF(F237="","",PRIX!B258) -> 64000 | E237: =IF(F237="","",($F$4/$D$4)*D237) -> 38062.244 | F237: =IF(B237="","",PRIX!B258*$Q$6+$R$6*PRIX!C258+PRIX!D258*$S$6+$T$6*PRIX!E258+PRIX!F258*$U$6+PRIX!G258*$V$6+$W$6*PRIX!H258+PRIX!I258*$X$6) -> 28121.991 | G237: =IF(B237="","",'Historique détail'!U257) -> 37161.354 | H237: =IF(B237="","",(G237-F237)/F237) -> 0.32143395 | I237: =IF(H237="","",(G237-C237)/C237) -> -0.0081715604
B238: =IF(ARBITRAGES!E259=0,"",ARBITRAGES!E259) -> 46059 | C238: =IF(F238="","",C237) -> 37467.522 | D238: =IF(F238="","",59500) -> 59500 | E238: =IF(F238="","",($F$4/$D$4)*D238) -> 35385.993 | F238: =IF(B238="","",PRIX!B259*$Q$6+$R$6*PRIX!C259+PRIX!D259*$S$6+$T$6*PRIX!E259+PRIX!F259*$U$6+PRIX!G259*$V$6+$W$6*PRIX!H259+PRIX!I259*$X$6) -> 26828.54 | G238: =IF(B238="","",'Historique détail'!U258) -> 35761.941 | H238: =IF(B238="","",(G238-F238)/F238) -> 0.33298125 | I238: =IF(H238="","",(G238-C238)/C238) -> -0.04552157
B239: =IF(ARBITRAGES!E260=0,"",ARBITRAGES!E260) -> 46060 | C239: =IF(F239="","",C238) -> 37467.522 | D239: =IF(F239="","",PRIX!B260) -> 67000 | E239: =IF(F239="","",($F$4/$D$4)*D239) -> 39846.412 | F239: =IF(B239="","",PRIX!B260*$Q$6+$R$6*PRIX!C260+PRIX!D260*$S$6+$T$6*PRIX!E260+PRIX!F260*$U$6+PRIX!G260*$V$6+$W$6*PRIX!H260+PRIX!I260*$X$6) -> 29339.589 | G239: =IF(B239="","",'Historique détail'!U259) -> 38537.782 | H239: =IF(B239="","",(G239-F239)/F239) -> 0.31350791 | I239: =IF(H239="","",(G239-C239)/C239) -> 0.028565022
B240: =IF(ARBITRAGES!E261=0,"",ARBITRAGES!E261) -> 46060 | C240: =IF(F240="","",C239) -> 37467.522 | D240: =IF(F240="","",PRIX!B261) -> 67000 | E240: =IF(F240="","",($F$4/$D$4)*D240) -> 39846.412 | F240: =IF(B240="","",PRIX!B261*$Q$6+$R$6*PRIX!C261+PRIX!D261*$S$6+$T$6*PRIX!E261+PRIX!F261*$U$6+PRIX!G261*$V$6+$W$6*PRIX!H261+PRIX!I261*$X$6) -> 29339.589 | G240: =IF(B240="","",'Historique détail'!U260) -> 38562.882 | H240: =IF(B240="","",(G240-F240)/F240) -> 0.3143634 | I240: =IF(H240="","",(G240-C240)/C240) -> 0.029234932
B241: =IF(ARBITRAGES!E262=0,"",ARBITRAGES!E262) -> 46061 | C241: =IF(F241="","",C240) -> 37467.522 | D241: =IF(F241="","",PRIX!B262) -> 69000 | E241: =IF(F241="","",($F$4/$D$4)*D241) -> 41035.857 | F241: =IF(B241="","",PRIX!B262*$Q$6+$R$6*PRIX!C262+PRIX!D262*$S$6+$T$6*PRIX!E262+PRIX!F262*$U$6+PRIX!G262*$V$6+$W$6*PRIX!H262+PRIX!I262*$X$6) -> 30329.389 | G241: =IF(B241="","",'Historique détail'!U261) -> 39554.087 | H241: =IF(B241="","",(G241-F241)/F241) -> 0.30415048 | I241: =IF(H241="","",(G241-C241)/C241) -> 0.055689965
B242: =IF(ARBITRAGES!E263=0,"",ARBITRAGES!E263) -> 46061 | C242: =IF(F242="","",C241) -> 37467.522 | D242: =IF(F242="","",PRIX!B263) -> 69000 | E242: =IF(F242="","",($F$4/$D$4)*D242) -> 41035.857 | F242: =IF(B242="","",PRIX!B263*$Q$6+$R$6*PRIX!C263+PRIX!D263*$S$6+$T$6*PRIX!E263+PRIX!F263*$U$6+PRIX!G263*$V$6+$W$6*PRIX!H263+PRIX!I263*$X$6) -> 30329.389 | G242: =IF(B242="","",'Historique détail'!U262) -> 39557.526 | H242: =IF(B242="","",(G242-F242)/F242) -> 0.30426389 | I242: =IF(H242="","",(G242-C242)/C242) -> 0.055781773
B243: =IF(ARBITRAGES!E264=0,"",ARBITRAGES!E264) -> 46062 | C243: =IF(F243="","",C242) -> 37467.522 | D243: =IF(F243="","",PRIX!B264) -> 69000 | E243: =IF(F243="","",($F$4/$D$4)*D243) -> 41035.857 | F243: =IF(B243="","",PRIX!B264*$Q$6+$R$6*PRIX!C264+PRIX!D264*$S$6+$T$6*PRIX!E264+PRIX!F264*$U$6+PRIX!G264*$V$6+$W$6*PRIX!H264+PRIX!I264*$X$6) -> 30037.309 | G243: =IF(B243="","",'Historique détail'!U263) -> 39497.218 | H243: =IF(B243="","",(G243-F243)/F243) -> 0.31493863 | I243: =IF(H243="","",(G243-C243)/C243) -> 0.054172161
B244: =IF(ARBITRAGES!E265=0,"",ARBITRAGES!E265) -> 46063 | C244: =IF(F244="","",C243) -> 37467.522 | D244: =IF(F244="","",PRIX!B265) -> 66000 | E244: =IF(F244="","",($F$4/$D$4)*D244) -> 39251.689 | F244: =IF(B244="","",PRIX!B265*$Q$6+$R$6*PRIX!C265+PRIX!D265*$S$6+$T$6*PRIX!E265+PRIX!F265*$U$6+PRIX!G265*$V$6+$W$6*PRIX!H265+PRIX!I265*$X$6) -> 28663.301 | G244: =IF(B244="","",'Historique détail'!U264) -> 38119.993 | H244: =IF(B244="","",(G244-F244)/F244) -> 0.32992332 | I244: =IF(H244="","",(G244-C244)/C244) -> 0.017414307
B245: =IF(ARBITRAGES!E266=0,"",ARBITRAGES!E266) -> 46064 | C245: =IF(F245="","",C244) -> 37467.522 | D245: =IF(F245="","",PRIX!B266) -> 66700 | E245: =IF(F245="","",($F$4/$D$4)*D245) -> 39667.995 | F245: =IF(B245="","",PRIX!B266*$Q$6+$R$6*PRIX!C266+PRIX!D266*$S$6+$T$6*PRIX!E266+PRIX!F266*$U$6+PRIX!G266*$V$6+$W$6*PRIX!H266+PRIX!I266*$X$6) -> 28998.804 | G245: =IF(B245="","",'Historique détail'!U265) -> 38487.885 | H245: =IF(B245="","",(G245-F245)/F245) -> 0.32722318 | I245: =IF(H245="","",(G245-C245)/C245) -> 0.027233279
B246: =IF(ARBITRAGES!E267=0,"",ARBITRAGES!E267) -> 46065 | C246: =IF(F246="","",C245) -> 37467.522 | D246: =IF(F246="","",PRIX!B267) -> 67500 | E246: =IF(F246="","",($F$4/$D$4)*D246) -> 40143.773 | F246: =IF(B246="","",PRIX!B267*$Q$6+$R$6*PRIX!C267+PRIX!D267*$S$6+$T$6*PRIX!E267+PRIX!F267*$U$6+PRIX!G267*$V$6+$W$6*PRIX!H267+PRIX!I267*$X$6) -> 29736.897 | G246: =IF(B246="","",'Historique détail'!U266) -> 38787.841 | H246: =IF(B246="","",(G246-F246)/F246) -> 0.30436749 | I246: =IF(H246="","",(G246-C246)/C246) -> 0.035239047
B247: =IF(ARBITRAGES!E268=0,"",ARBITRAGES!E268) -> 46066 | C247: =IF(F247="","",C246) -> 37467.522 | D247: =IF(F247="","",PRIX!B268) -> 67500 | E247: =IF(F247="","",($F$4/$D$4)*D247) -> 40143.773 | F247: =IF(B247="","",PRIX!B268*$Q$6+$R$6*PRIX!C268+PRIX!D268*$S$6+$T$6*PRIX!E268+PRIX!F268*$U$6+PRIX!G268*$V$6+$W$6*PRIX!H268+PRIX!I268*$X$6) -> 29736.897 | G247: =IF(B247="","",'Historique détail'!U267) -> 38821.353 | H247: =IF(B247="","",(G247-F247)/F247) -> 0.30549441 | I247: =IF(H247="","",(G247-C247)/C247) -> 0.036133457
B248: =IF(ARBITRAGES!E269=0,"",ARBITRAGES!E269) | C248: =IF(F248="","",C247) | D248: =IF(F248="","",PRIX!B269) | E248: =IF(F248="","",($F$4/$D$4)*D248) | F248: =IF(B248="","",PRIX!B269*$Q$6+$R$6*PRIX!C269+PRIX!D269*$S$6+$T$6*PRIX!E269+PRIX!F269*$U$6+PRIX!G269*$V$6+$W$6*PRIX!H269+PRIX!I269*$X$6) | G248: =IF(B248="","",'Historique détail'!U268) | H248: =IF(B248="","",(G248-F248)/F248) | I248: =IF(H248="","",(G248-C248)/C248)
B249: =IF(ARBITRAGES!E270=0,"",ARBITRAGES!E270) | C249: =IF(F249="","",C248) | D249: =IF(F249="","",PRIX!B270) | E249: =IF(F249="","",($F$4/$D$4)*D249) | F249: =IF(B249="","",PRIX!B270*$Q$6+$R$6*PRIX!C270+PRIX!D270*$S$6+$T$6*PRIX!E270+PRIX!F270*$U$6+PRIX!G270*$V$6+$W$6*PRIX!H270+PRIX!I270*$X$6) | G249: =IF(B249="","",'Historique détail'!U269) | H249: =IF(B249="","",(G249-F249)/F249) | I249: =IF(H249="","",(G249-C249)/C249)
B250: =IF(ARBITRAGES!E271=0,"",ARBITRAGES!E271) | C250: =IF(F250="","",C249) | D250: =IF(F250="","",PRIX!B271) | E250: =IF(F250="","",($F$4/$D$4)*D250) | F250: =IF(B250="","",PRIX!B271*$Q$6+$R$6*PRIX!C271+PRIX!D271*$S$6+$T$6*PRIX!E271+PRIX!F271*$U$6+PRIX!G271*$V$6+$W$6*PRIX!H271+PRIX!I271*$X$6) | G250: =IF(B250="","",'Historique détail'!U270) | H250: =IF(B250="","",(G250-F250)/F250) | I250: =IF(H250="","",(G250-C250)/C250)
... B307: =IF(ARBITRAGES!E328=0,"",ARBITRAGES!E328) | C307: =IF(F307="","",C306) | D307: =IF(F307="","",PRIX!B328) | E307: =IF(F307="","",($F$4/$D$4)*D307) | F307: =IF(B307="","",PRIX!B328*$Q$6+$R$6*PRIX!C328+PRIX!D328*$S$6+$T$6*PRIX!E328+PRIX!F328*$U$6+PRIX!G328*$V$6+$W$6*PRIX!H328+PRIX!I328*$X$6) | G307: =IF(B307="","",'Historique détail'!U327) | H307: =IF(B307="","",(G307-F307)/F307) | I307: =IF(H307="","",(G307-C307)/C307)
B308: =IF(ARBITRAGES!E329=0,"",ARBITRAGES!E329) | C308: =IF(F308="","",C307) | D308: =IF(F308="","",PRIX!B329) | E308: =IF(F308="","",($F$4/PRIX!$B$3)*PRIX!B307) | F308: =IF(B308="","",PRIX!B329*$Q$6+$R$6*PRIX!C329+PRIX!D329*$S$6+$T$6*PRIX!E329+PRIX!F329*$U$6+PRIX!G329*$V$6+$W$6*PRIX!H329+PRIX!I329*$X$6) | G308: =IF(B308="","",'Historique détail'!U328) | H308: =IF(B308="","",(G308-F308)/F308) | I308: =IF(H308="","",(G308-C308)/C308)
B309: =IF(ARBITRAGES!E330=0,"",ARBITRAGES!E330) | C309: =IF(F309="","",C308) | D309: =IF(F309="","",PRIX!B330) | E309: =IF(F309="","",($F$4/PRIX!$B$3)*PRIX!B308) | F309: =IF(B309="","",PRIX!B330*$Q$6+$R$6*PRIX!C330+PRIX!D330*$S$6+$T$6*PRIX!E330+PRIX!F330*$U$6+PRIX!G330*$V$6+$W$6*PRIX!H330+PRIX!I330*$X$6) | G309: =IF(B309="","",'Historique détail'!U329) | H309: =IF(B309="","",(G309-F309)/F309) | I309: =IF(H309="","",(G309-C309)/C309)
B310: =IF(ARBITRAGES!E331=0,"",ARBITRAGES!E331) | C310: =IF(F310="","",C309) | D310: =IF(F310="","",PRIX!B331) | E310: =IF(F310="","",($F$4/PRIX!$B$3)*PRIX!B309) | F310: =IF(B310="","",PRIX!B331*$Q$6+$R$6*PRIX!C331+PRIX!D331*$S$6+$T$6*PRIX!E331+PRIX!F331*$U$6+PRIX!G331*$V$6+$W$6*PRIX!H331+PRIX!I331*$X$6) | G310: =IF(B310="","",'Historique détail'!U330) | H310: =IF(B310="","",(G310-F310)/F310) | I310: =IF(H310="","",(G310-C310)/C310)
...

Sheet Historique détail
B1: Historique détaillé | T1: $$$ | V1: %
A2: DATE | B2: $BTC | C2: $ETH | D2: $TON | E2: $SOL | F2: $TAO | G2: $RON | H2: $LINK | I2: $DOGE | J2: $SHIB | K2: $CAKE | L2: $JUP | M2: $AAVE | N2: $CKB | O2: $PENDLE | P2: $BOME | Q2: $PEPE | R2: $WIF | S2: $RAY | T2: USDC | U2: TOTAL | V2: Exposition
A3: =ARBITRAGES!E3 -> 45515 | B3: =IF(A3="","",PRIX!B3*'QUANTITE DETENUES'!B3) -> 6216.5137 | C3: =IF(B3="","",PRIX!C3*'QUANTITE DETENUES'!C3) -> 5059.3988 | D3: =IF(C3="","",PRIX!D3*'QUANTITE DETENUES'!D3) -> 0 | E3: =IF(D3="","",PRIX!E3*'QUANTITE DETENUES'!E3) -> 4858.6938 | F3: =IF(E3="","",PRIX!F3*'QUANTITE DETENUES'!F3) -> 0 | G3: =IF(F3="","",PRIX!G3*'QUANTITE DETENUES'!G3) -> 0 | H3: =IF(G3="","",PRIX!H3*'QUANTITE DETENUES'!H3) -> 0 | I3: =IF(H3="","",PRIX!I3*'QUANTITE DETENUES'!I3) -> 0 | ... R3: =IF(Q3="","",PRIX!R3*'QUANTITE DETENUES'!R3) -> 0 | S3: =IF(R3="","",PRIX!T3*'QUANTITE DETENUES'!S3) -> 0 | T3: =ARBITRAGES!M3 -> 21550 | U3: =IF(A3="","",SUM(B3:T3)) -> 38541.409 | V3: =IF(U3="","",1-T3/U3) -> 0.44086113
A4: =IF(ARBITRAGES!E4="","",ARBITRAGES!E4) -> 45515 | B4: =IF(A4="","",PRIX!B4*'QUANTITE DETENUES'!B4) -> 14363.044 | C4: =IF(B4="","",PRIX!C4*'QUANTITE DETENUES'!C4) -> 5059.3988 | D4: =IF(C4="","",PRIX!D4*'QUANTITE DETENUES'!D4) -> 0 | E4: =IF(D4="","",PRIX!E4*'QUANTITE DETENUES'!E4) -> 4858.6938 | F4: =IF(E4="","",PRIX!F4*'QUANTITE DETENUES'!F4) -> 0 | G4: =IF(F4="","",PRIX!G4*'QUANTITE DETENUES'!G4) -> 0 | H4: =IF(G4="","",PRIX!H4*'QUANTITE DETENUES'!H4) -> 0 | I4: =IF(H4="","",PRIX!I4*'QUANTITE DETENUES'!I4) -> 0 | ... R4: =IF(Q4="","",PRIX!R4*'QUANTITE DETENUES'!R4) -> 0 | S4: =IF(R4="","",PRIX!T4*'QUANTITE DETENUES'!S4) -> 0 | T4: =IF(A4="","",ARBITRAGES!M4) -> 14050 | U4: =IF(A4="","",SUM(B4:T4)) -> 39187.939 | V4: =IF(U4="","",1-T4/U4) -> 0.64147132
A5: =IF(ARBITRAGES!E5="","",ARBITRAGES!E5) -> 45516 | B5: =IF(A5="","",PRIX!B5*'QUANTITE DETENUES'!B5) -> 13633.492 | C5: =IF(B5="","",PRIX!C5*'QUANTITE DETENUES'!C5) -> 8224.174 | D5: =IF(C5="","",PRIX!D5*'QUANTITE DETENUES'!D5) -> 0 | E5: =IF(D5="","",PRIX!E5*'QUANTITE DETENUES'!E5) -> 4645.2628 | F5: =IF(E5="","",PRIX!F5*'QUANTITE DETENUES'!F5) -> 0 | G5: =IF(F5="","",PRIX!G5*'QUANTITE DETENUES'!G5) -> 0 | H5: =IF(G5="","",PRIX!H5*'QUANTITE DETENUES'!H5) -> 0 | I5: =IF(H5="","",PRIX!I5*'QUANTITE DETENUES'!I5) -> 0 | ... R5: =IF(Q5="","",PRIX!R5*'QUANTITE DETENUES'!R5) -> 0 | S5: =IF(R5="","",PRIX!T5*'QUANTITE DETENUES'!S5) -> 0 | T5: =IF(A5="","",ARBITRAGES!M5) -> 11050 | U5: =IF(A5="","",SUM(B5:T5)) -> 38425.058 | V5: =IF(U5="","",1-T5/U5) -> 0.71242724
A6: =IF(ARBITRAGES!E6="","",ARBITRAGES!E6) -> 45517 | B6: =IF(A6="","",PRIX!B6*'QUANTITE DETENUES'!B6) -> 13907.074 | C6: =IF(B6="","",PRIX!C6*'QUANTITE DETENUES'!C6) -> 8322.1902 | D6: =IF(C6="","",PRIX!D6*'QUANTITE DETENUES'!D6) -> 0 | E6: =IF(D6="","",PRIX!E6*'QUANTITE DETENUES'!E6) -> 5787.5965 | F6: =IF(E6="","",PRIX!F6*'QUANTITE DETENUES'!F6) -> 0 | G6: =IF(F6="","",PRIX!G6*'QUANTITE DETENUES'!G6) -> 0 | H6: =IF(G6="","",PRIX!H6*'QUANTITE DETENUES'!H6) -> 0 | I6: =IF(H6="","",PRIX!I6*'QUANTITE DETENUES'!I6) -> 0 | ... R6: =IF(Q6="","",PRIX!R6*'QUANTITE DETENUES'!R6) -> 0 | S6: =IF(R6="","",PRIX!T6*'QUANTITE DETENUES'!S6) -> 0 | T6: =IF(A6="","",ARBITRAGES!M6) -> 9900 | U6: =IF(A6="","",SUM(B6:T6)) -> 38797.452 | V6: =IF(U6="","",1-T6/U6) -> 0.74482861
A7: =IF(ARBITRAGES!E7="","",ARBITRAGES!E7) -> 45518 | B7: =IF(A7="","",PRIX!B7*'QUANTITE DETENUES'!B7) -> 13907.074 | C7: =IF(B7="","",PRIX!C7*'QUANTITE DETENUES'!C7) -> 8322.1902 | D7: =IF(C7="","",PRIX!D7*'QUANTITE DETENUES'!D7) -> 0 | E7: =IF(D7="","",PRIX!E7*'QUANTITE DETENUES'!E7) -> 5787.5965 | F7: =IF(E7="","",PRIX!F7*'QUANTITE DETENUES'!F7) -> 861.9 | G7: =IF(F7="","",PRIX!G7*'QUANTITE DETENUES'!G7) -> 0 | H7: =IF(G7="","",PRIX!H7*'QUANTITE DETENUES'!H7) -> 0 | I7: =IF(H7="","",PRIX!I7*'QUANTITE DETENUES'!I7) -> 0 | ... R7: =IF(Q7="","",PRIX!R7*'QUANTITE DETENUES'!R7) -> 0 | S7: =IF(R7="","",PRIX!T7*'QUANTITE DETENUES'!S7) -> 0 | T7: =IF(A7="","",ARBITRAGES!M7) -> 9060 | U7: =IF(A7="","",SUM(B7:T7)) -> 38816.265 | V7: =IF(U7="","",1-T7/U7) -> 0.76659269
A8: =IF(ARBITRAGES!E8="","",ARBITRAGES!E8) -> 45518 | B8: =IF(A8="","",PRIX!B8*'QUANTITE DETENUES'!B8) -> 13907.074 | C8: =IF(B8="","",PRIX!C8*'QUANTITE DETENUES'!C8) -> 8322.1902 | D8: =IF(C8="","",PRIX!D8*'QUANTITE DETENUES'!D8) -> 0 | E8: =IF(D8="","",PRIX!E8*'QUANTITE DETENUES'!E8) -> 5787.5965 | F8: =IF(E8="","",PRIX!F8*'QUANTITE DETENUES'!F8) -> 861.9 | G8: =IF(F8="","",PRIX!G8*'QUANTITE DETENUES'!G8) -> 330 | H8: =IF(G8="","",PRIX!H8*'QUANTITE DETENUES'!H8) -> 0 | I8: =IF(H8="","",PRIX!I8*'QUANTITE DETENUES'!I8) -> 0 | ... R8: =IF(Q8="","",PRIX!R8*'QUANTITE DETENUES'!R8) -> 0 | S8: =IF(R8="","",PRIX!T8*'QUANTITE DETENUES'!S8) -> 0 | T8: =IF(A8="","",ARBITRAGES!M8) -> 8750 | U8: =IF(A8="","",SUM(B8:T8)) -> 38836.265 | V8: =IF(U8="","",1-T8/U8) -> 0.77469512
A9: =IF(ARBITRAGES!E9="","",ARBITRAGES!E9) -> 45519 | B9: =IF(A9="","",PRIX!B9*'QUANTITE DETENUES'!B9) -> 13223.12 | C9: =IF(B9="","",PRIX!C9*'QUANTITE DETENUES'!C9) -> 8116.9688 | D9: =IF(C9="","",PRIX!D9*'QUANTITE DETENUES'!D9) -> 2758.4877 | E9: =IF(D9="","",PRIX!E9*'QUANTITE DETENUES'!E9) -> 5897.6867 | F9: =IF(E9="","",PRIX!F9*'QUANTITE DETENUES'!F9) -> 819 | G9: =IF(F9="","",PRIX!G9*'QUANTITE DETENUES'!G9) -> 326 | H9: =IF(G9="","",PRIX!H9*'QUANTITE DETENUES'!H9) -> 0 | I9: =IF(H9="","",PRIX!I9*'QUANTITE DETENUES'!I9) -> 0 | ... R9: =IF(Q9="","",PRIX!R9*'QUANTITE DETENUES'!R9) -> 0 | S9: =IF(R9="","",PRIX!T9*'QUANTITE DETENUES'!S9) -> 0 | T9: =IF(A9="","",ARBITRAGES!M9) -> 6000 | U9: =IF(A9="","",SUM(B9:T9)) -> 37999.572 | V9: =IF(U9="","",1-T9/U9) -> 0.84210348
A10: =IF(ARBITRAGES!E10="","",ARBITRAGES!E10) -> 45522 | B10: =IF(A10="","",PRIX!B10*'QUANTITE DETENUES'!B10) -> 15269.714 | C10: =IF(B10="","",PRIX!C10*'QUANTITE DETENUES'!C10) -> 8193.5439 | D10: =IF(C10="","",PRIX!D10*'QUANTITE DETENUES'!D10) -> 2826.3889 | E10: =IF(D10="","",PRIX!E10*'QUANTITE DETENUES'!E10) -> 5756.1422 | F10: =IF(E10="","",PRIX!F10*'QUANTITE DETENUES'!F10) -> 879 | G10: =IF(F10="","",PRIX!G10*'QUANTITE DETENUES'!G10) -> 329.4 | H10: =IF(G10="","",PRIX!H10*'QUANTITE DETENUES'!H10) -> 0 | I10: =IF(H10="","",PRIX!I10*'QUANTITE DETENUES'!I10) -> 0 | ... R10: =IF(Q10="","",PRIX!R10*'QUANTITE DETENUES'!R10) -> 0 | S10: =IF(R10="","",PRIX!T10*'QUANTITE DETENUES'!S10) -> 0 | T10: =IF(A10="","",ARBITRAGES!M10) -> 4500 | U10: =IF(A10="","",SUM(B10:T10)) -> 38621.63 | V10: =IF(U10="","",1-T10/U10) -> 0.88348498
A11: =IF(ARBITRAGES!E11="","",ARBITRAGES!E11) -> 45527 | B11: =IF(A11="","",PRIX!B11*'QUANTITE DETENUES'!B11) -> 16108.151 | C11: =IF(B11="","",PRIX!C11*'QUANTITE DETENUES'!C11) -> 8392.6394 | D11: =IF(C11="","",PRIX!D11*'QUANTITE DETENUES'!D11) -> 2839.1204 | E11: =IF(D11="","",PRIX!E11*'QUANTITE DETENUES'!E11) -> 5851.6847 | F11: =IF(E11="","",PRIX!F11*'QUANTITE DETENUES'!F11) -> 696 | G11: =IF(F11="","",PRIX!G11*'QUANTITE DETENUES'!G11) -> 355.4 | H11: =IF(G11="","",PRIX!H11*'QUANTITE DETENUES'!H11) -> 0 | I11: =IF(H11="","",PRIX!I11*'QUANTITE DETENUES'!I11) -> 0 | ... R11: =IF(Q11="","",PRIX!R11*'QUANTITE DETENUES'!R11) -> 0 | S11: =IF(R11="","",PRIX!T11*'QUANTITE DETENUES'!S11) -> 0 | T11: =IF(A11="","",ARBITRAGES!M11) -> 4845 | U11: =IF(A11="","",SUM(B11:T11)) -> 40071.087 | V11: =IF(U11="","",1-T11/U11) -> 0.87908988
A12: =IF(ARBITRAGES!E12="","",ARBITRAGES!E12) -> 45527 | B12: =IF(A12="","",PRIX!B12*'QUANTITE DETENUES'!B12) -> 16108.151 | C12: =IF(B12="","",PRIX!C12*'QUANTITE DETENUES'!C12) -> 8392.6394 | D12: =IF(C12="","",PRIX!D12*'QUANTITE DETENUES'!D12) -> 2839.1204 | E12: =IF(D12="","",PRIX!E12*'QUANTITE DETENUES'!E12) -> 4411.3944 | F12: =IF(E12="","",PRIX!F12*'QUANTITE DETENUES'!F12) -> 696 | G12: =IF(F12="","",PRIX!G12*'QUANTITE DETENUES'!G12) -> 355.4 | H12: =IF(G12="","",PRIX!H12*'QUANTITE DETENUES'!H12) -> 0 | I12: =IF(H12="","",PRIX!I12*'QUANTITE DETENUES'!I12) -> 0 | ... R12: =IF(Q12="","",PRIX!R12*'QUANTITE DETENUES'!R12) -> 0 | S12: =IF(R12="","",PRIX!T12*'QUANTITE DETENUES'!S12) -> 0 | T12: =IF(A12="","",ARBITRAGES!M12) -> 6345 | U12: =IF(A12="","",SUM(B12:T12)) -> 40130.796 | V12: =IF(U12="","",1-T12/U12) -> 0.841892
A13: =IF(ARBITRAGES!E13="","",ARBITRAGES!E13) -> 45528 | B13: =IF(A13="","",PRIX!B13*'QUANTITE DETENUES'!B13) -> 16362.222 | C13: =IF(B13="","",PRIX!C13*'QUANTITE DETENUES'!C13) -> 8576.4198 | D13: =IF(C13="","",PRIX!D13*'QUANTITE DETENUES'!D13) -> 2871.3735 | E13: =IF(D13="","",PRIX!E13*'QUANTITE DETENUES'!E13) -> 2844.3786 | F13: =IF(E13="","",PRIX!F13*'QUANTITE DETENUES'!F13) -> 686 | G13: =IF(F13="","",PRIX!G13*'QUANTITE DETENUES'!G13) -> 360 | H13: =IF(G13="","",PRIX!H13*'QUANTITE DETENUES'!H13) -> 0 | I13: =IF(H13="","",PRIX!I13*'QUANTITE DETENUES'!I13) -> 0 | ... R13: =IF(Q13="","",PRIX!R13*'QUANTITE DETENUES'!R13) -> 0 | S13: =IF(R13="","",PRIX!T13*'QUANTITE DETENUES'!S13) -> 0 | T13: =IF(A13="","",ARBITRAGES!M13) -> 8178 | U13: =IF(A13="","",SUM(B13:T13)) -> 40893.775 | V13: =IF(U13="","",1-T13/U13) -> 0.80001846
A14: =IF(ARBITRAGES!E14="","",ARBITRAGES!E14) -> 45529 | B14: =IF(A14="","",PRIX!B14*'QUANTITE DETENUES'!B14) -> 16260.594 | C14: =IF(B14="","",PRIX!C14*'QUANTITE DETENUES'!C14) -> 8469.2146 | D14: =IF(C14="","",PRIX!D14*'QUANTITE DETENUES'!D14) -> 2856.1301 | E14: =IF(D14="","",PRIX!E14*'QUANTITE DETENUES'!E14) -> 2844.3786 | F14: =IF(E14="","",PRIX!F14*'QUANTITE DETENUES'!F14) -> 654 | G14: =IF(F14="","",PRIX!G14*'QUANTITE DETENUES'!G14) -> 352 | H14: =IF(G14="","",PRIX!H14*'QUANTITE DETENUES'!H14) -> 0 | I14: =IF(H14="","",PRIX!I14*'QUANTITE DETENUES'!I14) -> 0 | ... R14: =IF(Q14="","",PRIX!R14*'QUANTITE DETENUES'!R14) -> 0 | S14: =IF(R14="","",PRIX!T14*'QUANTITE DETENUES'!S14) -> 0 | T14: =IF(A14="","",ARBITRAGES!M14) -> 7678 | U14: =IF(A14="","",SUM(B14:T14)) -> 40117.46 | V14: =IF(U14="","",1-T14/U14) -> 0.80861201
A15: =IF(ARBITRAGES!E15="","",ARBITRAGES!E15) -> 45530 | B15: =IF(A15="","",PRIX!B15*'QUANTITE DETENUES'!B15) -> 17948.907 | C15: =IF(B15="","",PRIX!C15*'QUANTITE DETENUES'!C15) -> 7963.8184 | D15: =IF(C15="","",PRIX!D15*'QUANTITE DETENUES'!D15) -> 2759.913 | E15: =IF(D15="","",PRIX!E15*'QUANTITE DETENUES'!E15) -> 2772.3691 | F15: =IF(E15="","",PRIX!F15*'QUANTITE DETENUES'!F15) -> 674 | G15: =IF(F15="","",PRIX!G15*'QUANTITE DETENUES'!G15) -> 331.2 | H15: =IF(G15="","",PRIX!H15*'QUANTITE DETENUES'!H15) -> 0 | I15: =IF(H15="","",PRIX!I15*'QUANTITE DETENUES'!I15) -> 0 | ... R15: =IF(Q15="","",PRIX!R15*'QUANTITE DETENUES'!R15) -> 0 | S15: =IF(R15="","",PRIX!T15*'QUANTITE DETENUES'!S15) -> 0 | T15: =IF(A15="","",ARBITRAGES!M15) -> 5478 | U15: =IF(A15="","",SUM(B15:T15)) -> 38900.624 | V15: =IF(U15="","",1-T15/U15) -> 0.85917964
... A26: =IF(ARBITRAGES!E26="","",ARBITRAGES!E26) -> 45558 | B26: =IF(A26="","",PRIX!B26*'QUANTITE DETENUES'!B26) -> 18703.416 | C26: =IF(B26="","",PRIX!C26*'QUANTITE DETENUES'!C26) -> 8116.9688 | D26: =IF(C26="","",PRIX!D26*'QUANTITE DETENUES'!D26) -> 2840.9379 | E26: =IF(D26="","",PRIX!E26*'QUANTITE DETENUES'!E26) -> 2628.3499 | F26: =IF(E26="","",PRIX!F26*'QUANTITE DETENUES'!F26) -> 2663.9985 | G26: =IF(F26="","",PRIX!G26*'QUANTITE DETENUES'!G26) -> 1176 | H26: =IF(G26="","",PRIX!H26*'QUANTITE DETENUES'!H26) -> 1145 | I26: =IF(H26="","",PRIX!I26*'QUANTITE DETENUES'!I26) -> 294.25 | ... R26: =IF(Q26="","",PRIX!R26*'QUANTITE DETENUES'!R26) -> 0 | S26: =IF(R26="","",PRIX!T26*'QUANTITE DETENUES'!S26) -> 0 | T26: =IF(A26="","",ARBITRAGES!M26) -> 2286.14 | U26: =IF(A26="","",SUM(B26:T26)) -> 40838.915 | V26: =IF(U26="","",1-T26/U26) -> 0.94402055
A27: =IF(ARBITRAGES!E27="","",ARBITRAGES!E27) -> 45568 | B27: =IF(A27="","",PRIX!B27*'QUANTITE DETENUES'!B27) -> 17968.219 | C27: =IF(B27="","",PRIX!C27*'QUANTITE DETENUES'!C27) -> 7657.5177 | D27: =IF(C27="","",PRIX!D27*'QUANTITE DETENUES'!D27) -> 2683.9521 | E27: =IF(D27="","",PRIX!E27*'QUANTITE DETENUES'!E27) -> 2484.3307 | F27: =IF(E27="","",PRIX!F27*'QUANTITE DETENUES'!F27) -> 2599.9987 | G27: =IF(F27="","",PRIX!G27*'QUANTITE DETENUES'!G27) -> 1120 | H27: =IF(G27="","",PRIX!H27*'QUANTITE DETENUES'!H27) -> 1060 | I27: =IF(H27="","",PRIX!I27*'QUANTITE DETENUES'!I27) -> 297 | ... R27: =IF(Q27="","",PRIX!R27*'QUANTITE DETENUES'!R27) -> 0 | S27: =IF(R27="","",PRIX!T27*'QUANTITE DETENUES'!S27) -> 0 | T27: =IF(A27="","",ARBITRAGES!M27) -> 2094.14 | U27: =IF(A27="","",SUM(B27:T27)) -> 38996.089 | V27: =IF(U27="","",1-T27/U27) -> 0.94629872 | W27: 1
A28: =IF(ARBITRAGES!E28="","",ARBITRAGES!E28) -> 45586 | B28: =IF(A28="","",PRIX!B28*'QUANTITE DETENUES'!B28) -> 20320.85 | C28: =IF(B28="","",PRIX!C28*'QUANTITE DETENUES'!C28) -> 7698.7158 | D28: =IF(C28="","",PRIX!D28*'QUANTITE DETENUES'!D28) -> 2719.4005 | E28: =IF(D28="","",PRIX!E28*'QUANTITE DETENUES'!E28) -> 3078.4098 | F28: =IF(E28="","",PRIX!F28*'QUANTITE DETENUES'!F28) -> 3073.1984 | G28: =IF(F28="","",PRIX!G28*'QUANTITE DETENUES'!G28) -> 1197 | H28: =IF(G28="","",PRIX!H28*'QUANTITE DETENUES'!H28) -> 1200 | I28: =IF(H28="","",PRIX!I28*'QUANTITE DETENUES'!I28) -> 409.75 | ... R28: =IF(Q28="","",PRIX!R28*'QUANTITE DETENUES'!R28) -> 0 | S28: =IF(R28="","",PRIX!T28*'QUANTITE DETENUES'!S28) -> 0 | T28: =IF(A28="","",ARBITRAGES!M28) -> 2805.52 | U28: =IF(A28="","",SUM(B28:T28)) -> 43650.544 | V28: =IF(U28="","",1-T28/U28) -> 0.93572772
A29: =IF(ARBITRAGES!E29="","",ARBITRAGES!E29) -> 45591 | B29: =IF(A29="","",PRIX!B29*'QUANTITE DETENUES'!B29) -> 19703.284 | C29: =IF(B29="","",PRIX!C29*'QUANTITE DETENUES'!C29) -> 10078.319 | D29: =IF(C29="","",PRIX!D29*'QUANTITE DETENUES'!D29) -> 2694.9806 | E29: =IF(D29="","",PRIX!E29*'QUANTITE DETENUES'!E29) -> 3024.4026 | F29: =IF(E29="","",PRIX!F29*'QUANTITE DETENUES'!F29) -> 2651.9986 | G29: =IF(F29="","",PRIX!G29*'QUANTITE DETENUES'!G29) -> 1050 | H29: =IF(G29="","",PRIX!H29*'QUANTITE DETENUES'!H29) -> 1100 | I29: =IF(H29="","",PRIX!I29*'QUANTITE DETENUES'!I29) -> 368.5 | ... R29: =IF(Q29="","",PRIX!R29*'QUANTITE DETENUES'!R29) -> 0 | S29: =IF(R29="","",PRIX!T29*'QUANTITE DETENUES'!S29) -> 0 | T29: =IF(A29="","",ARBITRAGES!M29) -> 2589.7495 | U29: =IF(A29="","",SUM(B29:T29)) -> 44302.285 | V29: =IF(U29="","",1-T29/U29) -> 0.94154366
A30: =IF(ARBITRAGES!E30="","",ARBITRAGES!E30) -> 45594 | B30: =IF(A30="","",PRIX!B30*'QUANTITE DETENUES'!B30) -> 21320.718 | C30: =IF(B30="","",PRIX!C30*'QUANTITE DETENUES'!C30) -> 7488.7508 | D30: =IF(C30="","",PRIX!D30*'QUANTITE DETENUES'!D30) -> 2777.48 | E30: =IF(D30="","",PRIX!E30*'QUANTITE DETENUES'!E30) -> 3076.7817 | F30: =IF(E30="","",PRIX!F30*'QUANTITE DETENUES'!F30) -> 2885.9985 | G30: =IF(F30="","",PRIX!G30*'QUANTITE DETENUES'!G30) -> 1085 | H30: =IF(G30="","",PRIX!H30*'QUANTITE DETENUES'!H30) -> 1160 | I30: =IF(H30="","",PRIX!I30*'QUANTITE DETENUES'!I30) -> 475.75 | ... R30: =IF(Q30="","",PRIX!R30*'QUANTITE DETENUES'!R30) -> 0 | S30: =IF(R30="","",PRIX!T30*'QUANTITE DETENUES'!S30) -> 0 | T30: =IF(A30="","",ARBITRAGES!M30) -> 2766.2029 | U30: =IF(A30="","",SUM(B30:T30)) -> 44166.08 | V30: =IF(U30="","",1-T30/U30) -> 0.93736816 | W30: 1
A31: =IF(ARBITRAGES!E31="","",ARBITRAGES!E31) -> 45595 | B31: =IF(A31="","",PRIX!B31*'QUANTITE DETENUES'!B31) -> 20585.521 | C31: =IF(B31="","",PRIX!C31*'QUANTITE DETENUES'!C31) -> 6998.8325 | D31: =IF(C31="","",PRIX!D31*'QUANTITE DETENUES'!D31) -> 2749.9802 | E31: =IF(D31="","",PRIX!E31*'QUANTITE DETENUES'!E31) -> 2838.7986 | F31: =IF(E31="","",PRIX!F31*'QUANTITE DETENUES'!F31) -> 2736.9988 | G31: =IF(F31="","",PRIX!G31*'QUANTITE DETENUES'!G31) -> 966 | H31: =IF(G31="","",PRIX!H31*'QUANTITE DETENUES'!H31) -> 1125 | I31: =IF(H31="","",PRIX!I31*'QUANTITE DETENUES'!I31) -> 440 | ... R31: =IF(Q31="","",PRIX!R31*'QUANTITE DETENUES'!R31) -> 0 | S31: =IF(R31="","",PRIX!T31*'QUANTITE DETENUES'!S31) -> 0 | T31: =IF(A31="","",ARBITRAGES!M31) -> 2406.2029 | U31: =IF(A31="","",SUM(B31:T31)) -> 41963.675 | V31: =IF(U31="","",1-T31/U31) -> 0.94265986
A32: =IF(ARBITRAGES!E32="","",ARBITRAGES!E32) -> 45598 | B32: =IF(A32="","",PRIX!B32*'QUANTITE DETENUES'!B32) -> 20144.402 | C32: =IF(B32="","",PRIX!C32*'QUANTITE DETENUES'!C32) -> 6858.8558 | D32: =IF(C32="","",PRIX!D32*'QUANTITE DETENUES'!D32) -> 2529.9818 | E32: =IF(D32="","",PRIX!E32*'QUANTITE DETENUES'!E32) -> 2719.807 | F32: =IF(E32="","",PRIX!F32*'QUANTITE DETENUES'!F32) -> 2498.9989 | G32: =IF(F32="","",PRIX!G32*'QUANTITE DETENUES'!G32) -> 889 | H32: =IF(G32="","",PRIX!H32*'QUANTITE DETENUES'!H32) -> 1060 | I32: =IF(H32="","",PRIX!I32*'QUANTITE DETENUES'!I32) -> 473 | ... R32: =IF(Q32="","",PRIX!R32*'QUANTITE DETENUES'!R32) -> 0 | S32: =IF(R32="","",PRIX!T32*'QUANTITE DETENUES'!S32) -> 0 | T32: =IF(A32="","",ARBITRAGES!M32) -> 1704.9529 | U32: =IF(A32="","",SUM(B32:T32)) -> 40654.557 | V32: =IF(U32="","",1-T32/U32) -> 0.95806244
A33: =IF(ARBITRAGES!E33="","",ARBITRAGES!E33) -> 45599 | B33: =IF(A33="","",PRIX!B33*'QUANTITE DETENUES'!B33) -> 20291.442 | C33: =IF(B33="","",PRIX!C33*'QUANTITE DETENUES'!C33) -> 6858.8558 | D33: =IF(C33="","",PRIX!D33*'QUANTITE DETENUES'!D33) -> 2529.9818 | E33: =IF(D33="","",PRIX!E33*'QUANTITE DETENUES'!E33) -> 2770.8034 | F33: =IF(E33="","",PRIX!F33*'QUANTITE DETENUES'!F33) -> 2558.4988 | G33: =IF(F33="","",PRIX!G33*'QUANTITE DETENUES'!G33) -> 889 | H33: =IF(G33="","",PRIX!H33*'QUANTITE DETENUES'!H33) -> 1060 | I33: =IF(H33="","",PRIX!I33*'QUANTITE DETENUES'!I33) -> 473 | ... R33: =IF(Q33="","",PRIX!R33*'QUANTITE DETENUES'!R33) -> 0 | S33: =IF(R33="","",PRIX!T33*'QUANTITE DETENUES'!S33) -> 0 | T33: =IF(A33="","",ARBITRAGES!M33) -> 2109.4154 | U33: =IF(A33="","",SUM(B33:T33)) -> 40932.405 | V33: =IF(U33="","",1-T33/U33) -> 0.94846588
A34: =IF(ARBITRAGES!E34="","",ARBITRAGES!E34) -> 45602 | B34: =IF(A34="","",PRIX!B34*'QUANTITE DETENUES'!B34) -> 22350.754 | C34: =IF(B34="","",PRIX!C34*'QUANTITE DETENUES'!C34) -> 7564.4361 | D34: =IF(C34="","",PRIX!D34*'QUANTITE DETENUES'!D34) -> 2615.8755 | E34: =IF(D34="","",PRIX!E34*'QUANTITE DETENUES'!E34) -> 2456.772 | F34: =IF(E34="","",PRIX!F34*'QUANTITE DETENUES'!F34) -> 3124.3497 | G34: =IF(F34="","",PRIX!G34*'QUANTITE DETENUES'!G34) -> 969.87949 | H34: =IF(G34="","",PRIX!H34*'QUANTITE DETENUES'!H34) -> 1207 | I34: =IF(H34="","",PRIX!I34*'QUANTITE DETENUES'!I34) -> 535.7 | ... R34: =IF(Q34="","",PRIX!R34*'QUANTITE DETENUES'!R34) -> 0 | S34: =IF(R34="","",PRIX!T34*'QUANTITE DETENUES'!S34) -> 0 | T34: =IF(A34="","",ARBITRAGES!M34) -> 2829.4154 | U34: =IF(A34="","",SUM(B34:T34)) -> 45162.981 | V34: =IF(U34="","",1-T34/U34) -> 0.937351
A35: =PRIX!A35 -> 45606 | B35: =IF(A35="","",PRIX!B35*'QUANTITE DETENUES'!B35) -> 23821.198 | C35: =IF(B35="","",PRIX!C35*'QUANTITE DETENUES'!C35) -> 9049.3069 | D35: =IF(C35="","",PRIX!D35*'QUANTITE DETENUES'!D35) -> 3025.7235 | E35: =IF(D35="","",PRIX!E35*'QUANTITE DETENUES'!E35) -> 2794.7407 | F35: =IF(E35="","",PRIX!F35*'QUANTITE DETENUES'!F35) -> 3421.9068 | G35: =IF(F35="","",PRIX!G35*'QUANTITE DETENUES'!G35) -> 1162.4548 | H35: =IF(G35="","",PRIX!H35*'QUANTITE DETENUES'!H35) -> 1470 | I35: =IF(H35="","",PRIX!I35*'QUANTITE DETENUES'!I35) -> 783.75 | ... R35: =IF(Q35="","",PRIX!R35*'QUANTITE DETENUES'!R35) -> 0 | S35: =IF(R35="","",PRIX!T35*'QUANTITE DETENUES'!S35) -> 0 | T35: =IF(A35="","",ARBITRAGES!M35) -> 3104.2612 | U35: =IF(A35="","",SUM(B35:T35)) -> 50381.221 | V35: =IF(U35="","",1-T35/U35) -> 0.93838456
A36: =PRIX!A36 -> 45576 | B36: =IF(A36="","",PRIX!B36*'QUANTITE DETENUES'!B36) -> 25585.731 | C36: =IF(B36="","",PRIX!C36*'QUANTITE DETENUES'!C36) -> 9385.504 | D36: =IF(C36="","",PRIX!D36*'QUANTITE DETENUES'!D36) -> 3025.7235 | E36: =IF(D36="","",PRIX!E36*'QUANTITE DETENUES'!E36) -> 2859.7346 | F36: =IF(E36="","",PRIX!F36*'QUANTITE DETENUES'!F36) -> 3630.1968 | G36: =IF(F36="","",PRIX!G36*'QUANTITE DETENUES'!G36) -> 1120.4384 | H36: =IF(G36="","",PRIX!H36*'QUANTITE DETENUES'!H36) -> 1465 | I36: =IF(H36="","",PRIX!I36*'QUANTITE DETENUES'!I36) -> 612.5 | ... R36: =IF(Q36="","",PRIX!R36*'QUANTITE DETENUES'!R36) -> 0 | S36: =IF(R36="","",PRIX!T36*'QUANTITE DETENUES'!S36) -> 0 | T36: =IF(A36="","",ARBITRAGES!M36) -> 3454.2612 | U36: =IF(A36="","",SUM(B36:T36)) -> 52869.461 | V36: =IF(U36="","",1-T36/U36) -> 0.93466434
A37: =PRIX!A37 -> 45608 | B37: =IF(A37="","",PRIX!B37*'QUANTITE DETENUES'!B37) -> 25255.747 | C37: =IF(B37="","",PRIX!C37*'QUANTITE DETENUES'!C37) -> 9525.5862 | D37: =IF(C37="","",PRIX!D37*'QUANTITE DETENUES'!D37) -> 3053.2301 | E37: =IF(D37="","",PRIX!E37*'QUANTITE DETENUES'!E37) -> 2924.7286 | F37: =IF(E37="","",PRIX!F37*'QUANTITE DETENUES'!F37) -> 3600.4411 | G37: =IF(F37="","",PRIX!G37*'QUANTITE DETENUES'!G37) -> 1127.4411 | H37: =IF(G37="","",PRIX!H37*'QUANTITE DETENUES'!H37) -> 1500 | I37: =IF(H37="","",PRIX!I37*'QUANTITE DETENUES'!I37) -> 728 | ... R37: =IF(Q37="","",PRIX!R37*'QUANTITE DETENUES'!R37) -> 0 | S37: =IF(R37="","",PRIX!T37*'QUANTITE DETENUES'!S37) -> 0 | T37: =IF(A37="","",ARBITRAGES!M37) -> 4715.4656 | U37: =IF(A37="","",SUM(B37:T37)) -> 54208.656 | V37: =IF(U37="","",1-T37/U37) -> 0.91301268
A38: =PRIX!A38 -> 45609 | B38: =IF(A38="","",PRIX!B38*'QUANTITE DETENUES'!B38) -> 24499.755 | C38: =IF(B38="","",PRIX!C38*'QUANTITE DETENUES'!C38) -> 8881.2083 | D38: =IF(C38="","",PRIX!D38*'QUANTITE DETENUES'!D38) -> 2871.6867 | E38: =IF(D38="","",PRIX!E38*'QUANTITE DETENUES'!E38) -> 2703.7491 | F38: =IF(E38="","",PRIX!F38*'QUANTITE DETENUES'!F38) -> 3213.6169 | G38: =IF(F38="","",PRIX!G38*'QUANTITE DETENUES'!G38) -> 1008.3946 | H38: =IF(G38="","",PRIX!H38*'QUANTITE DETENUES'!H38) -> 1335 | I38: =IF(H38="","",PRIX!I38*'QUANTITE DETENUES'!I38) -> 665 | ... R38: =IF(Q38="","",PRIX!R38*'QUANTITE DETENUES'!R38) -> 0 | S38: =IF(R38="","",PRIX!T38*'QUANTITE DETENUES'!S38) -> 0 | T38: =IF(A38="","",ARBITRAGES!M38) -> 3965.4656 | U38: =IF(A38="","",SUM(B38:T38)) -> 51415.192 | V38: =IF(U38="","",1-T38/U38) -> 0.92287366
A39: =PRIX!A39 -> 45609 | B39: =IF(A39="","",PRIX!B39*'QUANTITE DETENUES'!B39) -> 24499.755 | C39: =IF(B39="","",PRIX!C39*'QUANTITE DETENUES'!C39) -> 8881.2083 | D39: =IF(C39="","",PRIX!D39*'QUANTITE DETENUES'!D39) -> 2871.6867 | E39: =IF(D39="","",PRIX!E39*'QUANTITE DETENUES'!E39) -> 2703.7491 | F39: =IF(E39="","",PRIX!F39*'QUANTITE DETENUES'!F39) -> 3213.6169 | G39: =IF(F39="","",PRIX!G39*'QUANTITE DETENUES'!G39) -> 1008.3946 | H39: =IF(G39="","",PRIX!H39*'QUANTITE DETENUES'!H39) -> 1335 | I39: =IF(H39="","",PRIX!I39*'QUANTITE DETENUES'!I39) -> 665 | ... R39: =IF(Q39="","",PRIX!R39*'QUANTITE DETENUES'!R39) -> 0 | S39: =IF(R39="","",PRIX!T39*'QUANTITE DETENUES'!S39) -> 0 | T39: =IF(A39="","",ARBITRAGES!M39) -> 3395.9656 | U39: =IF(A39="","",SUM(B39:T39)) -> 51415.192 | V39: =IF(U39="","",1-T39/U39) -> 0.93395015
A40: =PRIX!A40 -> 45609 | B40: =IF(A40="","",PRIX!B40*'QUANTITE DETENUES'!B40) -> 24499.755 | C40: =IF(B40="","",PRIX!C40*'QUANTITE DETENUES'!C40) -> 8881.2083 | D40: =IF(C40="","",PRIX!D40*'QUANTITE DETENUES'!D40) -> 2871.6867 | E40: =IF(D40="","",PRIX!E40*'QUANTITE DETENUES'!E40) -> 2703.7491 | F40: =IF(E40="","",PRIX!F40*'QUANTITE DETENUES'!F40) -> 3213.6169 | G40: =IF(F40="","",PRIX!G40*'QUANTITE DETENUES'!G40) -> 1008.3946 | H40: =IF(G40="","",PRIX!H40*'QUANTITE DETENUES'!H40) -> 1335 | I40: =IF(H40="","",PRIX!I40*'QUANTITE DETENUES'!I40) -> 665 | ... R40: =IF(Q40="","",PRIX!R40*'QUANTITE DETENUES'!R40) -> 0 | S40: =IF(R40="","",PRIX!T40*'QUANTITE DETENUES'!S40) -> 0 | T40: =IF(A40="","",ARBITRAGES!M40) -> 2895.4656 | U40: =IF(A40="","",SUM(B40:T40)) -> 51415.192 | V40: =IF(U40="","",1-T40/U40) -> 0.94368463
A41: =PRIX!A41 -> 45610 | B41: =IF(A41="","",PRIX!B41*'QUANTITE DETENUES'!B41) -> 27582.331 | C41: =IF(B41="","",PRIX!C41*'QUANTITE DETENUES'!C41) -> 8828.3255 | D41: =IF(C41="","",PRIX!D41*'QUANTITE DETENUES'!D41) -> 3053.4521 | E41: =IF(D41="","",PRIX!E41*'QUANTITE DETENUES'!E41) -> 3185.709 | F41: =IF(E41="","",PRIX!F41*'QUANTITE DETENUES'!F41) -> 2976.3212 | G41: =IF(F41="","",PRIX!G41*'QUANTITE DETENUES'!G41) -> 1019.7473 | H41: =IF(G41="","",PRIX!H41*'QUANTITE DETENUES'!H41) -> 1440.216 | I41: =IF(H41="","",PRIX!I41*'QUANTITE DETENUES'!I41) -> 717.5082 | ... R41: =IF(Q41="","",PRIX!R41*'QUANTITE DETENUES'!R41) -> 0 | S41: =IF(R41="","",PRIX!T41*'QUANTITE DETENUES'!S41) -> 0 | T41: =IF(A41="","",ARBITRAGES!M41) -> 1585.4656 | U41: =IF(A41="","",SUM(B41:T41)) -> 53867.707 | V41: =IF(U41="","",1-T41/U41) -> 0.97056742
A42: =PRIX!A42 -> 45615 | B42: =IF(A42="","",PRIX!B42*'QUANTITE DETENUES'!B42) -> 27582.331 | C42: =IF(B42="","",PRIX!C42*'QUANTITE DETENUES'!C42) -> 8828.3255 | D42: =IF(C42="","",PRIX!D42*'QUANTITE DETENUES'!D42) -> 3053.4521 | E42: =IF(D42="","",PRIX!E42*'QUANTITE DETENUES'!E42) -> 3185.709 | F42: =IF(E42="","",PRIX!F42*'QUANTITE DETENUES'!F42) -> 2976.3212 | G42: =IF(F42="","",PRIX!G42*'QUANTITE DETENUES'!G42) -> 1019.7473 | H42: =IF(G42="","",PRIX!H42*'QUANTITE DETENUES'!H42) -> 1440.216 | I42: =IF(H42="","",PRIX!I42*'QUANTITE DETENUES'!I42) -> 717.5082 | ... R42: =IF(Q42="","",PRIX!R42*'QUANTITE DETENUES'!R42) -> 0 | S42: =IF(R42="","",PRIX!T42*'QUANTITE DETENUES'!S42) -> 0 | T42: =IF(A42="","",ARBITRAGES!M42) -> 1962.4656 | U42: =IF(A42="","",SUM(B42:T42)) -> 53874.957 | V42: =IF(U42="","",1-T42/U42) -> 0.96357369
A43: =PRIX!A43 -> 45618 | B43: =IF(A43="","",PRIX!B43*'QUANTITE DETENUES'!B43) -> 29204.822 | C43: =IF(B43="","",PRIX!C43*'QUANTITE DETENUES'!C43) -> 9809.2505 | D43: =IF(C43="","",PRIX!D43*'QUANTITE DETENUES'!D43) -> 3576.1151 | E43: =IF(D43="","",PRIX!E43*'QUANTITE DETENUES'!E43) -> 3419.7611 | F43: =IF(E43="","",PRIX!F43*'QUANTITE DETENUES'!F43) -> 3184.6636 | G43: =IF(F43="","",PRIX!G43*'QUANTITE DETENUES'!G43) -> 1146.3366 | H43: =IF(G43="","",PRIX!H43*'QUANTITE DETENUES'!H43) -> 1800.27 | I43: =IF(H43="","",PRIX!I43*'QUANTITE DETENUES'!I43) -> 840.0096 | ... R43: =IF(Q43="","",PRIX!R43*'QUANTITE DETENUES'!R43) -> 0 | S43: =IF(R43="","",PRIX!T43*'QUANTITE DETENUES'!S43) -> 0 | T43: =IF(A43="","",ARBITRAGES!M43) -> 1522.4656 | U43: =IF(A43="","",SUM(B43:T43)) -> 58333.004 | V43: =IF(U43="","",1-T43/U43) -> 0.97390044
A44: =PRIX!A44 -> 45619 | B44: =IF(A44="","",PRIX!B44*'QUANTITE DETENUES'!B44) -> 29204.822 | C44: =IF(B44="","",PRIX!C44*'QUANTITE DETENUES'!C44) -> 9809.2505 | D44: =IF(C44="","",PRIX!D44*'QUANTITE DETENUES'!D44) -> 3576.1151 | E44: =IF(D44="","",PRIX!E44*'QUANTITE DETENUES'!E44) -> 3419.7611 | F44: =IF(E44="","",PRIX!F44*'QUANTITE DETENUES'!F44) -> 3184.6636 | G44: =IF(F44="","",PRIX!G44*'QUANTITE DETENUES'!G44) -> 1146.3366 | H44: =IF(G44="","",PRIX!H44*'QUANTITE DETENUES'!H44) -> 1800.27 | I44: =IF(H44="","",PRIX!I44*'QUANTITE DETENUES'!I44) -> 840.0096 | ... R44: =IF(Q44="","",PRIX!R44*'QUANTITE DETENUES'!R44) -> 0 | S44: =IF(R44="","",PRIX!T44*'QUANTITE DETENUES'!S44) -> 0 | T44: =IF(A44="","",ARBITRAGES!M44) -> 1346.5336 | U44: =IF(A44="","",SUM(B44:T44)) -> 58333.004 | V44: =IF(U44="","",1-T44/U44) -> 0.97691644
A45: =PRIX!A45 -> 45622 | B45: =IF(A45="","",PRIX!B45*'QUANTITE DETENUES'!B45) -> 27729.831 | C45: =IF(B45="","",PRIX!C45*'QUANTITE DETENUES'!C45) -> 9332.8012 | D45: =IF(C45="","",PRIX!D45*'QUANTITE DETENUES'!D45) -> 3301.0293 | E45: =IF(D45="","",PRIX!E45*'QUANTITE DETENUES'!E45) -> 2990.6656 | F45: =IF(E45="","",PRIX!F45*'QUANTITE DETENUES'!F45) -> 3125.1372 | G45: =IF(F45="","",PRIX!G45*'QUANTITE DETENUES'!G45) -> 1139.3039 | H45: =IF(G45="","",PRIX!H45*'QUANTITE DETENUES'!H45) -> 1720.258 | I45: =IF(H45="","",PRIX!I45*'QUANTITE DETENUES'!I45) -> 670.25766 | ... R45: =IF(Q45="","",PRIX!R45*'QUANTITE DETENUES'!R45) -> 197.65 | S45: =IF(R45="","",PRIX!T45*'QUANTITE DETENUES'!S45) -> 0 | T45: =IF(A45="","",ARBITRAGES!M45) -> 1148.8836 | U45: =IF(A45="","",SUM(B45:T45)) -> 55137.786 | V45: =IF(U45="","",1-T45/U45) -> 0.97916341
A46: =PRIX!A46 -> 45630 | B46: =IF(A46="","",PRIX!B46*'QUANTITE DETENUES'!B46) -> 28468.369 | C46: =IF(B46="","",PRIX!C46*'QUANTITE DETENUES'!C46) -> 10486.96 | D46: =IF(C46="","",PRIX!D46*'QUANTITE DETENUES'!D46) -> 3907.496 | E46: =IF(D46="","",PRIX!E46*'QUANTITE DETENUES'!E46) -> 3122.7825 | F46: =IF(E46="","",PRIX!F46*'QUANTITE DETENUES'!F46) -> 4168.8096 | G46: =IF(F46="","",PRIX!G46*'QUANTITE DETENUES'!G46) -> 1653.6339 | H46: =IF(G46="","",PRIX!H46*'QUANTITE DETENUES'!H46) -> 2510.4945 | I46: =IF(H46="","",PRIX!I46*'QUANTITE DETENUES'!I46) -> 735.0609 | ... R46: =IF(Q46="","",PRIX!R46*'QUANTITE DETENUES'!R46) -> 200.6408 | S46: =IF(R46="","",PRIX!T46*'QUANTITE DETENUES'!S46) -> 0 | T46: =IF(A46="","",ARBITRAGES!M46) -> 1257.1936 | U46: =IF(A46="","",SUM(B46:T46)) -> 61473.762 | V46: =IF(U46="","",1-T46/U46) -> 0.9795491
... A49: =PRIX!A49 -> 45646 | B49: =IF(A49="","",PRIX!B49*'QUANTITE DETENUES'!B49) -> 27435.837 | C49: =IF(B49="","",PRIX!C49*'QUANTITE DETENUES'!C49) -> 9393.4 | D49: =IF(C49="","",PRIX!D49*'QUANTITE DETENUES'!D49) -> 2977.4019 | E49: =IF(D49="","",PRIX!E49*'QUANTITE DETENUES'!E49) -> 2747.1217 | F49: =IF(E49="","",PRIX!F49*'QUANTITE DETENUES'!F49) -> 2739.5035 | G49: =IF(F49="","",PRIX!G49*'QUANTITE DETENUES'!G49) -> 1322.9071 | H49: =IF(G49="","",PRIX!H49*'QUANTITE DETENUES'!H49) -> 2240.4413 | I49: =IF(H49="","",PRIX!I49*'QUANTITE DETENUES'!I49) -> 560.0464 | ... R49: =IF(Q49="","",PRIX!R49*'QUANTITE DETENUES'!R49) -> 118.024 | S49: =IF(R49="","",PRIX!T49*'QUANTITE DETENUES'!S49) -> 0 | T49: =IF(A49="","",ARBITRAGES!M49) -> 408.19364 | U49: =IF(A49="","",SUM(B49:T49)) -> 54086.409 | V49: =IF(U49="","",1-T49/U49) -> 0.99245294
A50: =PRIX!A50 -> 45658 | B50: =IF(A50="","",PRIX!B50*'QUANTITE DETENUES'!B50) -> 26255.801 | C50: =IF(B50="","",PRIX!C50*'QUANTITE DETENUES'!C50) -> 8972.8 | D50: =IF(C50="","",PRIX!D50*'QUANTITE DETENUES'!D50) -> 3081.9687 | E50: =IF(D50="","",PRIX!E50*'QUANTITE DETENUES'!E50) -> 3002.3188 | F50: =IF(E50="","",PRIX!F50*'QUANTITE DETENUES'!F50) -> 2977.7212 | G50: =IF(F50="","",PRIX!G50*'QUANTITE DETENUES'!G50) -> 1407.348 | H50: =IF(G50="","",PRIX!H50*'QUANTITE DETENUES'!H50) -> 2100.4137 | I50: =IF(H50="","",PRIX!I50*'QUANTITE DETENUES'!I50) -> 612.55075 | ... S50: =IF(R50="","",PRIX!S50*'QUANTITE DETENUES'!S50) -> 0 | T50: =IF(A50="","",ARBITRAGES!M50) -> 206.91864 | U50: =IF(A50="","",SUM(B50:T50)) -> 52919.583 | V50: =IF(U50="","",1-T50/U50) -> 0.99608994
A51: =PRIX!A51 -> 45666 | B51: =IF(A51="","",PRIX!B51*'QUANTITE DETENUES'!B51) -> 27141.748 | C51: =IF(B51="","",PRIX!C51*'QUANTITE DETENUES'!C51) -> 9547.2 | D51: =IF(C51="","",PRIX!D51*'QUANTITE DETENUES'!D51) -> 2973.5184 | E51: =IF(D51="","",PRIX!E51*'QUANTITE DETENUES'!E51) -> 3609.9825 | F51: =IF(E51="","",PRIX!F51*'QUANTITE DETENUES'!F51) -> 2946.5035 | G51: =IF(F51="","",PRIX!G51*'QUANTITE DETENUES'!G51) -> 1267.7472 | H51: =IF(G51="","",PRIX!H51*'QUANTITE DETENUES'!H51) -> 2450.7276 | I51: =IF(H51="","",PRIX!I51*'QUANTITE DETENUES'!I51) -> 700.178 | ... S51: =IF(R51="","",PRIX!S51*'QUANTITE DETENUES'!S51) -> 0 | T51: =IF(A51="","",ARBITRAGES!M51) -> 13.418639 | U51: =IF(A51="","",SUM(B51:T51)) -> 55303.265 | V51: =IF(U51="","",1-T51/U51) -> 0.99975736
A52: =PRIX!A52 -> 45676 | B52: =IF(A52="","",PRIX!B52*'QUANTITE DETENUES'!B52) -> 26551.71 | C52: =IF(B52="","",PRIX!C52*'QUANTITE DETENUES'!C52) -> 8985.6 | D52: =IF(C52="","",PRIX!D52*'QUANTITE DETENUES'!D52) -> 3028.5835 | E52: =IF(D52="","",PRIX!E52*'QUANTITE DETENUES'!E52) -> 3861.4383 | F52: =IF(E52="","",PRIX!F52*'QUANTITE DETENUES'!F52) -> 2754.3402 | G52: =IF(F52="","",PRIX!G52*'QUANTITE DETENUES'!G52) -> 1197.3168 | H52: =IF(G52="","",PRIX!H52*'QUANTITE DETENUES'!H52) -> 2300.6831 | I52: =IF(H52="","",PRIX!I52*'QUANTITE DETENUES'!I52) -> 656.41688 | ... S52: =IF(R52="","",PRIX!S52*'QUANTITE DETENUES'!S52) -> 0 | T52: =IF(A52="","",ARBITRAGES!M52) -> 293.41864 | U52: =IF(A52="","",SUM(B52:T52)) -> 54210.272 | V52: =IF(U52="","",1-T52/U52) -> 0.9945874
A53: =PRIX!A53 -> 45677 | B53: =IF(A53="","",PRIX!B53*'QUANTITE DETENUES'!B53) -> 27141.748 | C53: =IF(B53="","",PRIX!C53*'QUANTITE DETENUES'!C53) -> 9266.4 | D53: =IF(C53="","",PRIX!D53*'QUANTITE DETENUES'!D53) -> 2863.3881 | E53: =IF(D53="","",PRIX!E53*'QUANTITE DETENUES'!E53) -> 3510.3984 | F53: =IF(E53="","",PRIX!F53*'QUANTITE DETENUES'!F53) -> 2402.0409 | G53: =IF(F53="","",PRIX!G53*'QUANTITE DETENUES'!G53) -> 1197.3168 | H53: =IF(G53="","",PRIX!H53*'QUANTITE DETENUES'!H53) -> 2555.7588 | I53: =IF(H53="","",PRIX!I53*'QUANTITE DETENUES'!I53) -> 621.40797 | ... S53: =IF(R53="","",PRIX!S53*'QUANTITE DETENUES'!S53) -> 363 | T53: =IF(A53="","",ARBITRAGES!M53) -> 14.018639 | U53: =IF(A53="","",SUM(B53:T53)) -> 53954.968 | V53: =IF(U53="","",1-T53/U53) -> 0.99974018
A54: =PRIX!A54 -> 45718 | B54: =IF(A54="","",PRIX!B54*'QUANTITE DETENUES'!B54) -> 25384.163 | C54: =IF(B54="","",PRIX!C54*'QUANTITE DETENUES'!C54) -> 8433.6 | D54: =IF(C54="","",PRIX!D54*'QUANTITE DETENUES'!D54) -> 2312.7365 | E54: =IF(D54="","",PRIX!E54*'QUANTITE DETENUES'!E54) -> 3031.8427 | F54: =IF(E54="","",PRIX!F54*'QUANTITE DETENUES'!F54) -> 2115.446 | G54: =IF(F54="","",PRIX!G54*'QUANTITE DETENUES'!G54) -> 848.7648 | H54: =IF(G54="","",PRIX!H54*'QUANTITE DETENUES'!H54) -> 1800.8946 | I54: =IF(H54="","",PRIX!I54*'QUANTITE DETENUES'!I54) -> 525.3135 | ... S54: =IF(R54="","",PRIX!S54*'QUANTITE DETENUES'!S54) -> 132 | T54: =IF(A54="","",ARBITRAGES!M54) -> 2376.0186 | U54: =IF(A54="","",SUM(B54:T54)) -> 50501.989 | V54: =IF(U54="","",1-T54/U54) -> 0.95295198
A55: =PRIX!A55 -> 45719 | B55: =IF(A55="","",PRIX!B55*'QUANTITE DETENUES'!B55) -> 23763.898 | C55: =IF(B55="","",PRIX!C55*'QUANTITE DETENUES'!C55) -> 7702.688 | D55: =IF(C55="","",PRIX!D55*'QUANTITE DETENUES'!D55) -> 1872.2153 | E55: =IF(D55="","",PRIX!E55*'QUANTITE DETENUES'!E55) -> 2721.6076 | F55: =IF(E55="","",PRIX!F55*'QUANTITE DETENUES'!F55) -> 2362.2371 | G55: =IF(F55="","",PRIX!G55*'QUANTITE DETENUES'!G55) -> 707.304 | H55: =IF(G55="","",PRIX!H55*'QUANTITE DETENUES'!H55) -> 1550.7704 | I55: =IF(H55="","",PRIX!I55*'QUANTITE DETENUES'!I55) -> 385.2299 | ... S55: =IF(R55="","",PRIX!S55*'QUANTITE DETENUES'!S55) -> 110 | T55: =IF(A55="","",ARBITRAGES!M55) -> 2001.0186 | U55: =IF(A55="","",SUM(B55:T55)) -> 46003.507 | V55: =IF(U55="","",1-T55/U55) -> 0.95650291
A56: =PRIX!A56 -> 45719 | B56: =IF(A56="","",PRIX!B56*'QUANTITE DETENUES'!B56) -> 23763.898 | C56: =IF(B56="","",PRIX!C56*'QUANTITE DETENUES'!C56) -> 7702.688 | D56: =IF(C56="","",PRIX!D56*'QUANTITE DETENUES'!D56) -> 1872.2153 | E56: =IF(D56="","",PRIX!E56*'QUANTITE DETENUES'!E56) -> 2721.6076 | F56: =IF(E56="","",PRIX!F56*'QUANTITE DETENUES'!F56) -> 2362.2371 | G56: =IF(F56="","",PRIX!G56*'QUANTITE DETENUES'!G56) -> 707.304 | H56: =IF(G56="","",PRIX!H56*'QUANTITE DETENUES'!H56) -> 1550.7704 | I56: =IF(H56="","",PRIX!I56*'QUANTITE DETENUES'!I56) -> 385.2299 | ... S56: =IF(R56="","",PRIX!S56*'QUANTITE DETENUES'!S56) -> 110 | T56: =IF(A56="","",ARBITRAGES!M56) -> 1874.2686 | U56: =IF(A56="","",SUM(B56:T56)) -> 46010.474 | V56: =IF(U56="","",1-T56/U56) -> 0.9592643
A57: =PRIX!A57 -> 45719 | B57: =IF(A57="","",PRIX!B57*'QUANTITE DETENUES'!B57) -> 24069.1 | C57: =IF(B57="","",PRIX!C57*'QUANTITE DETENUES'!C57) -> 7702.688 | D57: =IF(C57="","",PRIX!D57*'QUANTITE DETENUES'!D57) -> 1872.2153 | E57: =IF(D57="","",PRIX!E57*'QUANTITE DETENUES'!E57) -> 2721.6076 | F57: =IF(E57="","",PRIX!F57*'QUANTITE DETENUES'!F57) -> 2362.2371 | G57: =IF(F57="","",PRIX!G57*'QUANTITE DETENUES'!G57) -> 707.304 | H57: =IF(G57="","",PRIX!H57*'QUANTITE DETENUES'!H57) -> 1550.7704 | I57: =IF(H57="","",PRIX!I57*'QUANTITE DETENUES'!I57) -> 385.2299 | ... S57: =IF(R57="","",PRIX!S57*'QUANTITE DETENUES'!S57) -> 110 | T57: =IF(A57="","",ARBITRAGES!M57) -> 1574.2686 | U57: =IF(A57="","",SUM(B57:T57)) -> 46015.676 | V57: =IF(U57="","",1-T57/U57) -> 0.96578843
A58: =PRIX!A58 -> 45719 | B58: =IF(A58="","",PRIX!B58*'QUANTITE DETENUES'!B58) -> 24641.1 | C58: =IF(B58="","",PRIX!C58*'QUANTITE DETENUES'!C58) -> 7702.688 | D58: =IF(C58="","",PRIX!D58*'QUANTITE DETENUES'!D58) -> 1872.2153 | E58: =IF(D58="","",PRIX!E58*'QUANTITE DETENUES'!E58) -> 2721.6076 | F58: =IF(E58="","",PRIX!F58*'QUANTITE DETENUES'!F58) -> 2362.2371 | G58: =IF(F58="","",PRIX!G58*'QUANTITE DETENUES'!G58) -> 707.304 | H58: =IF(G58="","",PRIX!H58*'QUANTITE DETENUES'!H58) -> 1550.7704 | I58: =IF(H58="","",PRIX!I58*'QUANTITE DETENUES'!I58) -> 385.2299 | ... S58: =IF(R58="","",PRIX!S58*'QUANTITE DETENUES'!S58) -> 110 | T58: =IF(A58="","",ARBITRAGES!M58) -> 1015.2686 | U58: =IF(A58="","",SUM(B58:T58)) -> 46028.676 | V58: =IF(U58="","",1-T58/U58) -> 0.97794269
A59: =PRIX!A59 -> 45720 | B59: =IF(A59="","",PRIX!B59*'QUANTITE DETENUES'!B59) -> 24081.075 | C59: =IF(B59="","",PRIX!C59*'QUANTITE DETENUES'!C59) -> 7028 | D59: =IF(C59="","",PRIX!D59*'QUANTITE DETENUES'!D59) -> 1707.0198 | E59: =IF(D59="","",PRIX!E59*'QUANTITE DETENUES'!E59) -> 2185.747 | F59: =IF(E59="","",PRIX!F59*'QUANTITE DETENUES'!F59) -> 2362.2371 | G59: =IF(F59="","",PRIX!G59*'QUANTITE DETENUES'!G59) -> 671.9388 | H59: =IF(G59="","",PRIX!H59*'QUANTITE DETENUES'!H59) -> 1610.8002 | I59: =IF(H59="","",PRIX!I59*'QUANTITE DETENUES'!I59) -> 367.71945 | ... S59: =IF(R59="","",PRIX!S59*'QUANTITE DETENUES'!S59) -> 96.8 | T59: =IF(A59="","",ARBITRAGES!M59) -> 940.26864 | U59: =IF(A59="","",SUM(B59:T59)) -> 44004.982 | V59: =IF(U59="","",1-T59/U59) -> 0.97863268
A60: =PRIX!A60 -> 45725 | B60: =IF(A60="","",PRIX!B60*'QUANTITE DETENUES'!B60) -> 23801.062 | C60: =IF(B60="","",PRIX!C60*'QUANTITE DETENUES'!C60) -> 6184.64 | D60: =IF(C60="","",PRIX!D60*'QUANTITE DETENUES'!D60) -> 1596.8895 | E60: =IF(D60="","",PRIX!E60*'QUANTITE DETENUES'!E60) -> 1974.2231 | F60: =IF(E60="","",PRIX!F60*'QUANTITE DETENUES'!F60) -> 2286.0359 | G60: =IF(F60="","",PRIX!G60*'QUANTITE DETENUES'!G60) -> 608.28144 | H60: =IF(G60="","",PRIX!H60*'QUANTITE DETENUES'!H60) -> 1500.7455 | I60: =IF(H60="","",PRIX!I60*'QUANTITE DETENUES'!I60) -> 350.209 | ... S60: =IF(R60="","",PRIX!S60*'QUANTITE DETENUES'!S60) -> 79.2 | T60: =IF(A60="","",ARBITRAGES!M60) -> 852.86864 | U60: =IF(A60="","",SUM(B60:T60)) -> 42004.476 | V60: =IF(U60="","",1-T60/U60) -> 0.97969577
A61: =PRIX!A61 -> 45734 | B61: =IF(A61="","",PRIX!B61*'QUANTITE DETENUES'!B61) -> 26041.162 | C61: =IF(B61="","",PRIX!C61*'QUANTITE DETENUES'!C61) -> 5622.4 | D61: =IF(C61="","",PRIX!D61*'QUANTITE DETENUES'!D61) -> 1622.3456 | E61: =IF(D61="","",PRIX!E61*'QUANTITE DETENUES'!E61) -> 1847.3088 | F61: =IF(E61="","",PRIX!F61*'QUANTITE DETENUES'!F61) -> 1943.1305 | G61: =IF(F61="","",PRIX!G61*'QUANTITE DETENUES'!G61) -> 565.8432 | H61: =IF(G61="","",PRIX!H61*'QUANTITE DETENUES'!H61) -> 1450.7206 | I61: =IF(H61="","",PRIX!I61*'QUANTITE DETENUES'!I61) -> 297.67765 | ... S61: =IF(R61="","",PRIX!S61*'QUANTITE DETENUES'!S61) -> 79.2 | T61: =IF(A61="","",ARBITRAGES!M61) -> 1205.3686 | U61: =IF(A61="","",SUM(B61:T61)) -> 43548.663 | V61: =IF(U61="","",1-T61/U61) -> 0.97232134
... A73: =PRIX!A73 -> 45779 | B73: =IF(A73="","",PRIX!B73*'QUANTITE DETENUES'!B73) -> 23505.512 | C73: =IF(B73="","",PRIX!C73*'QUANTITE DETENUES'!C73) -> 5524.56 | D73: =IF(C73="","",PRIX!D73*'QUANTITE DETENUES'!D73) -> 1442.085 | E73: =IF(D73="","",PRIX!E73*'QUANTITE DETENUES'!E73) -> 2940.2391 | F73: =IF(E73="","",PRIX!F73*'QUANTITE DETENUES'!F73) -> 3006.0359 | G73: =IF(F73="","",PRIX!G73*'QUANTITE DETENUES'!G73) -> 209.56083 | H73: =IF(G73="","",PRIX!H73*'QUANTITE DETENUES'!H73) -> 1500.7455 | I73: =IF(H73="","",PRIX!I73*'QUANTITE DETENUES'!I73) -> 504.1672 | ... S73: =IF(R73="","",PRIX!S73*'QUANTITE DETENUES'!S73) -> 127.6 | T73: =IF(A73="","",ARBITRAGES!M73) -> 2551.1596 | U73: =IF(A73="","",SUM(B73:T73)) -> 44157.819 | V73: =IF(U73="","",1-T73/U73) -> 0.94222632
A74: =PRIX!A75 -> 45785 | B74: =IF(A74="","",PRIX!B74*'QUANTITE DETENUES'!B75) -> 23961.056 | C74: =IF(B74="","",PRIX!C74*'QUANTITE DETENUES'!C75) -> 7673 | D74: =IF(C74="","",PRIX!D74*'QUANTITE DETENUES'!D75) -> 1487.1501 | E74: =IF(D74="","",PRIX!E74*'QUANTITE DETENUES'!E75) -> 3332.2709 | F74: =IF(E74="","",PRIX!F74*'QUANTITE DETENUES'!F75) -> 4509.0539 | G74: =IF(F74="","",PRIX!G74*'QUANTITE DETENUES'!G75) -> 238.37544 | H74: =IF(G74="","",PRIX!H74*'QUANTITE DETENUES'!H75) -> 1620.8051 | I74: =IF(H74="","",PRIX!I74*'QUANTITE DETENUES'!I75) -> 65.226631 | ... S74: =IF(R74="","",PRIX!S74*'QUANTITE DETENUES'!S75) -> 127.6 | T74: =IF(A74="","",ARBITRAGES!M75) -> 4837.3083 | U74: =IF(A74="","",SUM(B74:T74)) -> 51120.011 | V74: =IF(U74="","",1-T74/U74) -> 0.90537349
A75: =PRIX!A76 -> 45054 | B75: =IF(A75="","",PRIX!B76*'QUANTITE DETENUES'!B76) -> 23961.056 | C75: =IF(B75="","",PRIX!C76*'QUANTITE DETENUES'!C76) -> 7673 | D75: =IF(C75="","",PRIX!D76*'QUANTITE DETENUES'!D76) -> 1487.1501 | E75: =IF(D75="","",PRIX!E76*'QUANTITE DETENUES'!E76) -> 3332.2709 | F75: =IF(E75="","",PRIX!F76*'QUANTITE DETENUES'!F76) -> 4509.0539 | G75: =IF(F75="","",PRIX!G76*'QUANTITE DETENUES'!G76) -> 0 | H75: =IF(G75="","",PRIX!H76*'QUANTITE DETENUES'!H76) -> 1620.8051 | I75: =IF(H75="","",PRIX!I76*'QUANTITE DETENUES'!I76) -> 65.226631 | ... S75: =IF(R75="","",PRIX!S76*'QUANTITE DETENUES'!S76) -> 127.6 | T75: =IF(A75="","",ARBITRAGES!M76) -> 5059.86 | U75: =IF(A75="","",SUM(B75:T75)) -> 51104.187 | V75: =IF(U75="","",1-T75/U75) -> 0.90098933
A76: =PRIX!A77 -> 45786 | B76: =IF(A76="","",PRIX!B77*'QUANTITE DETENUES'!B77) -> 23921.536 | C76: =IF(B76="","",PRIX!C77*'QUANTITE DETENUES'!C77) -> 7695.5 | D76: =IF(C76="","",PRIX!D77*'QUANTITE DETENUES'!D77) -> 1487.1501 | E76: =IF(D76="","",PRIX!E77*'QUANTITE DETENUES'!E77) -> 3332.2709 | F76: =IF(E76="","",PRIX!F77*'QUANTITE DETENUES'!F77) -> 4059.0539 | G76: =IF(F76="","",PRIX!G77*'QUANTITE DETENUES'!G77) -> 0 | H76: =IF(G76="","",PRIX!H77*'QUANTITE DETENUES'!H77) -> 1620.8051 | I76: =IF(H76="","",PRIX!I77*'QUANTITE DETENUES'!I77) -> 65.226631 | ... S76: =IF(R76="","",PRIX!S77*'QUANTITE DETENUES'!S77) -> 127.6 | T76: =IF(A76="","",ARBITRAGES!M77) -> 5484.86 | U76: =IF(A76="","",SUM(B76:T76)) -> 51062.167 | V76: =IF(U76="","",1-T76/U76) -> 0.89258466
A77: =PRIX!A78 -> 45789 | B77: =IF(A77="","",PRIX!B78*'QUANTITE DETENUES'!B78) -> 24036.543 | C77: =IF(B77="","",PRIX!C78*'QUANTITE DETENUES'!C78) -> 7849.41 | D77: =IF(C77="","",PRIX!D78*'QUANTITE DETENUES'!D78) -> 1316.7997 | E77: =IF(D77="","",PRIX!E78*'QUANTITE DETENUES'!E78) -> 3442.5289 | F77: =IF(E77="","",PRIX!F78*'QUANTITE DETENUES'!F78) -> 4248.8563 | G77: =IF(F77="","",PRIX!G78*'QUANTITE DETENUES'!G78) -> 0 | H77: =IF(G77="","",PRIX!H78*'QUANTITE DETENUES'!H78) -> 1751.3947 | I77: =IF(H77="","",PRIX!I78*'QUANTITE DETENUES'!I78) -> 766.01904 | ... S77: =IF(R77="","",PRIX!S78*'QUANTITE DETENUES'!S78) -> 145.2 | T77: =IF(A77="","",ARBITRAGES!M78) -> 5731.61 | U77: =IF(A77="","",SUM(B77:T77)) -> 52809.097 | V77: =IF(U77="","",1-T77/U77) -> 0.89146548
A78: =PRIX!A79 -> 45790 | B78: =IF(A78="","",PRIX!B79*'QUANTITE DETENUES'!B79) -> 25221.224 | C78: =IF(B78="","",PRIX!C79*'QUANTITE DETENUES'!C79) -> 7695.5 | D78: =IF(C78="","",PRIX!D79*'QUANTITE DETENUES'!D79) -> 1241.554 | E78: =IF(D78="","",PRIX!E79*'QUANTITE DETENUES'!E79) -> 3442.5289 | F78: =IF(E78="","",PRIX!F79*'QUANTITE DETENUES'!F79) -> 4158.4551 | G78: =IF(F78="","",PRIX!G79*'QUANTITE DETENUES'!G79) -> 0 | H78: =IF(G78="","",PRIX!H79*'QUANTITE DETENUES'!H79) -> 1651.315 | I78: =IF(H78="","",PRIX!I79*'QUANTITE DETENUES'!I79) -> 707.4096 | ... S78: =IF(R78="","",PRIX!S79*'QUANTITE DETENUES'!S79) -> 136.84 | T78: =IF(A78="","",ARBITRAGES!M79) -> 4231.61 | U78: =IF(A78="","",SUM(B78:T78)) -> 51891.139 | V78: =IF(U78="","",1-T78/U78) -> 0.91845217
A79: =PRIX!A80 -> 45808 | B79: =IF(A79="","",PRIX!B80*'QUANTITE DETENUES'!B80) -> 25221.224 | C79: =IF(B79="","",PRIX!C80*'QUANTITE DETENUES'!C80) -> 7849.41 | D79: =IF(C79="","",PRIX!D80*'QUANTITE DETENUES'!D80) -> 1222.7425 | E79: =IF(D79="","",PRIX!E80*'QUANTITE DETENUES'!E80) -> 3049.097 | F79: =IF(E79="","",PRIX!F80*'QUANTITE DETENUES'!F80) -> 4096.0479 | G79: =IF(F79="","",PRIX!G80*'QUANTITE DETENUES'!G80) -> 0 | H79: =IF(G79="","",PRIX!H80*'QUANTITE DETENUES'!H80) -> 1451.1556 | I79: =IF(H79="","",PRIX!I80*'QUANTITE DETENUES'!I80) -> 567.1881 | ... S79: =IF(R79="","",PRIX!S80*'QUANTITE DETENUES'!S80) -> 136.84 | T79: =IF(A79="","",ARBITRAGES!M80) -> 3775.61 | U79: =IF(A79="","",SUM(B79:T79)) -> 50774.018 | V79: =IF(U79="","",1-T79/U79) -> 0.92563893
A80: =PRIX!A81 -> 45817 | B80: =IF(A80="","",PRIX!B81*'QUANTITE DETENUES'!B81) -> 24750.867 | C80: =IF(B80="","",PRIX!C81*'QUANTITE DETENUES'!C81) -> 8311.14 | D80: =IF(C80="","",PRIX!D81*'QUANTITE DETENUES'!D81) -> 1252.8408 | E80: =IF(D80="","",PRIX!E81*'QUANTITE DETENUES'!E81) -> 3147.455 | F80: =IF(E80="","",PRIX!F81*'QUANTITE DETENUES'!F81) -> 4505.6527 | G80: =IF(F80="","",PRIX!G81*'QUANTITE DETENUES'!G81) -> 0 | H80: =IF(G80="","",PRIX!H81*'QUANTITE DETENUES'!H81) -> 1501.1955 | I80: =IF(H80="","",PRIX!I81*'QUANTITE DETENUES'!I81) -> 630.209 | ... S80: =IF(R80="","",PRIX!S81*'QUANTITE DETENUES'!S81) -> 105.6 | T80: =IF(A80="","",ARBITRAGES!M81) -> 5930.2432 | U80: =IF(A80="","",SUM(B80:T80)) -> 53696.276 | V80: =IF(U80="","",1-T80/U80) -> 0.88955951
A81: =PRIX!A82 -> 45817 | B81: =IF(A81="","",PRIX!B82*'QUANTITE DETENUES'!B82) -> 22000.867 | C81: =IF(B81="","",PRIX!C82*'QUANTITE DETENUES'!C82) -> 8317.35 | D81: =IF(C81="","",PRIX!D82*'QUANTITE DETENUES'!D82) -> 1252.8408 | E81: =IF(D81="","",PRIX!E82*'QUANTITE DETENUES'!E82) -> 3154.24 | F81: =IF(E81="","",PRIX!F82*'QUANTITE DETENUES'!F82) -> 4505.6527 | G81: =IF(F81="","",PRIX!G82*'QUANTITE DETENUES'!G82) -> 0 | H81: =IF(G81="","",PRIX!H82*'QUANTITE DETENUES'!H82) -> 1501.1955 | I81: =IF(H81="","",PRIX!I82*'QUANTITE DETENUES'!I82) -> 630.316 | ... S81: =IF(R81="","",PRIX!S82*'QUANTITE DETENUES'!S82) -> 105.6 | T81: =IF(A81="","",ARBITRAGES!M82) -> 8690.2432 | U81: =IF(A81="","",SUM(B81:T81)) -> 53721.829 | V81: =IF(U81="","",1-T81/U81) -> 0.83823627
A82: =PRIX!A83 -> 45818 | B82: =IF(A82="","",PRIX!B83*'QUANTITE DETENUES'!B83) -> 23312.794 | C82: =IF(B82="","",PRIX!C83*'QUANTITE DETENUES'!C83) -> 8471.375 | D82: =IF(C82="","",PRIX!D83*'QUANTITE DETENUES'!D83) -> 1252.8408 | E82: =IF(D82="","",PRIX!E83*'QUANTITE DETENUES'!E83) -> 3154.24 | F82: =IF(E82="","",PRIX!F83*'QUANTITE DETENUES'!F83) -> 4505.6527 | G82: =IF(F82="","",PRIX!G83*'QUANTITE DETENUES'!G83) -> 0 | H82: =IF(G82="","",PRIX!H83*'QUANTITE DETENUES'!H83) -> 1501.1955 | I82: =IF(H82="","",PRIX!I83*'QUANTITE DETENUES'!I83) -> 630.316 | ... S82: =IF(R82="","",PRIX!S83*'QUANTITE DETENUES'!S83) -> 105.6 | T82: =IF(A82="","",ARBITRAGES!M83) -> 7390.2432 | U82: =IF(A82="","",SUM(B82:T82)) -> 53968.134 | V82: =IF(U82="","",1-T82/U82) -> 0.86306284
A83: =PRIX!A84 -> 45831 | B83: =IF(A83="","",PRIX!B84*'QUANTITE DETENUES'!B84) -> 22465.056 | C83: =IF(B83="","",PRIX!C84*'QUANTITE DETENUES'!C84) -> 8009.3 | D83: =IF(C83="","",PRIX!D84*'QUANTITE DETENUES'!D84) -> 1128.6854 | E83: =IF(D83="","",PRIX!E84*'QUANTITE DETENUES'!E84) -> 2858.53 | F83: =IF(E83="","",PRIX!F84*'QUANTITE DETENUES'!F84) -> 3788.8443 | G83: =IF(F83="","",PRIX!G84*'QUANTITE DETENUES'!G84) -> 0 | H83: =IF(G83="","",PRIX!H84*'QUANTITE DETENUES'!H84) -> 1401.1158 | I83: =IF(H83="","",PRIX!I84*'QUANTITE DETENUES'!I84) -> 485.34332 | ... S83: =IF(R83="","",PRIX!S84*'QUANTITE DETENUES'!S84) -> 83.6 | T83: =IF(A83="","",ARBITRAGES!M84) -> 6991.2432 | U83: =IF(A83="","",SUM(B83:T83)) -> 50244.473 | V83: =IF(U83="","",1-T83/U83) -> 0.86085548
A84: =PRIX!A85 -> 45831 | B84: =IF(A84="","",PRIX!B85*'QUANTITE DETENUES'!B85) -> 22465.056 | C84: =IF(B84="","",PRIX!C85*'QUANTITE DETENUES'!C85) -> 8009.3 | D84: =IF(C84="","",PRIX!D85*'QUANTITE DETENUES'!D85) -> 1128.6854 | E84: =IF(D84="","",PRIX!E85*'QUANTITE DETENUES'!E85) -> 2858.53 | F84: =IF(E84="","",PRIX!F85*'QUANTITE DETENUES'!F85) -> 3788.8443 | G84: =IF(F84="","",PRIX!G85*'QUANTITE DETENUES'!G85) -> 0 | H84: =IF(G84="","",PRIX!H85*'QUANTITE DETENUES'!H85) -> 1401.1158 | I84: =IF(H84="","",PRIX!I85*'QUANTITE DETENUES'!I85) -> 485.34332 | ... S84: =IF(R84="","",PRIX!S85*'QUANTITE DETENUES'!S85) -> 83.6 | T84: =IF(A84="","",ARBITRAGES!M85) -> 7131.2432 | U84: =IF(A84="","",SUM(B84:T84)) -> 50244.473 | V84: =IF(U84="","",1-T84/U84) -> 0.8580691
A85: =PRIX!A86 -> 45831 | B85: =IF(A85="","",PRIX!B86*'QUANTITE DETENUES'!B86) -> 22465.056 | C85: =IF(B85="","",PRIX!C86*'QUANTITE DETENUES'!C86) -> 8009.3 | D85: =IF(C85="","",PRIX!D86*'QUANTITE DETENUES'!D86) -> 1128.6854 | E85: =IF(D85="","",PRIX!E86*'QUANTITE DETENUES'!E86) -> 2858.53 | F85: =IF(E85="","",PRIX!F86*'QUANTITE DETENUES'!F86) -> 3788.8443 | G85: =IF(F85="","",PRIX!G86*'QUANTITE DETENUES'!G86) -> 0 | H85: =IF(G85="","",PRIX!H86*'QUANTITE DETENUES'!H86) -> 1401.1158 | I85: =IF(H85="","",PRIX!I86*'QUANTITE DETENUES'!I86) -> 485.34332 | ... S85: =IF(R85="","",PRIX!S86*'QUANTITE DETENUES'!S86) -> 83.6 | T85: =IF(A85="","",ARBITRAGES!M86) -> 7259.2432 | U85: =IF(A85="","",SUM(B85:T85)) -> 50252.473 | V85: =IF(U85="","",1-T85/U85) -> 0.85554456
A86: =PRIX!A87 -> 45831 | B86: =IF(A86="","",PRIX!B87*'QUANTITE DETENUES'!B87) -> 22465.056 | C86: =IF(B86="","",PRIX!C87*'QUANTITE DETENUES'!C87) -> 8009.3 | D86: =IF(C86="","",PRIX!D87*'QUANTITE DETENUES'!D87) -> 1128.6854 | E86: =IF(D86="","",PRIX!E87*'QUANTITE DETENUES'!E87) -> 2858.53 | F86: =IF(E86="","",PRIX!F87*'QUANTITE DETENUES'!F87) -> 3788.8443 | G86: =IF(F86="","",PRIX!G87*'QUANTITE DETENUES'!G87) -> 0 | H86: =IF(G86="","",PRIX!H87*'QUANTITE DETENUES'!H87) -> 1401.1158 | I86: =IF(H86="","",PRIX!I87*'QUANTITE DETENUES'!I87) -> 485.34332 | ... S86: =IF(R86="","",PRIX!S87*'QUANTITE DETENUES'!S87) -> 0 | T86: =IF(A86="","",ARBITRAGES!M87) -> 7342.7932 | U86: =IF(A86="","",SUM(B86:T86)) -> 50252.423 | V86: =IF(U86="","",1-T86/U86) -> 0.85388181
... A304: =PRIX!A305 | B304: =IF(A304="","",PRIX!B305*'QUANTITE DETENUES'!B305) | C304: =IF(B304="","",PRIX!C305*'QUANTITE DETENUES'!C305) | D304: =IF(C304="","",PRIX!D305*'QUANTITE DETENUES'!D305) | E304: =IF(D304="","",PRIX!E305*'QUANTITE DETENUES'!E305) | F304: =IF(E304="","",PRIX!F305*'QUANTITE DETENUES'!F305) | G304: =IF(F304="","",PRIX!G305*'QUANTITE DETENUES'!G305) | H304: =IF(G304="","",PRIX!H305*'QUANTITE DETENUES'!H305) | I304: =IF(H304="","",PRIX!I305*'QUANTITE DETENUES'!I305) | ... S304: =IF(R304="","",PRIX!S305*'QUANTITE DETENUES'!S305) | T304: =IF(A304="","",ARBITRAGES!M305) | U304: =IF(A304="","",SUM(B304:T304)) | V304: =IF(U304="","",1-T304/U304)
A305: =PRIX!A306 | B305: =IF(A305="","",PRIX!B306*'QUANTITE DETENUES'!B306) | C305: =IF(B305="","",PRIX!C306*'QUANTITE DETENUES'!C306) | D305: =IF(C305="","",PRIX!D306*'QUANTITE DETENUES'!D306) | E305: =IF(D305="","",PRIX!E306*'QUANTITE DETENUES'!E306) | F305: =IF(E305="","",PRIX!F306*'QUANTITE DETENUES'!F306) | G305: =IF(F305="","",PRIX!G306*'QUANTITE DETENUES'!G306) | H305: =IF(G305="","",PRIX!H306*'QUANTITE DETENUES'!H306) | I305: =IF(H305="","",PRIX!I306*'QUANTITE DETENUES'!I306) | ... S305: =IF(R305="","",PRIX!S306*'QUANTITE DETENUES'!S306) | T305: =IF(A305="","",ARBITRAGES!M306) | U305: =IF(A305="","",SUM(B305:T305)) | V305: =IF(U305="","",1-T305/U305) | AZ305: $TON | BA305: 4.755
A306: =PRIX!A307 | B306: =IF(A306="","",PRIX!B307*'QUANTITE DETENUES'!B307) | C306: =IF(B306="","",PRIX!C307*'QUANTITE DETENUES'!C307) | D306: =IF(C306="","",PRIX!D307*'QUANTITE DETENUES'!D307) | E306: =IF(D306="","",PRIX!E307*'QUANTITE DETENUES'!E307) | F306: =IF(E306="","",PRIX!F307*'QUANTITE DETENUES'!F307) | G306: =IF(F306="","",PRIX!G307*'QUANTITE DETENUES'!G307) | H306: =IF(G306="","",PRIX!H307*'QUANTITE DETENUES'!H307) | I306: =IF(H306="","",PRIX!I307*'QUANTITE DETENUES'!I307) | ... S306: =IF(R306="","",PRIX!S307*'QUANTITE DETENUES'!S307) | T306: =IF(A306="","",ARBITRAGES!M307) | U306: =IF(A306="","",SUM(B306:T306)) | V306: =IF(U306="","",1-T306/U306) | AZ306: $ETH | BA306: 2700
A307: =PRIX!A308 | B307: =IF(A307="","",PRIX!B308*'QUANTITE DETENUES'!B308) | C307: =IF(B307="","",PRIX!C308*'QUANTITE DETENUES'!C308) | D307: =IF(C307="","",PRIX!D308*'QUANTITE DETENUES'!D308) | E307: =IF(D307="","",PRIX!E308*'QUANTITE DETENUES'!E308) | F307: =IF(E307="","",PRIX!F308*'QUANTITE DETENUES'!F308) | G307: =IF(F307="","",PRIX!G308*'QUANTITE DETENUES'!G308) | H307: =IF(G307="","",PRIX!H308*'QUANTITE DETENUES'!H308) | I307: =IF(H307="","",PRIX!I308*'QUANTITE DETENUES'!I308) | ... S307: =IF(R307="","",PRIX!S308*'QUANTITE DETENUES'!S308) | T307: =IF(A307="","",ARBITRAGES!M308) | U307: =IF(A307="","",SUM(B307:T307)) | V307: =IF(U307="","",1-T307/U307) | AZ307: $ETH | BA307: 2700
A308: =PRIX!A309 | B308: =IF(A308="","",PRIX!B309*'QUANTITE DETENUES'!B309) | C308: =IF(B308="","",PRIX!C309*'QUANTITE DETENUES'!C309) | D308: =IF(C308="","",PRIX!D309*'QUANTITE DETENUES'!D309) | E308: =IF(D308="","",PRIX!E309*'QUANTITE DETENUES'!E309) | F308: =IF(E308="","",PRIX!F309*'QUANTITE DETENUES'!F309) | G308: =IF(F308="","",PRIX!G309*'QUANTITE DETENUES'!G309) | H308: =IF(G308="","",PRIX!H309*'QUANTITE DETENUES'!H309) | I308: =IF(H308="","",PRIX!I309*'QUANTITE DETENUES'!I309) | ... S308: =IF(R308="","",PRIX!S309*'QUANTITE DETENUES'!S309) | T308: =IF(A308="","",ARBITRAGES!M309) | U308: =IF(A308="","",SUM(B308:T308)) | V308: =IF(U308="","",1-T308/U308) | AZ308: $ETH | BA308: 2700
A309: =PRIX!A310 | B309: =IF(A309="","",PRIX!B310*'QUANTITE DETENUES'!B310) | C309: =IF(B309="","",PRIX!C310*'QUANTITE DETENUES'!C310) | D309: =IF(C309="","",PRIX!D310*'QUANTITE DETENUES'!D310) | E309: =IF(D309="","",PRIX!E310*'QUANTITE DETENUES'!E310) | F309: =IF(E309="","",PRIX!F310*'QUANTITE DETENUES'!F310) | G309: =IF(F309="","",PRIX!G310*'QUANTITE DETENUES'!G310) | H309: =IF(G309="","",PRIX!H310*'QUANTITE DETENUES'!H310) | I309: =IF(H309="","",PRIX!I310*'QUANTITE DETENUES'!I310) | ... S309: =IF(R309="","",PRIX!S310*'QUANTITE DETENUES'!S310) | T309: =IF(A309="","",ARBITRAGES!M310) | U309: =IF(A309="","",SUM(B309:T309)) | V309: =IF(U309="","",1-T309/U309) | AZ309: $TON | BA309: 4.755
A310: =PRIX!A311 | B310: =IF(A310="","",PRIX!B311*'QUANTITE DETENUES'!B311) | C310: =IF(B310="","",PRIX!C311*'QUANTITE DETENUES'!C311) | D310: =IF(C310="","",PRIX!D311*'QUANTITE DETENUES'!D311) | E310: =IF(D310="","",PRIX!E311*'QUANTITE DETENUES'!E311) | F310: =IF(E310="","",PRIX!F311*'QUANTITE DETENUES'!F311) | G310: =IF(F310="","",PRIX!G311*'QUANTITE DETENUES'!G311) | H310: =IF(G310="","",PRIX!H311*'QUANTITE DETENUES'!H311) | I310: =IF(H310="","",PRIX!I311*'QUANTITE DETENUES'!I311) | ... S310: =IF(R310="","",PRIX!S311*'QUANTITE DETENUES'!S311) | T310: =IF(A310="","",ARBITRAGES!M311) | U310: =IF(A310="","",SUM(B310:T310)) | V310: =IF(U310="","",1-T310/U310) | AZ310: $TON | BA310: 4.755
A311: =PRIX!A312 | B311: =IF(A311="","",PRIX!B312*'QUANTITE DETENUES'!B312) | C311: =IF(B311="","",PRIX!C312*'QUANTITE DETENUES'!C312) | D311: =IF(C311="","",PRIX!D312*'QUANTITE DETENUES'!D312) | E311: =IF(D311="","",PRIX!E312*'QUANTITE DETENUES'!E312) | F311: =IF(E311="","",PRIX!F312*'QUANTITE DETENUES'!F312) | G311: =IF(F311="","",PRIX!G312*'QUANTITE DETENUES'!G312) | H311: =IF(G311="","",PRIX!H312*'QUANTITE DETENUES'!H312) | I311: =IF(H311="","",PRIX!I312*'QUANTITE DETENUES'!I312) | ... S311: =IF(R311="","",PRIX!S312*'QUANTITE DETENUES'!S312) | T311: =IF(A311="","",ARBITRAGES!M312) | U311: =IF(A311="","",SUM(B311:T311)) | V311: =IF(U311="","",1-T311/U311) | AZ311: $TON | BA311: 4.755
A312: =PRIX!A313 | B312: =IF(A312="","",PRIX!B313*'QUANTITE DETENUES'!B313) | C312: =IF(B312="","",PRIX!C313*'QUANTITE DETENUES'!C313) | D312: =IF(C312="","",PRIX!D313*'QUANTITE DETENUES'!D313) | E312: =IF(D312="","",PRIX!E313*'QUANTITE DETENUES'!E313) | F312: =IF(E312="","",PRIX!F313*'QUANTITE DETENUES'!F313) | G312: =IF(F312="","",PRIX!G313*'QUANTITE DETENUES'!G313) | H312: =IF(G312="","",PRIX!H313*'QUANTITE DETENUES'!H313) | I312: =IF(H312="","",PRIX!I313*'QUANTITE DETENUES'!I313) | ... S312: =IF(R312="","",PRIX!S313*'QUANTITE DETENUES'!S313) | T312: =IF(A312="","",ARBITRAGES!M313) | U312: =IF(A312="","",SUM(B312:T312)) | V312: =IF(U312="","",1-T312/U312) | AZ312: $TON | BA312: 4.755
A313: =PRIX!A314 | B313: =IF(A313="","",PRIX!B314*'QUANTITE DETENUES'!B314) | C313: =IF(B313="","",PRIX!C314*'QUANTITE DETENUES'!C314) | D313: =IF(C313="","",PRIX!D314*'QUANTITE DETENUES'!D314) | E313: =IF(D313="","",PRIX!E314*'QUANTITE DETENUES'!E314) | F313: =IF(E313="","",PRIX!F314*'QUANTITE DETENUES'!F314) | G313: =IF(F313="","",PRIX!G314*'QUANTITE DETENUES'!G314) | H313: =IF(G313="","",PRIX!H314*'QUANTITE DETENUES'!H314) | I313: =IF(H313="","",PRIX!I314*'QUANTITE DETENUES'!I314) | ... S313: =IF(R313="","",PRIX!S314*'QUANTITE DETENUES'!S314) | T313: =IF(A313="","",ARBITRAGES!M314) | U313: =IF(A313="","",SUM(B313:T313)) | V313: =IF(U313="","",1-T313/U313) | AZ313: $ETH | BA313: 2700
A314: =PRIX!A315 | B314: =IF(A314="","",PRIX!B315*'QUANTITE DETENUES'!B315) | C314: =IF(B314="","",PRIX!C315*'QUANTITE DETENUES'!C315) | D314: =IF(C314="","",PRIX!D315*'QUANTITE DETENUES'!D315) | E314: =IF(D314="","",PRIX!E315*'QUANTITE DETENUES'!E315) | F314: =IF(E314="","",PRIX!F315*'QUANTITE DETENUES'!F315) | G314: =IF(F314="","",PRIX!G315*'QUANTITE DETENUES'!G315) | H314: =IF(G314="","",PRIX!H315*'QUANTITE DETENUES'!H315) | I314: =IF(H314="","",PRIX!I315*'QUANTITE DETENUES'!I315) | ... S314: =IF(R314="","",PRIX!S315*'QUANTITE DETENUES'!S315) | T314: =IF(A314="","",ARBITRAGES!M315) | U314: =IF(A314="","",SUM(B314:T314)) | V314: =IF(U314="","",1-T314/U314) | AZ314: $ETH | BA314: 2700
A315: =PRIX!A316 | B315: =IF(A315="","",PRIX!B316*'QUANTITE DETENUES'!B316) | C315: =IF(B315="","",PRIX!C316*'QUANTITE DETENUES'!C316) | D315: =IF(C315="","",PRIX!D316*'QUANTITE DETENUES'!D316) | E315: =IF(D315="","",PRIX!E316*'QUANTITE DETENUES'!E316) | F315: =IF(E315="","",PRIX!F316*'QUANTITE DETENUES'!F316) | G315: =IF(F315="","",PRIX!G316*'QUANTITE DETENUES'!G316) | H315: =IF(G315="","",PRIX!H316*'QUANTITE DETENUES'!H316) | I315: =IF(H315="","",PRIX!I316*'QUANTITE DETENUES'!I316) | ... S315: =IF(R315="","",PRIX!S316*'QUANTITE DETENUES'!S316) | T315: =IF(A315="","",ARBITRAGES!M316) | U315: =IF(A315="","",SUM(B315:T315)) | V315: =IF(U315="","",1-T315/U315) | AY315: $ETH | AZ315: 2700
A316: =PRIX!A317 | B316: =IF(A316="","",PRIX!B317*'QUANTITE DETENUES'!B317) | C316: =IF(B316="","",PRIX!C317*'QUANTITE DETENUES'!C317) | D316: =IF(C316="","",PRIX!D317*'QUANTITE DETENUES'!D317) | E316: =IF(D316="","",PRIX!E317*'QUANTITE DETENUES'!E317) | F316: =IF(E316="","",PRIX!F317*'QUANTITE DETENUES'!F317) | G316: =IF(F316="","",PRIX!G317*'QUANTITE DETENUES'!G317) | H316: =IF(G316="","",PRIX!H317*'QUANTITE DETENUES'!H317) | I316: =IF(H316="","",PRIX!I317*'QUANTITE DETENUES'!I317) | ... S316: =IF(R316="","",PRIX!S317*'QUANTITE DETENUES'!S317) | T316: =IF(A316="","",ARBITRAGES!M317) | U316: =IF(A316="","",SUM(B316:T316)) | V316: =IF(U316="","",1-T316/U316) | AY316: $ETH | AZ316: 2700
A317: =PRIX!A318 | B317: =IF(A317="","",PRIX!B318*'QUANTITE DETENUES'!B318) | C317: =IF(B317="","",PRIX!C318*'QUANTITE DETENUES'!C318) | D317: =IF(C317="","",PRIX!D318*'QUANTITE DETENUES'!D318) | E317: =IF(D317="","",PRIX!E318*'QUANTITE DETENUES'!E318) | F317: =IF(E317="","",PRIX!F318*'QUANTITE DETENUES'!F318) | G317: =IF(F317="","",PRIX!G318*'QUANTITE DETENUES'!G318) | H317: =IF(G317="","",PRIX!H318*'QUANTITE DETENUES'!H318) | I317: =IF(H317="","",PRIX!I318*'QUANTITE DETENUES'!I318) | ... S317: =IF(R317="","",PRIX!S318*'QUANTITE DETENUES'!S318) | T317: =IF(A317="","",ARBITRAGES!M318) | U317: =IF(A317="","",SUM(B317:T317)) | V317: =IF(U317="","",1-T317/U317) | AY317: $ETH | AZ317: 2700
A318: =PRIX!A319 | B318: =IF(A318="","",PRIX!B319*'QUANTITE DETENUES'!B319) | C318: =IF(B318="","",PRIX!C319*'QUANTITE DETENUES'!C319) | D318: =IF(C318="","",PRIX!D319*'QUANTITE DETENUES'!D319) | E318: =IF(D318="","",PRIX!E319*'QUANTITE DETENUES'!E319) | F318: =IF(E318="","",PRIX!F319*'QUANTITE DETENUES'!F319) | G318: =IF(F318="","",PRIX!G319*'QUANTITE DETENUES'!G319) | H318: =IF(G318="","",PRIX!H319*'QUANTITE DETENUES'!H319) | I318: =IF(H318="","",PRIX!I319*'QUANTITE DETENUES'!I319) | ... S318: =IF(R318="","",PRIX!S319*'QUANTITE DETENUES'!S319) | T318: =IF(A318="","",ARBITRAGES!M319) | U318: =IF(A318="","",SUM(B318:T318)) | V318: =IF(U318="","",1-T318/U318) | AY318: $ETH | AZ318: 2700
A319: =PRIX!A320 | B319: =IF(A319="","",PRIX!B320*'QUANTITE DETENUES'!B320) | C319: =IF(B319="","",PRIX!C320*'QUANTITE DETENUES'!C320) | D319: =IF(C319="","",PRIX!D320*'QUANTITE DETENUES'!D320) | E319: =IF(D319="","",PRIX!E320*'QUANTITE DETENUES'!E320) | F319: =IF(E319="","",PRIX!F320*'QUANTITE DETENUES'!F320) | G319: =IF(F319="","",PRIX!G320*'QUANTITE DETENUES'!G320) | H319: =IF(G319="","",PRIX!H320*'QUANTITE DETENUES'!H320) | I319: =IF(H319="","",PRIX!I320*'QUANTITE DETENUES'!I320) | ... S319: =IF(R319="","",PRIX!S320*'QUANTITE DETENUES'!S320) | T319: =IF(A319="","",ARBITRAGES!M320) | U319: =IF(A319="","",SUM(B319:T319)) | V319: =IF(U319="","",1-T319/U319) | AY319: $ETH | AZ319: 2920
A320: =PRIX!A321 | B320: =IF(A320="","",PRIX!B321*'QUANTITE DETENUES'!B321) | C320: =IF(B320="","",PRIX!C321*'QUANTITE DETENUES'!C321) | D320: =IF(C320="","",PRIX!D321*'QUANTITE DETENUES'!D321) | E320: =IF(D320="","",PRIX!E321*'QUANTITE DETENUES'!E321) | F320: =IF(E320="","",PRIX!F321*'QUANTITE DETENUES'!F321) | G320: =IF(F320="","",PRIX!G321*'QUANTITE DETENUES'!G321) | H320: =IF(G320="","",PRIX!H321*'QUANTITE DETENUES'!H321) | I320: =IF(H320="","",PRIX!I321*'QUANTITE DETENUES'!I321) | ... S320: =IF(R320="","",PRIX!S321*'QUANTITE DETENUES'!S321) | T320: =IF(A320="","",ARBITRAGES!M321) | U320: =IF(A320="","",SUM(B320:T320)) | V320: =IF(U320="","",1-T320/U320) | AY320: $ETH | AZ320: 2920
A321: =PRIX!A322 | B321: =IF(A321="","",PRIX!B322*'QUANTITE DETENUES'!B322) | C321: =IF(B321="","",PRIX!C322*'QUANTITE DETENUES'!C322) | D321: =IF(C321="","",PRIX!D322*'QUANTITE DETENUES'!D322) | E321: =IF(D321="","",PRIX!E322*'QUANTITE DETENUES'!E322) | F321: =IF(E321="","",PRIX!F322*'QUANTITE DETENUES'!F322) | G321: =IF(F321="","",PRIX!G322*'QUANTITE DETENUES'!G322) | H321: =IF(G321="","",PRIX!H322*'QUANTITE DETENUES'!H322) | I321: =IF(H321="","",PRIX!I322*'QUANTITE DETENUES'!I322) | ... S321: =IF(R321="","",PRIX!S322*'QUANTITE DETENUES'!S322) | T321: =IF(A321="","",ARBITRAGES!M322) | U321: =IF(A321="","",SUM(B321:T321)) | V321: =IF(U321="","",1-T321/U321) | AY321: $TON | AZ321: 5.1
A322: =PRIX!A323 | B322: =IF(A322="","",PRIX!B323*'QUANTITE DETENUES'!B323) | C322: =IF(B322="","",PRIX!C323*'QUANTITE DETENUES'!C323) | D322: =IF(C322="","",PRIX!D323*'QUANTITE DETENUES'!D323) | E322: =IF(D322="","",PRIX!E323*'QUANTITE DETENUES'!E323) | F322: =IF(E322="","",PRIX!F323*'QUANTITE DETENUES'!F323) | G322: =IF(F322="","",PRIX!G323*'QUANTITE DETENUES'!G323) | H322: =IF(G322="","",PRIX!H323*'QUANTITE DETENUES'!H323) | I322: =IF(H322="","",PRIX!I323*'QUANTITE DETENUES'!I323) | ... S322: =IF(R322="","",PRIX!S323*'QUANTITE DETENUES'!S323) | T322: =IF(A322="","",ARBITRAGES!M323) | U322: =IF(A322="","",SUM(B322:T322)) | V322: =IF(U322="","",1-T322/U322) | AY322: $TON | AZ322: 5.1
A323: =PRIX!A324 | B323: =IF(A323="","",PRIX!B324*'QUANTITE DETENUES'!B324) | C323: =IF(B323="","",PRIX!C324*'QUANTITE DETENUES'!C324) | D323: =IF(C323="","",PRIX!D324*'QUANTITE DETENUES'!D324) | E323: =IF(D323="","",PRIX!E324*'QUANTITE DETENUES'!E324) | F323: =IF(E323="","",PRIX!F324*'QUANTITE DETENUES'!F324) | G323: =IF(F323="","",PRIX!G324*'QUANTITE DETENUES'!G324) | H323: =IF(G323="","",PRIX!H324*'QUANTITE DETENUES'!H324) | I323: =IF(H323="","",PRIX!I324*'QUANTITE DETENUES'!I324) | ... S323: =IF(R323="","",PRIX!S324*'QUANTITE DETENUES'!S324) | T323: =IF(A323="","",ARBITRAGES!M324) | U323: =IF(A323="","",SUM(B323:T323)) | V323: =IF(U323="","",1-T323/U323) | AY323: $TON | AZ323: 5.5
A324: =PRIX!A325 | B324: =IF(A324="","",PRIX!B325*'QUANTITE DETENUES'!B325) | C324: =IF(B324="","",PRIX!C325*'QUANTITE DETENUES'!C325) | D324: =IF(C324="","",PRIX!D325*'QUANTITE DETENUES'!D325) | E324: =IF(D324="","",PRIX!E325*'QUANTITE DETENUES'!E325) | F324: =IF(E324="","",PRIX!F325*'QUANTITE DETENUES'!F325) | G324: =IF(F324="","",PRIX!G325*'QUANTITE DETENUES'!G325) | H324: =IF(G324="","",PRIX!H325*'QUANTITE DETENUES'!H325) | I324: =IF(H324="","",PRIX!I325*'QUANTITE DETENUES'!I325) | ... S324: =IF(R324="","",PRIX!S325*'QUANTITE DETENUES'!S325) | T324: =IF(A324="","",ARBITRAGES!M325) | U324: =IF(A324="","",SUM(B324:T324)) | V324: =IF(U324="","",1-T324/U324) | AY324: $TON | AZ324: 5.5
A325: =PRIX!A326 | B325: =IF(A325="","",PRIX!B326*'QUANTITE DETENUES'!B326) | C325: =IF(B325="","",PRIX!C326*'QUANTITE DETENUES'!C326) | D325: =IF(C325="","",PRIX!D326*'QUANTITE DETENUES'!D326) | E325: =IF(D325="","",PRIX!E326*'QUANTITE DETENUES'!E326) | F325: =IF(E325="","",PRIX!F326*'QUANTITE DETENUES'!F326) | G325: =IF(F325="","",PRIX!G326*'QUANTITE DETENUES'!G326) | H325: =IF(G325="","",PRIX!H326*'QUANTITE DETENUES'!H326) | I325: =IF(H325="","",PRIX!I326*'QUANTITE DETENUES'!I326) | ... S325: =IF(R325="","",PRIX!S326*'QUANTITE DETENUES'!S326) | T325: =IF(A325="","",ARBITRAGES!M326) | U325: =IF(A325="","",SUM(B325:T325)) | V325: =IF(U325="","",1-T325/U325)
A326: =PRIX!A327 | B326: =IF(A326="","",PRIX!B327*'QUANTITE DETENUES'!B327) | C326: =IF(B326="","",PRIX!C327*'QUANTITE DETENUES'!C327) | D326: =IF(C326="","",PRIX!D327*'QUANTITE DETENUES'!D327) | E326: =IF(D326="","",PRIX!E327*'QUANTITE DETENUES'!E327) | F326: =IF(E326="","",PRIX!F327*'QUANTITE DETENUES'!F327) | G326: =IF(F326="","",PRIX!G327*'QUANTITE DETENUES'!G327) | H326: =IF(G326="","",PRIX!H327*'QUANTITE DETENUES'!H327) | I326: =IF(H326="","",PRIX!I327*'QUANTITE DETENUES'!I327) | ... S326: =IF(R326="","",PRIX!S327*'QUANTITE DETENUES'!S327) | T326: =IF(A326="","",ARBITRAGES!M327) | U326: =IF(A326="","",SUM(B326:T326)) | V326: =IF(U326="","",1-T326/U326)
A327: =PRIX!A328 | B327: =IF(A327="","",PRIX!B328*'QUANTITE DETENUES'!B328) | C327: =IF(B327="","",PRIX!C328*'QUANTITE DETENUES'!C328) | D327: =IF(C327="","",PRIX!D328*'QUANTITE DETENUES'!D328) | E327: =IF(D327="","",PRIX!E328*'QUANTITE DETENUES'!E328) | F327: =IF(E327="","",PRIX!F328*'QUANTITE DETENUES'!F328) | G327: =IF(F327="","",PRIX!G328*'QUANTITE DETENUES'!G328) | H327: =IF(G327="","",PRIX!H328*'QUANTITE DETENUES'!H328) | I327: =IF(H327="","",PRIX!I328*'QUANTITE DETENUES'!I328) | ... S327: =IF(R327="","",PRIX!S328*'QUANTITE DETENUES'!S328) | T327: =IF(A327="","",ARBITRAGES!M328) | U327: =IF(A327="","",SUM(B327:T327)) | V327: =IF(U327="","",1-T327/U327)
A328: =PRIX!A329 | B328: =IF(A328="","",PRIX!B329*'QUANTITE DETENUES'!B329) | C328: =IF(B328="","",PRIX!C329*'QUANTITE DETENUES'!C329) | D328: =IF(C328="","",PRIX!D329*'QUANTITE DETENUES'!D329) | E328: =IF(D328="","",PRIX!E329*'QUANTITE DETENUES'!E329) | F328: =IF(E328="","",PRIX!F329*'QUANTITE DETENUES'!F329) | G328: =IF(F328="","",PRIX!G329*'QUANTITE DETENUES'!G329) | H328: =IF(G328="","",PRIX!H329*'QUANTITE DETENUES'!H329) | I328: =IF(H328="","",PRIX!I329*'QUANTITE DETENUES'!I329) | ... S328: =IF(R328="","",PRIX!S329*'QUANTITE DETENUES'!S329) | T328: =IF(A328="","",ARBITRAGES!M329) | U328: =IF(A328="","",SUM(B328:T328)) | V328: =IF(U328="","",1-T328/U328)
A329: =PRIX!A330 | B329: =IF(A329="","",PRIX!B330*'QUANTITE DETENUES'!B330) | C329: =IF(B329="","",PRIX!C330*'QUANTITE DETENUES'!C330) | D329: =IF(C329="","",PRIX!D330*'QUANTITE DETENUES'!D330) | E329: =IF(D329="","",PRIX!E330*'QUANTITE DETENUES'!E330) | F329: =IF(E329="","",PRIX!F330*'QUANTITE DETENUES'!F330) | G329: =IF(F329="","",PRIX!G330*'QUANTITE DETENUES'!G330) | H329: =IF(G329="","",PRIX!H330*'QUANTITE DETENUES'!H330) | I329: =IF(H329="","",PRIX!I330*'QUANTITE DETENUES'!I330) | ... S329: =IF(R329="","",PRIX!S330*'QUANTITE DETENUES'!S330) | T329: =IF(A329="","",ARBITRAGES!M330) | U329: =IF(A329="","",SUM(B329:T329)) | V329: =IF(U329="","",1-T329/U329)
A330: =PRIX!A331 | B330: =IF(A330="","",PRIX!B331*'QUANTITE DETENUES'!B331) | C330: =IF(B330="","",PRIX!C331*'QUANTITE DETENUES'!C331) | D330: =IF(C330="","",PRIX!D331*'QUANTITE DETENUES'!D331) | E330: =IF(D330="","",PRIX!E331*'QUANTITE DETENUES'!E331) | F330: =IF(E330="","",PRIX!F331*'QUANTITE DETENUES'!F331) | G330: =IF(F330="","",PRIX!G331*'QUANTITE DETENUES'!G331) | H330: =IF(G330="","",PRIX!H331*'QUANTITE DETENUES'!H331) | I330: =IF(H330="","",PRIX!I331*'QUANTITE DETENUES'!I331) | ... S330: =IF(R330="","",PRIX!S331*'QUANTITE DETENUES'!S331) | T330: =IF(A330="","",ARBITRAGES!M331) | U330: =IF(A330="","",SUM(B330:T330)) | V330: =IF(U330="","",1-T330/U330)
A331: =PRIX!A332 | B331: =IF(A331="","",PRIX!B332*'QUANTITE DETENUES'!B332) | C331: =IF(B331="","",PRIX!C332*'QUANTITE DETENUES'!C332) | D331: =IF(C331="","",PRIX!D332*'QUANTITE DETENUES'!D332) | E331: =IF(D331="","",PRIX!E332*'QUANTITE DETENUES'!E332) | F331: =IF(E331="","",PRIX!F332*'QUANTITE DETENUES'!F332) | G331: =IF(F331="","",PRIX!G332*'QUANTITE DETENUES'!G332) | H331: =IF(G331="","",PRIX!H332*'QUANTITE DETENUES'!H332) | I331: =IF(H331="","",PRIX!I332*'QUANTITE DETENUES'!I332) | ... S331: =IF(R331="","",PRIX!S332*'QUANTITE DETENUES'!S332) | T331: =IF(A331="","",ARBITRAGES!M332) | U331: =IF(A331="","",SUM(B331:T331)) | V331: =IF(U331="","",1-T331/U331)
A332: =PRIX!A333 | B332: =IF(A332="","",PRIX!B333*'QUANTITE DETENUES'!B333) | C332: =IF(B332="","",PRIX!C333*'QUANTITE DETENUES'!C333) | D332: =IF(C332="","",PRIX!D333*'QUANTITE DETENUES'!D333) | E332: =IF(D332="","",PRIX!E333*'QUANTITE DETENUES'!E333) | F332: =IF(E332="","",PRIX!F333*'QUANTITE DETENUES'!F333) | G332: =IF(F332="","",PRIX!G333*'QUANTITE DETENUES'!G333) | H332: =IF(G332="","",PRIX!H333*'QUANTITE DETENUES'!H333) | I332: =IF(H332="","",PRIX!I333*'QUANTITE DETENUES'!I333) | ... S332: =IF(R332="","",PRIX!S333*'QUANTITE DETENUES'!S333) | T332: =IF(A332="","",ARBITRAGES!M333) | U332: =IF(A332="","",SUM(B332:T332)) | V332: =IF(U332="","",1-T332/U332)
A333: =PRIX!A334 | B333: =IF(A333="","",PRIX!B334*'QUANTITE DETENUES'!B334) | C333: =IF(B333="","",PRIX!C334*'QUANTITE DETENUES'!C334) | D333: =IF(C333="","",PRIX!D334*'QUANTITE DETENUES'!D334) | E333: =IF(D333="","",PRIX!E334*'QUANTITE DETENUES'!E334) | F333: =IF(E333="","",PRIX!F334*'QUANTITE DETENUES'!F334) | G333: =IF(F333="","",PRIX!G334*'QUANTITE DETENUES'!G334) | H333: =IF(G333="","",PRIX!H334*'QUANTITE DETENUES'!H334) | I333: =IF(H333="","",PRIX!I334*'QUANTITE DETENUES'!I334) | ... S333: =IF(R333="","",PRIX!S334*'QUANTITE DETENUES'!S334) | T333: =IF(A333="","",ARBITRAGES!M334) | U333: =IF(A333="","",SUM(B333:T333)) | V333: =IF(U333="","",1-T333/U333)
A334: =PRIX!A335 | B334: =IF(A334="","",PRIX!B335*'QUANTITE DETENUES'!B335) | C334: =IF(B334="","",PRIX!C335*'QUANTITE DETENUES'!C335) | D334: =IF(C334="","",PRIX!D335*'QUANTITE DETENUES'!D335) | E334: =IF(D334="","",PRIX!E335*'QUANTITE DETENUES'!E335) | F334: =IF(E334="","",PRIX!F335*'QUANTITE DETENUES'!F335) | G334: =IF(F334="","",PRIX!G335*'QUANTITE DETENUES'!G335) | H334: =IF(G334="","",PRIX!H335*'QUANTITE DETENUES'!H335) | I334: =IF(H334="","",PRIX!I335*'QUANTITE DETENUES'!I335) | ... S334: =IF(R334="","",PRIX!S335*'QUANTITE DETENUES'!S335) | T334: =IF(A334="","",ARBITRAGES!M335) | U334: =IF(A334="","",SUM(B334:T334)) | V334: =IF(U334="","",1-T334/U334)
A335: =PRIX!A336 | B335: =IF(A335="","",PRIX!B336*'QUANTITE DETENUES'!B336) | C335: =IF(B335="","",PRIX!C336*'QUANTITE DETENUES'!C336) | D335: =IF(C335="","",PRIX!D336*'QUANTITE DETENUES'!D336) | E335: =IF(D335="","",PRIX!E336*'QUANTITE DETENUES'!E336) | F335: =IF(E335="","",PRIX!F336*'QUANTITE DETENUES'!F336) | G335: =IF(F335="","",PRIX!G336*'QUANTITE DETENUES'!G336) | H335: =IF(G335="","",PRIX!H336*'QUANTITE DETENUES'!H336) | I335: =IF(H335="","",PRIX!I336*'QUANTITE DETENUES'!I336) | ... S335: =IF(R335="","",PRIX!S336*'QUANTITE DETENUES'!S336) | T335: =IF(A335="","",ARBITRAGES!M336) | U335: =IF(A335="","",SUM(B335:T335)) | V335: =IF(U335="","",1-T335/U335)
A336: =PRIX!A337 | B336: =IF(A336="","",PRIX!B337*'QUANTITE DETENUES'!B337) | C336: =IF(B336="","",PRIX!C337*'QUANTITE DETENUES'!C337) | D336: =IF(C336="","",PRIX!D337*'QUANTITE DETENUES'!D337) | E336: =IF(D336="","",PRIX!E337*'QUANTITE DETENUES'!E337) | F336: =IF(E336="","",PRIX!F337*'QUANTITE DETENUES'!F337) | G336: =IF(F336="","",PRIX!G337*'QUANTITE DETENUES'!G337) | H336: =IF(G336="","",PRIX!H337*'QUANTITE DETENUES'!H337) | I336: =IF(H336="","",PRIX!I337*'QUANTITE DETENUES'!I337) | ... S336: =IF(R336="","",PRIX!S337*'QUANTITE DETENUES'!S337) | T336: =IF(A336="","",ARBITRAGES!M337) | U336: =IF(A336="","",SUM(B336:T336)) | V336: =IF(U336="","",1-T336/U336)
... A418: =PRIX!A419 | B418: =IF(A418="","",PRIX!B419*'QUANTITE DETENUES'!B419) | C418: =IF(B418="","",PRIX!C419*'QUANTITE DETENUES'!C419) | D418: =IF(C418="","",PRIX!D419*'QUANTITE DETENUES'!D419) | E418: =IF(D418="","",PRIX!E419*'QUANTITE DETENUES'!E419) | F418: =IF(E418="","",PRIX!F419*'QUANTITE DETENUES'!F419) | G418: =IF(F418="","",PRIX!G419*'QUANTITE DETENUES'!G419) | H418: =IF(G418="","",PRIX!H419*'QUANTITE DETENUES'!H419) | I418: =IF(H418="","",PRIX!I419*'QUANTITE DETENUES'!I419) | ... S418: =IF(R418="","",PRIX!S419*'QUANTITE DETENUES'!S419) | T418: =IF(A418="","",ARBITRAGES!M419) | U418: =IF(A418="","",SUM(B418:T418)) | V418: =IF(U418="","",1-T418/U418)

Sheet Exposition
B1: Exposition | V1: $$$
A2: DATE | B2: TOTAL | C2: $BTC | D2: $ETH | E2: $TON | F2: $SOL | G2: $TAO | H2: $RON | I2: $LINK | J2: $DOGE | K2: $SHIB | L2: $CAKE | M2: $JUP | N2: $AAVE | O2: $CKB | P2: $PENDLE | Q2: $BOME | R2: $PEPE | S2: $WIF | T2: $RAY | U2: USDC | V2: USDC | W2: TOTAL
A3: =ARBITRAGES!E3 -> 45515 | B3: =IF(W3="","",1-V3/W3) -> 0.44086113 | C3: =IF(A3="","",'Historique détail'!B3/$W3) -> 0.1612944 | D3: =IF(B3="","",'Historique détail'!C3/$W3) -> 0.13127176 | E3: =IF(C3="","",'Historique détail'!D3/$W3) -> 0 | F3: =IF(D3="","",'Historique détail'!E3/$W3) -> 0.12606425 | G3: =IF(E3="","",'Historique détail'!F3/$W3) -> 0 | H3: =IF(F3="","",'Historique détail'!G3/$W3) -> 0 | I3: =IF(G3="","",'Historique détail'!H3/$W3) -> 0 | J3: =IF(H3="","",'Historique détail'!I3/$W3) -> 0 | ... T3: =IF(R3="","",'Historique détail'!S3/$W3) -> 0 | U3: =IF(T3="","",V3/W3) -> 0.55913887 | V3: =ARBITRAGES!M3 -> 21550 | W3: =IF(V3="","",'Historique détail'!U3) -> 38541.409
A4: =IF(ARBITRAGES!E4="","",ARBITRAGES!E4) -> 45515 | B4: =IF(W4="","",1-V4/W4) -> 0.64147132 | C4: =IF(A4="","",'Historique détail'!B4/$W4) -> 0.36651694 | D4: =IF(B4="","",'Historique détail'!C4/$W4) -> 0.12910602 | E4: =IF(C4="","",'Historique détail'!D4/$W4) -> 0 | F4: =IF(D4="","",'Historique détail'!E4/$W4) -> 0.12398442 | G4: =IF(E4="","",'Historique détail'!F4/$W4) -> 0 | H4: =IF(F4="","",'Historique détail'!G4/$W4) -> 0 | I4: =IF(G4="","",'Historique détail'!H4/$W4) -> 0 | J4: =IF(H4="","",'Historique détail'!I4/$W4) -> 0 | ... T4: =IF(R4="","",'Historique détail'!S4/$W4) -> 0 | U4: =IF(T4="","",V4/W4) -> 0.35852868 | V4: =IF(A4="","",ARBITRAGES!M4) -> 14050 | W4: =IF(V4="","",'Historique détail'!U4) -> 39187.939
A5: =IF(ARBITRAGES!E5="","",ARBITRAGES!E5) -> 45516 | B5: =IF(W5="","",1-V5/W5) -> 0.71242724 | C5: =IF(A5="","",'Historique détail'!B5/$W5) -> 0.35480733 | D5: =IF(B5="","",'Historique détail'!C5/$W5) -> 0.21403153 | E5: =IF(C5="","",'Historique détail'!D5/$W5) -> 0 | F5: =IF(D5="","",'Historique détail'!E5/$W5) -> 0.1208915 | G5: =IF(E5="","",'Historique détail'!F5/$W5) -> 0 | H5: =IF(F5="","",'Historique détail'!G5/$W5) -> 0 | I5: =IF(G5="","",'Historique détail'!H5/$W5) -> 0 | J5: =IF(H5="","",'Historique détail'!I5/$W5) -> 0 | ... T5: =IF(R5="","",'Historique détail'!S5/$W5) -> 0 | U5: =IF(T5="","",V5/W5) -> 0.28757276 | V5: =IF(A5="","",ARBITRAGES!M5) -> 11050 | W5: =IF(V5="","",'Historique détail'!U5) -> 38425.058
A6: =IF(ARBITRAGES!E6="","",ARBITRAGES!E6) -> 45517 | B6: =IF(W6="","",1-V6/W6) -> 0.74482861 | C6: =IF(A6="","",'Historique détail'!B6/$W6) -> 0.35845328 | D6: =IF(B6="","",'Historique détail'!C6/$W6) -> 0.21450352 | E6: =IF(C6="","",'Historique détail'!D6/$W6) -> 0 | F6: =IF(D6="","",'Historique détail'!E6/$W6) -> 0.14917465 | G6: =IF(E6="","",'Historique détail'!F6/$W6) -> 0 | H6: =IF(F6="","",'Historique détail'!G6/$W6) -> 0 | I6: =IF(G6="","",'Historique détail'!H6/$W6) -> 0 | J6: =IF(H6="","",'Historique détail'!I6/$W6) -> 0 | ... T6: =IF(R6="","",'Historique détail'!S6/$W6) -> 0 | U6: =IF(T6="","",V6/W6) -> 0.25517139 | V6: =IF(A6="","",ARBITRAGES!M6) -> 9900 | W6: =IF(V6="","",'Historique détail'!U6) -> 38797.452
A7: =IF(ARBITRAGES!E7="","",ARBITRAGES!E7) -> 45518 | B7: =IF(W7="","",1-V7/W7) -> 0.76659269 | C7: =IF(A7="","",'Historique détail'!B7/$W7) -> 0.35827955 | D7: =IF(B7="","",'Historique détail'!C7/$W7) -> 0.21439956 | E7: =IF(C7="","",'Historique détail'!D7/$W7) -> 0 | F7: =IF(D7="","",'Historique détail'!E7/$W7) -> 0.14910236 | G7: =IF(E7="","",'Historique détail'!F7/$W7) -> 0.022204609 | H7: =IF(F7="","",'Historique détail'!G7/$W7) -> 0 | I7: =IF(G7="","",'Historique détail'!H7/$W7) -> 0 | J7: =IF(H7="","",'Historique détail'!I7/$W7) -> 0 | ... T7: =IF(R7="","",'Historique détail'!S7/$W7) -> 0 | U7: =IF(T7="","",V7/W7) -> 0.23340731 | V7: =IF(A7="","",ARBITRAGES!M7) -> 9060 | W7: =IF(V7="","",'Historique détail'!U7) -> 38816.265
A8: =IF(ARBITRAGES!E8="","",ARBITRAGES!E8) -> 45518 | B8: =IF(W8="","",1-V8/W8) -> 0.77469512 | C8: =IF(A8="","",'Historique détail'!B8/$W8) -> 0.35809505 | D8: =IF(B8="","",'Historique détail'!C8/$W8) -> 0.21428915 | E8: =IF(C8="","",'Historique détail'!D8/$W8) -> 0 | F8: =IF(D8="","",'Historique détail'!E8/$W8) -> 0.14902557 | G8: =IF(E8="","",'Historique détail'!F8/$W8) -> 0.022193174 | H8: =IF(F8="","",'Historique détail'!G8/$W8) -> 0.0084972126 | I8: =IF(G8="","",'Historique détail'!H8/$W8) -> 0 | J8: =IF(H8="","",'Historique détail'!I8/$W8) -> 0 | ... T8: =IF(R8="","",'Historique détail'!S8/$W8) -> 0 | U8: =IF(T8="","",V8/W8) -> 0.22530488 | V8: =IF(A8="","",ARBITRAGES!M8) -> 8750 | W8: =IF(V8="","",'Historique détail'!U8) -> 38836.265
A9: =IF(ARBITRAGES!E9="","",ARBITRAGES!E9) -> 45519 | B9: =IF(W9="","",1-V9/W9) -> 0.84210348 | C9: =IF(A9="","",'Historique détail'!B9/$W9) -> 0.34798075 | D9: =IF(B9="","",'Historique détail'!C9/$W9) -> 0.21360685 | E9: =IF(C9="","",'Historique détail'!D9/$W9) -> 0.072592598 | F9: =IF(D9="","",'Historique détail'!E9/$W9) -> 0.15520403 | G9: =IF(E9="","",'Historique détail'!F9/$W9) -> 0.021552874 | H9: =IF(F9="","",'Historique détail'!G9/$W9) -> 0.008579044 | I9: =IF(G9="","",'Historique détail'!H9/$W9) -> 0 | J9: =IF(H9="","",'Historique détail'!I9/$W9) -> 0 | ... T9: =IF(R9="","",'Historique détail'!S9/$W9) -> 0 | U9: =IF(T9="","",V9/W9) -> 0.15789652 | V9: =IF(A9="","",ARBITRAGES!M9) -> 6000 | W9: =IF(V9="","",'Historique détail'!U9) -> 37999.572
A10: =IF(ARBITRAGES!E10="","",ARBITRAGES!E10) -> 45522 | B10: =IF(W10="","",1-V10/W10) -> 0.88348498 | C10: =IF(A10="","",'Historique détail'!B10/$W10) -> 0.39536689 | D10: =IF(B10="","",'Historique détail'!C10/$W10) -> 0.2121491 | E10: =IF(C10="","",'Historique détail'!D10/$W10) -> 0.073181502 | F10: =IF(D10="","",'Historique détail'!E10/$W10) -> 0.14903934 | G10: =IF(E10="","",'Historique détail'!F10/$W10) -> 0.022759267 | H10: =IF(F10="","",'Historique détail'!G10/$W10) -> 0.0085288995 | I10: =IF(G10="","",'Historique détail'!H10/$W10) -> 0 | J10: =IF(H10="","",'Historique détail'!I10/$W10) -> 0 | ... T10: =IF(R10="","",'Historique détail'!S10/$W10) -> 0 | U10: =IF(T10="","",V10/W10) -> 0.11651502 | V10: =IF(A10="","",ARBITRAGES!M10) -> 4500 | W10: =IF(V10="","",'Historique détail'!U10) -> 38621.63
A11: =IF(ARBITRAGES!E11="","",ARBITRAGES!E11) -> 45527 | B11: =IF(W11="","",1-V11/W11) -> 0.87908988 | C11: =IF(A11="","",'Historique détail'!B11/$W11) -> 0.40198936 | D11: =IF(B11="","",'Historique détail'!C11/$W11) -> 0.20944377 | E11: =IF(C11="","",'Historique détail'!D11/$W11) -> 0.070852093 | F11: =IF(D11="","",'Historique détail'!E11/$W11) -> 0.14603259 | G11: =IF(E11="","",'Historique détail'!F11/$W11) -> 0.017369132 | H11: =IF(F11="","",'Historique détail'!G11/$W11) -> 0.0088692379 | I11: =IF(G11="","",'Historique détail'!H11/$W11) -> 0 | J11: =IF(H11="","",'Historique détail'!I11/$W11) -> 0 | ... T11: =IF(R11="","",'Historique détail'!S11/$W11) -> 0 | U11: =IF(T11="","",V11/W11) -> 0.12091012 | V11: =IF(A11="","",ARBITRAGES!M11) -> 4845 | W11: =IF(V11="","",'Historique détail'!U11) -> 40071.087
A12: =IF(ARBITRAGES!E12="","",ARBITRAGES!E12) -> 45527 | B12: =IF(W12="","",1-V12/W12) -> 0.841892 | C12: =IF(A12="","",'Historique détail'!B12/$W12) -> 0.40139125 | D12: =IF(B12="","",'Historique détail'!C12/$W12) -> 0.20913214 | E12: =IF(C12="","",'Historique détail'!D12/$W12) -> 0.070746674 | F12: =IF(D12="","",'Historique détail'!E12/$W12) -> 0.10992541 | G12: =IF(E12="","",'Historique détail'!F12/$W12) -> 0.017343289 | H12: =IF(F12="","",'Historique détail'!G12/$W12) -> 0.0088560415 | I12: =IF(G12="","",'Historique détail'!H12/$W12) -> 0 | J12: =IF(H12="","",'Historique détail'!I12/$W12) -> 0 | ... T12: =IF(R12="","",'Historique détail'!S12/$W12) -> 0 | U12: =IF(T12="","",V12/W12) -> 0.158108 | V12: =IF(A12="","",ARBITRAGES!M12) -> 6345 | W12: =IF(V12="","",'Historique détail'!U12) -> 40130.796
A13: =IF(ARBITRAGES!E13="","",ARBITRAGES!E13) -> 45528 | B13: =IF(W13="","",1-V13/W13) -> 0.80001846 | C13: =IF(A13="","",'Historique détail'!B13/$W13) -> 0.40011523 | D13: =IF(B13="","",'Historique détail'!C13/$W13) -> 0.20972434 | E13: =IF(C13="","",'Historique détail'!D13/$W13) -> 0.070215417 | F13: =IF(D13="","",'Historique détail'!E13/$W13) -> 0.069555296 | G13: =IF(E13="","",'Historique détail'!F13/$W13) -> 0.016775169 | H13: =IF(F13="","",'Historique détail'!G13/$W13) -> 0.0088032958 | I13: =IF(G13="","",'Historique détail'!H13/$W13) -> 0 | J13: =IF(H13="","",'Historique détail'!I13/$W13) -> 0 | ... T13: =IF(R13="","",'Historique détail'!S13/$W13) -> 0 | U13: =IF(T13="","",V13/W13) -> 0.19998154 | V13: =IF(A13="","",ARBITRAGES!M13) -> 8178 | W13: =IF(V13="","",'Historique détail'!U13) -> 40893.775
A14: =IF(ARBITRAGES!E14="","",ARBITRAGES!E14) -> 45529 | B14: =IF(W14="","",1-V14/W14) -> 0.80861201 | C14: =IF(A14="","",'Historique détail'!B14/$W14) -> 0.40532461 | D14: =IF(B14="","",'Historique détail'!C14/$W14) -> 0.21111044 | E14: =IF(C14="","",'Historique détail'!D14/$W14) -> 0.071194192 | F14: =IF(D14="","",'Historique détail'!E14/$W14) -> 0.070901265 | G14: =IF(E14="","",'Historique détail'!F14/$W14) -> 0.016302129 | H14: =IF(F14="","",'Historique détail'!G14/$W14) -> 0.0087742346 | I14: =IF(G14="","",'Historique détail'!H14/$W14) -> 0 | J14: =IF(H14="","",'Historique détail'!I14/$W14) -> 0 | ... T14: =IF(R14="","",'Historique détail'!S14/$W14) -> 0 | U14: =IF(T14="","",V14/W14) -> 0.19138799 | V14: =IF(A14="","",ARBITRAGES!M14) -> 7678 | W14: =IF(V14="","",'Historique détail'!U14) -> 40117.46
A15: =IF(ARBITRAGES!E15="","",ARBITRAGES!E15) -> 45530 | B15: =IF(W15="","",1-V15/W15) -> 0.85917964 | C15: =IF(A15="","",'Historique détail'!B15/$W15) -> 0.4614041 | D15: =IF(B15="","",'Historique détail'!C15/$W15) -> 0.20472213 | E15: =IF(C15="","",'Historique détail'!D15/$W15) -> 0.070947782 | F15: =IF(D15="","",'Historique détail'!E15/$W15) -> 0.071267985 | G15: =IF(E15="","",'Historique détail'!F15/$W15) -> 0.0173262 | H15: =IF(F15="","",'Historique détail'!G15/$W15) -> 0.0085140023 | I15: =IF(G15="","",'Historique détail'!H15/$W15) -> 0 | J15: =IF(H15="","",'Historique détail'!I15/$W15) -> 0 | ... T15: =IF(R15="","",'Historique détail'!S15/$W15) -> 0 | U15: =IF(T15="","",V15/W15) -> 0.14082036 | V15: =IF(A15="","",ARBITRAGES!M15) -> 5478 | W15: =IF(V15="","",'Historique détail'!U15) -> 38900.624
... A26: =IF(ARBITRAGES!E26="","",ARBITRAGES!E26) -> 45558 | B26: =IF(W26="","",1-V26/W26) -> 0.94402055 | C26: =IF(A26="","",'Historique détail'!B26/$W26) -> 0.45798023 | D26: =IF(B26="","",'Historique détail'!C26/$W26) -> 0.19875574 | E26: =IF(C26="","",'Historique détail'!D26/$W26) -> 0.069564481 | F26: =IF(D26="","",'Historique détail'!E26/$W26) -> 0.064358955 | G26: =IF(E26="","",'Historique détail'!F26/$W26) -> 0.065231863 | H26: =IF(F26="","",'Historique détail'!G26/$W26) -> 0.028796064 | I26: =IF(G26="","",'Historique détail'!H26/$W26) -> 0.028036984 | J26: =IF(H26="","",'Historique détail'!I26/$W26) -> 0.0072051375 | ... T26: =IF(R26="","",'Historique détail'!S26/$W26) -> 0 | U26: =IF(T26="","",V26/W26) -> 0.05597945 | V26: =IF(A26="","",ARBITRAGES!M26) -> 2286.14 | W26: =IF(V26="","",'Historique détail'!U26) -> 40838.915
A27: =IF(ARBITRAGES!E27="","",ARBITRAGES!E27) -> 45568 | B27: =IF(W27="","",1-V27/W27) -> 0.94629872 | C27: =IF(A27="","",'Historique détail'!B27/$W27) -> 0.46076976 | D27: =IF(B27="","",'Historique détail'!C27/$W27) -> 0.1963663 | E27: =IF(C27="","",'Historique détail'!D27/$W27) -> 0.068826185 | F27: =IF(D27="","",'Historique détail'!E27/$W27) -> 0.063707176 | G27: =IF(E27="","",'Historique détail'!F27/$W27) -> 0.066673318 | H27: =IF(F27="","",'Historique détail'!G27/$W27) -> 0.028720829 | I27: =IF(G27="","",'Historique détail'!H27/$W27) -> 0.027182213 | J27: =IF(H27="","",'Historique détail'!I27/$W27) -> 0.0076161484 | ... T27: =IF(R27="","",'Historique détail'!S27/$W27) -> 0 | U27: =IF(T27="","",V27/W27) -> 0.053701283 | V27: =IF(A27="","",ARBITRAGES!M27) -> 2094.14 | W27: =IF(V27="","",'Historique détail'!U27) -> 38996.089 | X27: 1
A28: =IF(ARBITRAGES!E28="","",ARBITRAGES!E28) -> 45586 | B28: =IF(W28="","",1-V28/W28) -> 0.93572772 | C28: =IF(A28="","",'Historique détail'!B28/$W28) -> 0.46553486 | D28: =IF(B28="","",'Historique détail'!C28/$W28) -> 0.17637159 | E28: =IF(C28="","",'Historique détail'!D28/$W28) -> 0.062299349 | F28: =IF(D28="","",'Historique détail'!E28/$W28) -> 0.070523973 | G28: =IF(E28="","",'Historique détail'!F28/$W28) -> 0.070404585 | H28: =IF(F28="","",'Historique détail'!G28/$W28) -> 0.027422339 | I28: =IF(G28="","",'Historique détail'!H28/$W28) -> 0.027491066 | J28: =IF(H28="","",'Historique détail'!I28/$W28) -> 0.0093870537 | ... T28: =IF(R28="","",'Historique détail'!S28/$W28) -> 0 | U28: =IF(T28="","",V28/W28) -> 0.064272281 | V28: =IF(A28="","",ARBITRAGES!M28) -> 2805.52 | W28: =IF(V28="","",'Historique détail'!U28) -> 43650.544
A29: =IF(ARBITRAGES!E29="","",ARBITRAGES!E29) -> 45591 | B29: =IF(W29="","",1-V29/W29) -> 0.94154366 | C29: =IF(A29="","",'Historique détail'!B29/$W29) -> 0.44474646 | D29: =IF(B29="","",'Historique détail'!C29/$W29) -> 0.22748982 | E29: =IF(C29="","",'Historique détail'!D29/$W29) -> 0.06083164 | F29: =IF(D29="","",'Historique détail'!E29/$W29) -> 0.068267419 | G29: =IF(E29="","",'Historique détail'!F29/$W29) -> 0.059861442 | H29: =IF(F29="","",'Historique détail'!G29/$W29) -> 0.023700809 | I29: =IF(G29="","",'Historique détail'!H29/$W29) -> 0.024829419 | J29: =IF(H29="","",'Historique détail'!I29/$W29) -> 0.0083178555 | ... T29: =IF(R29="","",'Historique détail'!S29/$W29) -> 0 | U29: =IF(T29="","",V29/W29) -> 0.058456342 | V29: =IF(A29="","",ARBITRAGES!M29) -> 2589.7495 | W29: =IF(V29="","",'Historique détail'!U29) -> 44302.285
A30: =IF(ARBITRAGES!E30="","",ARBITRAGES!E30) -> 45594 | B30: =IF(W30="","",1-V30/W30) -> 0.93736816 | C30: =IF(A30="","",'Historique détail'!B30/$W30) -> 0.48273964 | D30: =IF(B30="","",'Historique détail'!C30/$W30) -> 0.16955887 | E30: =IF(C30="","",'Historique détail'!D30/$W30) -> 0.062887176 | F30: =IF(D30="","",'Historique détail'!E30/$W30) -> 0.069663906 | G30: =IF(E30="","",'Historique détail'!F30/$W30) -> 0.06534423 | H30: =IF(F30="","",'Historique détail'!G30/$W30) -> 0.024566364 | I30: =IF(G30="","",'Historique détail'!H30/$W30) -> 0.0262645 | J30: =IF(H30="","",'Historique détail'!I30/$W30) -> 0.010771841 | ... T30: =IF(R30="","",'Historique détail'!S30/$W30) -> 0 | U30: =IF(T30="","",V30/W30) -> 0.062631842 | V30: =IF(A30="","",ARBITRAGES!M30) -> 2766.2029 | W30: =IF(V30="","",'Historique détail'!U30) -> 44166.08 | X30: 1
A31: =IF(ARBITRAGES!E31="","",ARBITRAGES!E31) -> 45595 | B31: =IF(W31="","",1-V31/W31) -> 0.94265986 | C31: =IF(A31="","",'Historique détail'!B31/$W31) -> 0.49055571 | D31: =IF(B31="","",'Historique détail'!C31/$W31) -> 0.16678312 | E31: =IF(C31="","",'Historique détail'!D31/$W31) -> 0.065532397 | F31: =IF(D31="","",'Historique détail'!E31/$W31) -> 0.06764895 | G31: =IF(E31="","",'Historique détail'!F31/$W31) -> 0.065223047 | H31: =IF(F31="","",'Historique détail'!G31/$W31) -> 0.023019909 | I31: =IF(G31="","",'Historique détail'!H31/$W31) -> 0.026808901 | J31: =IF(H31="","",'Historique détail'!I31/$W31) -> 0.010485259 | ... T31: =IF(R31="","",'Historique détail'!S31/$W31) -> 0 | U31: =IF(T31="","",V31/W31) -> 0.057340138 | V31: =IF(A31="","",ARBITRAGES!M31) -> 2406.2029 | W31: =IF(V31="","",'Historique détail'!U31) -> 41963.675
A32: =IF(ARBITRAGES!E32="","",ARBITRAGES!E32) -> 45598 | B32: =IF(W32="","",1-V32/W32) -> 0.95806244 | C32: =IF(A32="","",'Historique détail'!B32/$W32) -> 0.49550171 | D32: =IF(B32="","",'Historique détail'!C32/$W32) -> 0.16871063 | E32: =IF(C32="","",'Historique détail'!D32/$W32) -> 0.0622312 | F32: =IF(D32="","",'Historique détail'!E32/$W32) -> 0.066900422 | G32: =IF(E32="","",'Historique détail'!F32/$W32) -> 0.061469097 | H32: =IF(F32="","",'Historique détail'!G32/$W32) -> 0.021867167 | I32: =IF(G32="","",'Historique détail'!H32/$W32) -> 0.026073338 | J32: =IF(H32="","",'Historique détail'!I32/$W32) -> 0.011634612 | ... T32: =IF(R32="","",'Historique détail'!S32/$W32) -> 0 | U32: =IF(T32="","",V32/W32) -> 0.041937561 | V32: =IF(A32="","",ARBITRAGES!M32) -> 1704.9529 | W32: =IF(V32="","",'Historique détail'!U32) -> 40654.557
A33: =IF(ARBITRAGES!E33="","",ARBITRAGES!E33) -> 45599 | B33: =IF(W33="","",1-V33/W33) -> 0.94846588 | C33: =IF(A33="","",'Historique détail'!B33/$W33) -> 0.49573051 | D33: =IF(B33="","",'Historique détail'!C33/$W33) -> 0.16756543 | E33: =IF(C33="","",'Historique détail'!D33/$W33) -> 0.061808775 | F33: =IF(D33="","",'Historique détail'!E33/$W33) -> 0.067692172 | G33: =IF(E33="","",'Historique détail'!F33/$W33) -> 0.062505461 | H33: =IF(F33="","",'Historique détail'!G33/$W33) -> 0.021718734 | I33: =IF(G33="","",'Historique détail'!H33/$W33) -> 0.025896353 | J33: =IF(H33="","",'Historique détail'!I33/$W33) -> 0.011555637 | ... T33: =IF(R33="","",'Historique détail'!S33/$W33) -> 0 | U33: =IF(T33="","",V33/W33) -> 0.051534119 | V33: =IF(A33="","",ARBITRAGES!M33) -> 2109.4154 | W33: =IF(V33="","",'Historique détail'!U33) -> 40932.405
A34: =IF(ARBITRAGES!E34="","",ARBITRAGES!E34) -> 45602 | B34: =IF(W34="","",1-V34/W34) -> 0.937351 | C34: =IF(A34="","",'Historique détail'!B34/$W34) -> 0.49489102 | D34: =IF(B34="","",'Historique détail'!C34/$W34) -> 0.16749196 | E34: =IF(C34="","",'Historique détail'!D34/$W34) -> 0.057920789 | F34: =IF(D34="","",'Historique détail'!E34/$W34) -> 0.054397915 | G34: =IF(E34="","",'Historique détail'!F34/$W34) -> 0.069179439 | H34: =IF(F34="","",'Historique détail'!G34/$W34) -> 0.021475099 | I34: =IF(G34="","",'Historique détail'!H34/$W34) -> 0.026725428 | J34: =IF(H34="","",'Historique détail'!I34/$W34) -> 0.011861484 | ... T34: =IF(R34="","",'Historique détail'!S34/$W34) -> 0 | U34: =IF(T34="","",V34/W34) -> 0.062648996 | V34: =IF(A34="","",ARBITRAGES!M34) -> 2829.4154 | W34: =IF(V34="","",'Historique détail'!U34) -> 45162.981
A35: =PRIX!A35 -> 45606 | B35: =IF(W35="","",1-V35/W35) -> 0.93838456 | C35: =IF(A35="","",'Historique détail'!B35/$W35) -> 0.47281899 | D35: =IF(B35="","",'Historique détail'!C35/$W35) -> 0.17961666 | E35: =IF(C35="","",'Historique détail'!D35/$W35) -> 0.060056573 | F35: =IF(D35="","",'Historique détail'!E35/$W35) -> 0.055471872 | G35: =IF(E35="","",'Historique détail'!F35/$W35) -> 0.067920283 | H35: =IF(F35="","",'Historique détail'!G35/$W35) -> 0.023073177 | I35: =IF(G35="","",'Historique détail'!H35/$W35) -> 0.029177538 | J35: =IF(H35="","",'Historique détail'!I35/$W35) -> 0.015556391 | ... T35: =IF(R35="","",'Historique détail'!S35/$W35) -> 0 | U35: =IF(T35="","",V35/W35) -> 0.061615441 | V35: =IF(A35="","",ARBITRAGES!M35) -> 3104.2612 | W35: =IF(V35="","",'Historique détail'!U35) -> 50381.221
A36: =PRIX!A36 -> 45576 | B36: =IF(W36="","",1-V36/W36) -> 0.93466434 | C36: =IF(A36="","",'Historique détail'!B36/$W36) -> 0.4839416 | D36: =IF(B36="","",'Historique détail'!C36/$W36) -> 0.17752222 | E36: =IF(C36="","",'Historique détail'!D36/$W36) -> 0.057230081 | F36: =IF(D36="","",'Historique détail'!E36/$W36) -> 0.054090483 | G36: =IF(E36="","",'Historique détail'!F36/$W36) -> 0.068663398 | H36: =IF(F36="","",'Historique détail'!G36/$W36) -> 0.021192545 | I36: =IF(G36="","",'Historique détail'!H36/$W36) -> 0.027709759 | J36: =IF(H36="","",'Historique détail'!I36/$W36) -> 0.011585138 | ... T36: =IF(R36="","",'Historique détail'!S36/$W36) -> 0 | U36: =IF(T36="","",V36/W36) -> 0.065335662 | V36: =IF(A36="","",ARBITRAGES!M36) -> 3454.2612 | W36: =IF(V36="","",'Historique détail'!U36) -> 52869.461
A37: =PRIX!A37 -> 45608 | B37: =IF(W37="","",1-V37/W37) -> 0.91301268 | C37: =IF(A37="","",'Historique détail'!B37/$W37) -> 0.46589879 | D37: =IF(B37="","",'Historique détail'!C37/$W37) -> 0.17572076 | E37: =IF(C37="","",'Historique détail'!D37/$W37) -> 0.056323664 | F37: =IF(D37="","",'Historique détail'!E37/$W37) -> 0.053953166 | G37: =IF(E37="","",'Historique détail'!F37/$W37) -> 0.066418195 | H37: =IF(F37="","",'Historique détail'!G37/$W37) -> 0.020798175 | I37: =IF(G37="","",'Historique détail'!H37/$W37) -> 0.027670858 | J37: =IF(H37="","",'Historique détail'!I37/$W37) -> 0.01342959 | ... T37: =IF(R37="","",'Historique détail'!S37/$W37) -> 0 | U37: =IF(T37="","",V37/W37) -> 0.086987319 | V37: =IF(A37="","",ARBITRAGES!M37) -> 4715.4656 | W37: =IF(V37="","",'Historique détail'!U37) -> 54208.656
A38: =PRIX!A38 -> 45609 | B38: =IF(W38="","",1-V38/W38) -> 0.92287366 | C38: =IF(A38="","",'Historique détail'!B38/$W38) -> 0.47650808 | D38: =IF(B38="","",'Historique détail'!C38/$W38) -> 0.1727351 | E38: =IF(C38="","",'Historique détail'!D38/$W38) -> 0.055852882 | F38: =IF(D38="","",'Historique détail'!E38/$W38) -> 0.05258658 | G38: =IF(E38="","",'Historique détail'!F38/$W38) -> 0.062503254 | H38: =IF(F38="","",'Historique détail'!G38/$W38) -> 0.019612774 | I38: =IF(G38="","",'Historique détail'!H38/$W38) -> 0.025965088 | J38: =IF(H38="","",'Historique détail'!I38/$W38) -> 0.01293392 | ... T38: =IF(R38="","",'Historique détail'!S38/$W38) -> 0 | U38: =IF(T38="","",V38/W38) -> 0.077126341 | V38: =IF(A38="","",ARBITRAGES!M38) -> 3965.4656 | W38: =IF(V38="","",'Historique détail'!U38) -> 51415.192
A39: =PRIX!A39 -> 45609 | B39: =IF(W39="","",1-V39/W39) -> 0.93395015 | C39: =IF(A39="","",'Historique détail'!B39/$W39) -> 0.47650808 | D39: =IF(B39="","",'Historique détail'!C39/$W39) -> 0.1727351 | E39: =IF(C39="","",'Historique détail'!D39/$W39) -> 0.055852882 | F39: =IF(D39="","",'Historique détail'!E39/$W39) -> 0.05258658 | G39: =IF(E39="","",'Historique détail'!F39/$W39) -> 0.062503254 | H39: =IF(F39="","",'Historique détail'!G39/$W39) -> 0.019612774 | I39: =IF(G39="","",'Historique détail'!H39/$W39) -> 0.025965088 | J39: =IF(H39="","",'Historique détail'!I39/$W39) -> 0.01293392 | ... T39: =IF(R39="","",'Historique détail'!S39/$W39) -> 0 | U39: =IF(T39="","",V39/W39) -> 0.066049848 | V39: =IF(A39="","",ARBITRAGES!M39) -> 3395.9656 | W39: =IF(V39="","",'Historique détail'!U39) -> 51415.192
A40: =PRIX!A40 -> 45609 | B40: =IF(W40="","",1-V40/W40) -> 0.94368463 | C40: =IF(A40="","",'Historique détail'!B40/$W40) -> 0.47650808 | D40: =IF(B40="","",'Historique détail'!C40/$W40) -> 0.1727351 | E40: =IF(C40="","",'Historique détail'!D40/$W40) -> 0.055852882 | F40: =IF(D40="","",'Historique détail'!E40/$W40) -> 0.05258658 | G40: =IF(E40="","",'Historique détail'!F40/$W40) -> 0.062503254 | H40: =IF(F40="","",'Historique détail'!G40/$W40) -> 0.019612774 | I40: =IF(G40="","",'Historique détail'!H40/$W40) -> 0.025965088 | J40: =IF(H40="","",'Historique détail'!I40/$W40) -> 0.01293392 | ... T40: =IF(R40="","",'Historique détail'!S40/$W40) -> 0 | U40: =IF(T40="","",V40/W40) -> 0.056315371 | V40: =IF(A40="","",ARBITRAGES!M40) -> 2895.4656 | W40: =IF(V40="","",'Historique détail'!U40) -> 51415.192
A41: =PRIX!A41 -> 45610 | B41: =IF(W41="","",1-V41/W41) -> 0.97056742 | C41: =IF(A41="","",'Historique détail'!B41/$W41) -> 0.51203835 | D41: =IF(B41="","",'Historique détail'!C41/$W41) -> 0.16388902 | E41: =IF(C41="","",'Historique détail'!D41/$W41) -> 0.056684279 | F41: =IF(D41="","",'Historique détail'!E41/$W41) -> 0.059139495 | G41: =IF(E41="","",'Historique détail'!F41/$W41) -> 0.05525242 | H41: =IF(F41="","",'Historique détail'!G41/$W41) -> 0.018930587 | I41: =IF(G41="","",'Historique détail'!H41/$W41) -> 0.026736167 | J41: =IF(H41="","",'Historique détail'!I41/$W41) -> 0.013319821 | ... T41: =IF(R41="","",'Historique détail'!S41/$W41) -> 0 | U41: =IF(T41="","",V41/W41) -> 0.029432581 | V41: =IF(A41="","",ARBITRAGES!M41) -> 1585.4656 | W41: =IF(V41="","",'Historique détail'!U41) -> 53867.707
A42: =PRIX!A42 -> 45615 | B42: =IF(W42="","",1-V42/W42) -> 0.96357369 | C42: =IF(A42="","",'Historique détail'!B42/$W42) -> 0.51196944 | D42: =IF(B42="","",'Historique détail'!C42/$W42) -> 0.16386696 | E42: =IF(C42="","",'Historique détail'!D42/$W42) -> 0.056676651 | F42: =IF(D42="","",'Historique détail'!E42/$W42) -> 0.059131537 | G42: =IF(E42="","",'Historique détail'!F42/$W42) -> 0.055244985 | H42: =IF(F42="","",'Historique détail'!G42/$W42) -> 0.018928039 | I42: =IF(G42="","",'Historique détail'!H42/$W42) -> 0.026732569 | J42: =IF(H42="","",'Historique détail'!I42/$W42) -> 0.013318028 | ... T42: =IF(R42="","",'Historique détail'!S42/$W42) -> 0 | U42: =IF(T42="","",V42/W42) -> 0.036426306 | V42: =IF(A42="","",ARBITRAGES!M42) -> 1962.4656 | W42: =IF(V42="","",'Historique détail'!U42) -> 53874.957
A43: =PRIX!A43 -> 45618 | B43: =IF(W43="","",1-V43/W43) -> 0.97390044 | C43: =IF(A43="","",'Historique détail'!B43/$W43) -> 0.50065691 | D43: =IF(B43="","",'Historique détail'!C43/$W43) -> 0.16815953 | E43: =IF(C43="","",'Historique détail'!D43/$W43) -> 0.061305176 | F43: =IF(D43="","",'Historique détail'!E43/$W43) -> 0.058624806 | G43: =IF(E43="","",'Historique détail'!F43/$W43) -> 0.054594542 | H43: =IF(F43="","",'Historique détail'!G43/$W43) -> 0.019651596 | I43: =IF(G43="","",'Historique détail'!H43/$W43) -> 0.030861945 | J43: =IF(H43="","",'Historique détail'!I43/$W43) -> 0.014400246 | ... T43: =IF(R43="","",'Historique détail'!S43/$W43) -> 0 | U43: =IF(T43="","",V43/W43) -> 0.026099558 | V43: =IF(A43="","",ARBITRAGES!M43) -> 1522.4656 | W43: =IF(V43="","",'Historique détail'!U43) -> 58333.004
A44: =PRIX!A44 -> 45619 | B44: =IF(W44="","",1-V44/W44) -> 0.97691644 | C44: =IF(A44="","",'Historique détail'!B44/$W44) -> 0.50065691 | D44: =IF(B44="","",'Historique détail'!C44/$W44) -> 0.16815953 | E44: =IF(C44="","",'Historique détail'!D44/$W44) -> 0.061305176 | F44: =IF(D44="","",'Historique détail'!E44/$W44) -> 0.058624806 | G44: =IF(E44="","",'Historique détail'!F44/$W44) -> 0.054594542 | H44: =IF(F44="","",'Historique détail'!G44/$W44) -> 0.019651596 | I44: =IF(G44="","",'Historique détail'!H44/$W44) -> 0.030861945 | J44: =IF(H44="","",'Historique détail'!I44/$W44) -> 0.014400246 | ... T44: =IF(R44="","",'Historique détail'!S44/$W44) -> 0 | U44: =IF(T44="","",V44/W44) -> 0.023083564 | V44: =IF(A44="","",ARBITRAGES!M44) -> 1346.5336 | W44: =IF(V44="","",'Historique détail'!U44) -> 58333.004
A45: =PRIX!A45 -> 45622 | B45: =IF(W45="","",1-V45/W45) -> 0.97916341 | C45: =IF(A45="","",'Historique détail'!B45/$W45) -> 0.50291882 | D45: =IF(B45="","",'Historique détail'!C45/$W45) -> 0.16926326 | E45: =IF(C45="","",'Historique détail'!D45/$W45) -> 0.059868731 | F45: =IF(D45="","",'Historique détail'!E45/$W45) -> 0.054239856 | G45: =IF(E45="","",'Historique détail'!F45/$W45) -> 0.056678685 | H45: =IF(F45="","",'Historique détail'!G45/$W45) -> 0.020662851 | I45: =IF(G45="","",'Historique détail'!H45/$W45) -> 0.031199258 | J45: =IF(H45="","",'Historique détail'!I45/$W45) -> 0.01215605 | ... T45: =IF(R45="","",'Historique détail'!S45/$W45) -> 0 | U45: =IF(T45="","",V45/W45) -> 0.020836593 | V45: =IF(A45="","",ARBITRAGES!M45) -> 1148.8836 | W45: =IF(V45="","",'Historique détail'!U45) -> 55137.786
A46: =PRIX!A46 -> 45630 | B46: =IF(W46="","",1-V46/W46) -> 0.9795491 | C46: =IF(A46="","",'Historique détail'!B46/$W46) -> 0.46309787 | D46: =IF(B46="","",'Historique détail'!C46/$W46) -> 0.17059245 | E46: =IF(C46="","",'Historique détail'!D46/$W46) -> 0.063563638 | F46: =IF(D46="","",'Historique détail'!E46/$W46) -> 0.050798623 | G46: =IF(E46="","",'Historique détail'!F46/$W46) -> 0.067814454 | H46: =IF(F46="","",'Historique détail'!G46/$W46) -> 0.026899832 | I46: =IF(G46="","",'Historique détail'!H46/$W46) -> 0.040838471 | J46: =IF(H46="","",'Historique détail'!I46/$W46) -> 0.011957311 | ... T46: =IF(R46="","",'Historique détail'!S46/$W46) -> 0 | U46: =IF(T46="","",V46/W46) -> 0.020450898 | V46: =IF(A46="","",ARBITRAGES!M46) -> 1257.1936 | W46: =IF(V46="","",'Historique détail'!U46) -> 61473.762
... A73: =PRIX!A73 -> 45779 | B73: =IF(W73="","",1-V73/W73) -> 0.94222632 | C73: =IF(A73="","",'Historique détail'!B73/$W73) -> 0.5323069 | D73: =IF(B73="","",'Historique détail'!C73/$W73) -> 0.12510944 | E73: =IF(C73="","",'Historique détail'!D73/$W73) -> 0.032657522 | F73: =IF(D73="","",'Historique détail'!E73/$W73) -> 0.066584789 | G73: =IF(E73="","",'Historique détail'!F73/$W73) -> 0.068074828 | H73: =IF(F73="","",'Historique détail'!G73/$W73) -> 0.0047457241 | I73: =IF(G73="","",'Historique détail'!H73/$W73) -> 0.033985952 | J73: =IF(H73="","",'Historique détail'!I73/$W73) -> 0.011417394 | ... T73: =IF(R73="","",'Historique détail'!S73/$W73) -> 0.0028896355 | U73: =IF(T73="","",V73/W73) -> 0.057773678 | V73: =IF(A73="","",ARBITRAGES!M73) -> 2551.1596 | W73: =IF(V73="","",'Historique détail'!U73) -> 44157.819
A74: =PRIX!A75 -> 45785 | B74: =IF(W74="","",1-V74/W74) -> 0.90537349 | C74: =IF(A74="","",'Historique détail'!B74/$W74) -> 0.46872165 | D74: =IF(B74="","",'Historique détail'!C74/$W74) -> 0.15009778 | E74: =IF(C74="","",'Historique détail'!D74/$W74) -> 0.02909135 | F74: =IF(D74="","",'Historique détail'!E74/$W74) -> 0.065185255 | G74: =IF(E74="","",'Historique détail'!F74/$W74) -> 0.088205261 | H74: =IF(F74="","",'Historique détail'!G74/$W74) -> 0.0046630554 | I74: =IF(G74="","",'Historique détail'!H74/$W74) -> 0.031705884 | J74: =IF(H74="","",'Historique détail'!I74/$W74) -> 0.0012759511 | ... T74: =IF(R74="","",'Historique détail'!S74/$W74) -> 0.0024960871 | U74: =IF(T74="","",V74/W74) -> 0.094626512 | V74: =IF(A74="","",ARBITRAGES!M75) -> 4837.3083 | W74: =IF(V74="","",'Historique détail'!U74) -> 51120.011
A75: =PRIX!A76 -> 45054 | B75: =IF(W75="","",1-V75/W75) -> 0.90098933 | C75: =IF(A75="","",'Historique détail'!B75/$W75) -> 0.46886679 | D75: =IF(B75="","",'Historique détail'!C75/$W75) -> 0.15014425 | E75: =IF(C75="","",'Historique détail'!D75/$W75) -> 0.029100358 | F75: =IF(D75="","",'Historique détail'!E75/$W75) -> 0.065205439 | G75: =IF(E75="","",'Historique détail'!F75/$W75) -> 0.088232572 | H75: =IF(F75="","",'Historique détail'!G75/$W75) -> 0 | I75: =IF(G75="","",'Historique détail'!H75/$W75) -> 0.031715701 | J75: =IF(H75="","",'Historique détail'!I75/$W75) -> 0.0012763461 | ... T75: =IF(R75="","",'Historique détail'!S75/$W75) -> 0.00249686 | U75: =IF(T75="","",V75/W75) -> 0.099010675 | V75: =IF(A75="","",ARBITRAGES!M76) -> 5059.86 | W75: =IF(V75="","",'Historique détail'!U75) -> 51104.187
A76: =PRIX!A77 -> 45786 | B76: =IF(W76="","",1-V76/W76) -> 0.89258466 | C76: =IF(A76="","",'Historique détail'!B76/$W76) -> 0.46847867 | D76: =IF(B76="","",'Historique détail'!C76/$W76) -> 0.15070845 | E76: =IF(C76="","",'Historique détail'!D76/$W76) -> 0.029124305 | F76: =IF(D76="","",'Historique détail'!E76/$W76) -> 0.065259098 | G76: =IF(E76="","",'Historique détail'!F76/$W76) -> 0.079492394 | H76: =IF(F76="","",'Historique détail'!G76/$W76) -> 0 | I76: =IF(G76="","",'Historique détail'!H76/$W76) -> 0.031741801 | J76: =IF(H76="","",'Historique détail'!I76/$W76) -> 0.0012773965 | ... T76: =IF(R76="","",'Historique détail'!S76/$W76) -> 0.0024989147 | U76: =IF(T76="","",V76/W76) -> 0.10741534 | V76: =IF(A76="","",ARBITRAGES!M77) -> 5484.86 | W76: =IF(V76="","",'Historique détail'!U76) -> 51062.167
A77: =PRIX!A78 -> 45789 | B77: =IF(W77="","",1-V77/W77) -> 0.89146548 | C77: =IF(A77="","",'Historique détail'!B77/$W77) -> 0.45515915 | D77: =IF(B77="","",'Historique détail'!C77/$W77) -> 0.14863746 | E77: =IF(C77="","",'Historique détail'!D77/$W77) -> 0.024935091 | F77: =IF(D77="","",'Historique détail'!E77/$W77) -> 0.06518818 | G77: =IF(E77="","",'Historique détail'!F77/$W77) -> 0.080456901 | H77: =IF(F77="","",'Historique détail'!G77/$W77) -> 0 | I77: =IF(G77="","",'Historique détail'!H77/$W77) -> 0.033164641 | J77: =IF(H77="","",'Historique détail'!I77/$W77) -> 0.014505437 | ... T77: =IF(R77="","",'Historique détail'!S77/$W77) -> 0.0027495263 | U77: =IF(T77="","",V77/W77) -> 0.10853452 | V77: =IF(A77="","",ARBITRAGES!M78) -> 5731.61 | W77: =IF(V77="","",'Historique détail'!U77) -> 52809.097
A78: =PRIX!A79 -> 45790 | B78: =IF(W78="","",1-V78/W78) -> 0.91845217 | C78: =IF(A78="","",'Historique détail'!B78/$W78) -> 0.48604106 | D78: =IF(B78="","",'Historique détail'!C78/$W78) -> 0.14830085 | E78: =IF(C78="","",'Historique détail'!D78/$W78) -> 0.023926126 | F78: =IF(D78="","",'Historique détail'!E78/$W78) -> 0.066341363 | G78: =IF(E78="","",'Historique détail'!F78/$W78) -> 0.080138057 | H78: =IF(F78="","",'Historique détail'!G78/$W78) -> 0 | I78: =IF(G78="","",'Historique détail'!H78/$W78) -> 0.031822679 | J78: =IF(H78="","",'Historique détail'!I78/$W78) -> 0.01363257 | ... T78: =IF(R78="","",'Historique détail'!S78/$W78) -> 0.0026370591 | U78: =IF(T78="","",V78/W78) -> 0.081547835 | V78: =IF(A78="","",ARBITRAGES!M79) -> 4231.61 | W78: =IF(V78="","",'Historique détail'!U78) -> 51891.139
A79: =PRIX!A80 -> 45808 | B79: =IF(W79="","",1-V79/W79) -> 0.92563893 | C79: =IF(A79="","",'Historique détail'!B79/$W79) -> 0.49673485 | D79: =IF(B79="","",'Historique détail'!C79/$W79) -> 0.15459501 | E79: =IF(C79="","",'Historique détail'!D79/$W79) -> 0.024082052 | F79: =IF(D79="","",'Historique détail'!E79/$W79) -> 0.06005231 | G79: =IF(E79="","",'Historique détail'!F79/$W79) -> 0.080672125 | H79: =IF(F79="","",'Historique détail'!G79/$W79) -> 0 | I79: =IF(G79="","",'Historique détail'!H79/$W79) -> 0.028580674 | J79: =IF(H79="","",'Historique détail'!I79/$W79) -> 0.011170834 | ... T79: =IF(R79="","",'Historique détail'!S79/$W79) -> 0.0026950792 | U79: =IF(T79="","",V79/W79) -> 0.074361065 | V79: =IF(A79="","",ARBITRAGES!M80) -> 3775.61 | W79: =IF(V79="","",'Historique détail'!U79) -> 50774.018
A80: =PRIX!A81 -> 45817 | B80: =IF(W80="","",1-V80/W80) -> 0.88955951 | C80: =IF(A80="","",'Historique détail'!B80/$W80) -> 0.46094197 | D80: =IF(B80="","",'Historique détail'!C80/$W80) -> 0.15478057 | E80: =IF(C80="","",'Historique détail'!D80/$W80) -> 0.023331987 | F80: =IF(D80="","",'Historique détail'!E80/$W80) -> 0.05861589 | G80: =IF(E80="","",'Historique détail'!F80/$W80) -> 0.083909966 | H80: =IF(F80="","",'Historique détail'!G80/$W80) -> 0 | I80: =IF(G80="","",'Historique détail'!H80/$W80) -> 0.027957162 | J80: =IF(H80="","",'Historique détail'!I80/$W80) -> 0.01173655 | ... T80: =IF(R80="","",'Historique détail'!S80/$W80) -> 0.0019666168 | U80: =IF(T80="","",V80/W80) -> 0.11044049 | V80: =IF(A80="","",ARBITRAGES!M81) -> 5930.2432 | W80: =IF(V80="","",'Historique détail'!U80) -> 53696.276
A81: =PRIX!A82 -> 45817 | B81: =IF(W81="","",1-V81/W81) -> 0.83823627 | C81: =IF(A81="","",'Historique détail'!B81/$W81) -> 0.40953311 | D81: =IF(B81="","",'Historique détail'!C81/$W81) -> 0.15482254 | E81: =IF(C81="","",'Historique détail'!D81/$W81) -> 0.023320889 | F81: =IF(D81="","",'Historique détail'!E81/$W81) -> 0.058714308 | G81: =IF(E81="","",'Historique détail'!F81/$W81) -> 0.083870055 | H81: =IF(F81="","",'Historique détail'!G81/$W81) -> 0 | I81: =IF(G81="","",'Historique détail'!H81/$W81) -> 0.027943865 | J81: =IF(H81="","",'Historique détail'!I81/$W81) -> 0.011732959 | ... T81: =IF(R81="","",'Historique détail'!S81/$W81) -> 0.0019656814 | U81: =IF(T81="","",V81/W81) -> 0.16176373 | V81: =IF(A81="","",ARBITRAGES!M82) -> 8690.2432 | W81: =IF(V81="","",'Historique détail'!U81) -> 53721.829
A82: =PRIX!A83 -> 45818 | B82: =IF(W82="","",1-V82/W82) -> 0.86306284 | C82: =IF(A82="","",'Historique détail'!B82/$W82) -> 0.43197332 | D82: =IF(B82="","",'Historique détail'!C82/$W82) -> 0.15696994 | E82: =IF(C82="","",'Historique détail'!D82/$W82) -> 0.023214455 | F82: =IF(D82="","",'Historique détail'!E82/$W82) -> 0.058446341 | G82: =IF(E82="","",'Historique détail'!F82/$W82) -> 0.083487279 | H82: =IF(F82="","",'Historique détail'!G82/$W82) -> 0 | I82: =IF(G82="","",'Historique détail'!H82/$W82) -> 0.027816331 | J82: =IF(H82="","",'Historique détail'!I82/$W82) -> 0.011679411 | ... T82: =IF(R82="","",'Historique détail'!S82/$W82) -> 0.0019567102 | U82: =IF(T82="","",V82/W82) -> 0.13693716 | V82: =IF(A82="","",ARBITRAGES!M83) -> 7390.2432 | W82: =IF(V82="","",'Historique détail'!U82) -> 53968.134
A83: =PRIX!A84 -> 45831 | B83: =IF(W83="","",1-V83/W83) -> 0.86085548 | C83: =IF(A83="","",'Historique détail'!B83/$W83) -> 0.44711497 | D83: =IF(B83="","",'Historique détail'!C83/$W83) -> 0.15940659 | E83: =IF(C83="","",'Historique détail'!D83/$W83) -> 0.022463872 | F83: =IF(D83="","",'Historique détail'!E83/$W83) -> 0.056892427 | G83: =IF(E83="","",'Historique détail'!F83/$W83) -> 0.075408181 | H83: =IF(F83="","",'Historique détail'!G83/$W83) -> 0 | I83: =IF(G83="","",'Historique détail'!H83/$W83) -> 0.027885969 | J83: =IF(H83="","",'Historique détail'!I83/$W83) -> 0.009659636 | ... T83: =IF(R83="","",'Historique détail'!S83/$W83) -> 0.0016638646 | U83: =IF(T83="","",V83/W83) -> 0.13914452 | V83: =IF(A83="","",ARBITRAGES!M84) -> 6991.2432 | W83: =IF(V83="","",'Historique détail'!U83) -> 50244.473
A84: =PRIX!A85 -> 45831 | B84: =IF(W84="","",1-V84/W84) -> 0.8580691 | C84: =IF(A84="","",'Historique détail'!B84/$W84) -> 0.44711497 | D84: =IF(B84="","",'Historique détail'!C84/$W84) -> 0.15940659 | E84: =IF(C84="","",'Historique détail'!D84/$W84) -> 0.022463872 | F84: =IF(D84="","",'Historique détail'!E84/$W84) -> 0.056892427 | G84: =IF(E84="","",'Historique détail'!F84/$W84) -> 0.075408181 | H84: =IF(F84="","",'Historique détail'!G84/$W84) -> 0 | I84: =IF(G84="","",'Historique détail'!H84/$W84) -> 0.027885969 | J84: =IF(H84="","",'Historique détail'!I84/$W84) -> 0.009659636 | ... T84: =IF(R84="","",'Historique détail'!S84/$W84) -> 0.0016638646 | U84: =IF(T84="","",V84/W84) -> 0.1419309 | V84: =IF(A84="","",ARBITRAGES!M85) -> 7131.2432 | W84: =IF(V84="","",'Historique détail'!U84) -> 50244.473
